Workbook

Sheet README
A1: Scheduling — pitch, adoption and retention (v3, validated 04/08/26)
A4: Version | B4: v3 — 04/08/26. Pitch window widened to all months (median conversion lag is 35 days, so a single-month window understates). Adoption sheets rebuilt on 178 LEGITIMATE locations after removing 237 is_test and 29 is_active=FALSE entities. Payments date-filtered to post-launch. Pitch register screened for test entities: zero contamination.
A5: Definitions contract | B5: docs/scheduling-metric-definitions.md — every term here has one meaning. Read it before quoting anything.
A6: As-of date | B6: 03/08/26. Launch date 30/01/26. All trailing-window tests run off the as-of cell on Summary.
A7: Source | B7: Aurora via Metabase DB 7 — scheduling.*, chargebee.*, sales.fireflies_meeting, gbp.*, entities.*
A9: HEADLINE
A10: Accounts pitched (Nov 25 - Aug 26) | B10: 148 (133 still active)
A11: …reached scheduling enabled | B11: 23 onboarded to enabled; 23 taking bookings; median 35-day lag
A12: …never started onboarding | B12: 50 (79%)
A13: Legitimate locations in adoption sheets | B13: 178 (raw table holds 446; 237 are is_test, 29 inactive, 4 unverifiable)
A14: Locations enabled (config flag) | B14: 140
A15: Locations still booking in last 30d | B15: 112
A16: Value processed through scheduling | B16: $249,919 across the 178 legitimate locations; $328,021 platform-wide post-launch
A17: Customer-made bookings since launch | B17: 4,627 — zero pre-launch contamination; the cleanest proof the product works
A19: WHAT V1 GOT WRONG
A20: Pitch count 98 → 63 | B20: The offer regex had no word boundary, so 'our booking platform' also matched 'y-OUR booking platform'. Reps discussing the customer's EXISTING system were counted as Zoca pitches — 55% false positives on a 22-call sample. Fixed with \mour.
A21: Conversion 15 → 8 | B21: Same cause, plus counting per Chargebee customer record. 2,026 records hold 1,799 distinct emails; 89 emails map to multiple records. v2 resolves to entity_id.
A22: Native bookings 23,019 → 9,605 | B22: 'migration_source IS NULL' does NOT mean earned on Zoca. 33 entities had history imported with no migration tag; 13,266 bookings predated launch. v2 counts only bookings created between 30/01/26 and the as-of date.
A23: 'Ever booked' 279 vs 286 | B23: v1 gave the same label to two different populations on two sheets (one conditioned on the enabled flag, one not). v2 uses 'Operationally live' everywhere and the sheets reconcile exactly.
A24: Cohort footnote | B24: v1 claimed 'every settled cohort lands at 20-25%'. Only one of six cohorts did. Removed.
A26: DEFINITIONS THAT MATTER MOST
A27: Earned booking | B27: migration_source IS NULL AND created_at between 30/01/26 and the as-of date. Excludes untagged imported history and 351 future-dated rows.
A28: Customer-made booking | B28: Earned AND created_by_type in ('EC','CLIENT'). The figure that proves demand.
A29: Enabled (flag) | B29: is_scheduling_enabled = TRUE. A CONFIGURATION flag and it is unreliable — 7 locations took real bookings while flagged FALSE. Use for setup progress only.
A30: Operationally live | B30: Has at least one earned booking, regardless of the flag. Use this for 'is it actually being used'.
A31: Live in last 30d | B31: Most recent EARNED booking within 30 days of the as-of date.
A32: Location vs account | B32: 444 locations map to 270 Chargebee customers of any status and 156 active ones. Never quote 444 as an account count.
A34: COVERAGE LIMITS — STATE THESE WITH THE NUMBER
A35: 63 is a floor | B35: Only accounts whose call attendee email matches a Chargebee customer are counted; roughly half of external emails match.
A36: Prospects excluded | B36: Pitched emails matching no customer record are new-business pitches, not upsells, and are out of scope.
A37: Attribution is temporal | B37: An onboarding record created after the call is attributed to the pitch. Reasonable in a one-month window; not proven.
A38: Live data | B38: Aurora is queried live and grew during this session. Figures are as at 03/08/26.
A40: SHEET GUIDE
A41: Summary | B41: Headline metrics, all calculated
A42: July Pitch Funnel | B42: 1,051 calls narrowed to 63 pitched accounts
A43: Pitched Accounts | B43: 74 rows = 63 pitched + 11 already-live (flagged col H). Column F links to the call.
A44: Adoption Funnel | B44: All 444 locations, stage by stage
A45: Locations | B45: Per-location detail, business name in column B
A46: Cohort Retention | B46: Monthly cohorts — same definitions as Adoption Funnel, so totals reconcile
A47: Bookings and Revenue | B47: Earned vs pre-launch vs migrated, payments, incumbents
A48: Objection Themes | B48: Why accounts did not convert
A49: Data Quality | B49: Defects found in the source data itself — read before trusting any booking count
A51: QC 04/08/26 | B51: Third instance of the same root cause found and fixed: pre-launch rows inside scheduling.* tables. Payments now filtered to created_at >= 30/01/26. All-time completed payments are $646,104, of which $318,083 predate the launch. Post-launch value is $328,021. Bookings were already corrected for this; payments were not, until now.
A53: VALIDATION REGISTER (04/08/26)
A54: VALIDATED — 13 onboarded accounts | B54: Every booking, customer-made and 30-day figure recomputed from raw booking rows in Python, independent of the SQL that built the sheet. 13/13 accounts match exactly, 45/45 rows. Zero mismatches.
A55: VALIDATED — core funnel | B55: 63 pitched · 13 onboarded · 8 enabled · 444 locations · 368 enabled · 286 operationally live · 147 live-30d. Recomputed two ways; 132 formulas structurally checked; cohort rows partition all 444; Cohort TOTAL reconciles to Adoption Funnel.
A56: VALIDATED — competitor counts | B56: Vagaro 105 and Acuity 26 confirmed clean under word boundaries.
A57: CORRECTED — Square count | B57: 269 -> 101. The unbounded pattern matched non-product uses of the word.
A58: CORRECTED — payments scope | B58: All-time $646,104 included $318,083 created before the 30/01/26 launch. Post-launch value is $328,021. Every payment figure now date-filtered.
A59: CORRECTED — onboarding definition | B59: The 'onboarded successfully' label wrongly claimed to be the company's definition. Card 3778 uses a different rule entirely (see Pitch to Performance).
A60: STILL UNVERIFIED — objection themes | B60: The seven topic counts (deferred, migration effort, price, etc.) were not individually re-audited. Directional only; never present per-account.
A61: STILL UNVERIFIED — migration source table | B61: Hardcoded from v1, not re-queried.
A62: STILL UNVERIFIED — business names | B62: 89% coverage from a four-source fallback; not cross-checked against the dashboard's Locations->Name.
A63: INHERENT LIMIT — the 63 | B63: Rests on ~53% email-match coverage between call attendees and Chargebee customers. It is a floor and cannot be validated upward from this data.

Sheet Summary
A1: Summary — v2 corrected
A3: As-of date (drives every trailing-window test) | B3: =DATE(2026,8,3) | C3: Blue = input. Change this one cell to re-date the whole workbook.
A5: PITCH — ALL MONTHS (Nov 25 – Aug 26) | B5: Value | C5: Definition / note
A6: Accounts pitched (all months) | B6: =COUNTA('Pitch Register'!$A$16:$A$163) | C6: Offer made, not already live when pitched. All months Nov 25 - Aug 26.
A7: …started onboarding after the pitch | B7: =SUMPRODUCT(--('Pitch Register'!$E$16:$E$163<>"")) | C7: Median 35 days after the pitch; 16 of 31 took over 30 days
A8: …reached Enabled (flag) | B8: =SUMPRODUCT(--('Pitch Register'!$G$16:$G$163=TRUE)) | C8: The conversion number
A9: …operationally live (has earned bookings) | B9: =SUMPRODUCT(--('Pitch Register'!$I$16:$I$163>0)) | C9: Actually taking bookings
A10: …never started onboarding | B10: =SUMPRODUCT(--('Pitch Register'!$E$16:$E$163=""))
A11: Pitch-to-activation rate | B11: =B8/B6 | C11: Enabled ÷ pitched
A12: Excluded — already live at pitch | B12: 25 | C12: Static: excluded by construction, not present in the Pitch Register
A14: ADOPTION — 178 LEGITIMATE LOCATIONS | B14: Value | C14: Definition / note
A15: Locations entered onboarding | B15: =COUNTA(Locations!$A$2:$A$445) | C15: LOCATIONS, not accounts
A16: Enabled (config flag) | B16: =SUMPRODUCT(--(Locations!$M$2:$M$445=TRUE)) | C16: Setup progress only — flag is unreliable
A17: Operationally live (≥1 earned booking) | B17: =SUMPRODUCT(--(Locations!$X$2:$X$445=TRUE)) | C17: The honest 'is it used' measure
A18: Live in last 30 days | B18: =SUMPRODUCT(--(Locations!$W$2:$W$445>=$B$3-30)) | C18: Most recent EARNED booking within 30d
A19: Dormant (live once, not in last 30d) | B19: =B16-B17 | C19: The core finding
A20: Dormant share of operationally live | B20: =B18/B16
A21: Payments configured | B21: =SUMPRODUCT(--(Locations!$J$2:$J$445=TRUE))
A22: Payments explicitly skipped | B22: =SUMPRODUCT(--(Locations!$K$2:$K$445=TRUE)) | C22: The single biggest structural break
A23: Locations linked to a billed account | B23: =SUMPRODUCT(--(Locations!$AB$2:$AB$445<>"")) | C23: 444 locations ≠ 444 accounts
A25: VALUE AND VOLUME | B25: Value | C25: Definition / note
A26: Earned bookings since launch | B26: =SUM(Locations!$O$2:$O$445) | C26: Excludes untagged pre-launch history and future-dated
A27: Customer-made bookings | B27: =SUM(Locations!$P$2:$P$445) | C27: Zero pre-launch contamination — the cleanest proof of demand
A28: Staff-made bookings | B28: =SUM(Locations!$Q$2:$Q$445)
A29: Pre-launch untagged (EXCLUDED) | B29: =SUM(Locations!$R$2:$R$445) | C29: Imported history with no migration_source tag — v1 counted these as organic
A30: Tagged migration (EXCLUDED) | B30: =SUM(Locations!$S$2:$S$445) | C30: Square, Vagaro, Fresha, Booksy, GlossGenius, Acuity, Setmore, GoDaddy
A31: Value processed (USD) | B31: =SUM(Locations!$AA$2:$AA$445) | C31: POST-LAUNCH only (created >= 30/01/26). All-time incl. pre-launch history is $646,104 — not product value.
A32: Locations that processed a payment | B32: =SUMPRODUCT(--(Locations!$Z$2:$Z$445>0))

Sheet Pitch Register
A1: Pitch register — every recorded pitch, Nov 2025 to Aug 2026
A2: One row per account, dated by its FIRST recorded pitch. Conversion takes a median of 35 days, so recent months are still maturing — do not judge a pitch month before ~90 days.
A4: Accounts PITCHED | B4: 148 | C4: Offer made on a recorded call; not already using scheduling
A5: …onboarded after the pitch | B5: 31 | C5: Median 35 days later — 16 of 31 took over 30 days
A6: …reached enabled | B6: 23 | C6: Scheduling switched on
A7: …taking bookings | B7: 23 | C7: Actually receiving bookings — the real conversion
A8: …live in last 30 days | B8: 22 | C8: Still receiving bookings now
A9: NEVER onboarded | B9: 117 | C9: 15 of these have since churned; none of the 15 ever converted
A10: Excluded — already live when pitched | B10: 25 | C10: Offer language to an existing user = support, not a pitch
A11: Bookings from converted accounts | B11: 1584 | C11: Total taken by the 31 that onboarded
A12: …customer-made | B12: 407 | C12: Booked by the end customer, not staff
A13: Payments post-launch, converted | B13: 194993.61 | C13: Processed by those accounts since 30/01/26
A15: Business | B15: Contact | C15: Pitch month | D15: First pitched | E15: Onboarded | F15: Days pitch→onboard | G15: Enabled | H15: Payments set | I15: Earned bookings | J15: Customer-made | K15: Last booking | L15: Payments (USD) | M15: Outcome | N15: Pitch call | O15: Account still active
A16: Deka Lash | B16: amaiti@dekalash.com | C16: 2025-11 | D16: 45989 | G16: FALSE | H16: FALSE | I16: 0 | J16: 0 | L16: 0 | M16: Never onboarded | N16: Follow-up Call X Zoca | O16: TRUE
A17: All Aesthetics Kare | B17: info@allaestheticskare.com | C17: 2025-11 | D17: 45972 | G17: FALSE | H17: FALSE | I17: 0 | J17: 0 | L17: 0 | M17: Never onboarded | N17: Yarira Preston and Shipra Shreya from ZOCA | O17: TRUE
A18: Headquarters Hair Care | B18: kdpitman40@hotmail.com | C18: 2025-12 | D18: 46022 | E18: 46204 | F18: 182 | G18: FALSE | H18: FALSE | I18: 149 | J18: 0 | K18: 46235 | L18: 0 | M18: Booking | N18: Headquarters Hair Care X Zoca | Check In Dece | O18: TRUE
A19: Niks Lash NYC | B19: bandanasewa9@gmail.com | C19: 2025-12 | D19: 45993 | G19: FALSE | H19: FALSE | I19: 0 | J19: 0 | L19: 0 | M19: Never onboarded | N19: Bandana Sewa X Zoca | Check In December | O19: TRUE
A20: Urban Shave | B20: urbanshavellc@gmail.com | C20: 2025-12 | D20: 46000 | G20: FALSE | H20: FALSE | I20: 0 | J20: 0 | L20: 0 | M20: Never onboarded | N20: Urban Shave X Zoca | Check In December | O20: TRUE
A21: Sumathy Reddy, M.D. | B21: sumathyreddy@mail.com | C21: 2025-12 | D21: 46001 | G21: FALSE | H21: FALSE | I21: 0 | J21: 0 | L21: 0 | M21: Never onboarded | N21: Zoca Check-in | Sumathy Reddy, M.D. | O21: FALSE
A22: Hydra-Bar Salon | B22: info@hydrabarsalon.com | C22: 2025-12 | D22: 45994 | G22: FALSE | H22: FALSE | I22: 0 | J22: 0 | L22: 0 | M22: Never onboarded | N22: Hydra Bar X Zoca | Check In December | O22: TRUE
A23: Elva Medical Aesthetics | B23: elvabeautyy@gmail.com | C23: 2025-12 | D23: 45993 | G23: FALSE | H23: FALSE | I23: 0 | J23: 0 | L23: 0 | M23: Never onboarded | N23: Elva Beauty Inc. X Zoca | Check In December | O23: TRUE
A24: Les Ciseaux Salon and Spa | B24: lesciseaux@gmail.com | C24: 2025-12 | D24: 45994 | G24: FALSE | H24: FALSE | I24: 0 | J24: 0 | L24: 0 | M24: Never onboarded | N24: Les Ciseaux Salon & Spa X Zoca | Check In Nov | O24: TRUE
A25: Beverly Dentistry | B25: beverlydental1@gmail.com | C25: 2025-12 | D25: 46010 | G25: FALSE | H25: FALSE | I25: 0 | J25: 0 | L25: 0 | M25: Never onboarded | N25: Beverly Gonzales and Bikash Chandra | O25: TRUE
A26: VPRO Beauty Salon & Spa | B26: vprospa@gmail.com | C26: 2025-12 | D26: 46017 | G26: FALSE | H26: FALSE | I26: 0 | J26: 0 | L26: 0 | M26: Never onboarded | N26: VPRO Beauty Salon & Spa X Zoca | Check In Dec | O26: TRUE
A27: Mad Men Groom-In Room | B27: alvis.hamilton72@yahoo.com | C27: 2025-12 | D27: 46002 | G27: FALSE | H27: FALSE | I27: 0 | J27: 0 | L27: 0 | M27: Never onboarded | N27: Alvis and Kanak Sharma | O27: TRUE
A28: Donna Skin and Body Care | B28: donna.skin@gmail.com | C28: 2026-01 | D28: 46034 | E28: 46169 | F28: 135 | G28: TRUE | H28: TRUE | I28: 105 | J28: 6 | K28: 46237 | L28: 0 | M28: Booking | N28: Donna Skin and Body Care X Zoca | Check In Ja | O28: TRUE
A29: Adel braids | B29: adelbih76@gmail.com | C29: 2026-01 | D29: 46049 | E29: 46066 | F29: 17 | G29: TRUE | H29: TRUE | I29: 19 | J29: 17 | K29: 46220 | L29: 396 | M29: Booking | N29: Zoca X Adel Braids | O29: TRUE
A30: Michael's Salon | B30: baturov11@gmail.com | C30: 2026-01 | D30: 46042 | E30: 46223 | F30: 181 | G30: TRUE | H30: FALSE | I30: 1 | J30: 1 | K30: 46235 | L30: 0 | M30: Booking | N30: Irina Khaimova and Hubern | O30: TRUE
A31: BB Meme Salon Hillcrest | B31: bbmemesalon@gmail.com | C31: 2026-01 | D31: 46034 | E31: 46224 | F31: 190 | G31: TRUE | H31: FALSE | I31: 0 | J31: 0 | L31: 0 | M31: Enabled, no bookings | N31: bbmeme and Shikha | O31: TRUE
A32: Sugar Me Waxing Studio | B32: smwstudio@gmail.com | C32: 2026-01 | D32: 46037 | G32: FALSE | H32: FALSE | I32: 0 | J32: 0 | L32: 0 | M32: Never onboarded | N32: Sugar Me Waxing Studio X Zoca | Check In Janu | O32: TRUE
A33: IM=X Pilates and Fitness Mansfield | B33: michelle@imxpilates.com | C33: 2026-01 | D33: 46052 | G33: FALSE | H33: FALSE | I33: 0 | J33: 0 | L33: 0 | M33: Never onboarded | N33: IM=X Pilates and Fitness Mansfield X Zoca | C | O33: TRUE
A34: Rosy Tips Nail Salon Chula Vista CA | B34: rosytipsnailsnspa@gmail.com | C34: 2026-01 | D34: 46042 | G34: FALSE | H34: FALSE | I34: 0 | J34: 0 | L34: 0 | M34: Never onboarded | N34: Linh Nguyen and Shikha | O34: TRUE
A35: Lashes & Body on Fleek LLC | B35: lashesonfleekllc@gmail.com | C35: 2026-01 | D35: 46031 | G35: FALSE | H35: FALSE | I35: 0 | J35: 0 | L35: 0 | M35: Never onboarded | N35: Founder Connect |Lashes & Body on Fleek LLC | O35: TRUE
A36: The Wow Studio | B36: info@thewowstudio.net | C36: 2026-01 | D36: 46048 | G36: FALSE | H36: FALSE | I36: 0 | J36: 0 | L36: 0 | M36: Never onboarded | N36: The WOW Studio X ZOCA | Check-in Call | O36: TRUE
A37: InVein Aesthetics | B37: shawnta@inveinspa.com | C37: 2026-01 | D37: 46030 | G37: FALSE | H37: FALSE | I37: 0 | J37: 0 | L37: 0 | M37: Never onboarded | N37: Shawnta <> Check - in | O37: TRUE
A38: Bella Luna - Lash and Brow Boutique | B38: threadingbylinet@yahoo.com | C38: 2026-01 | D38: 46041 | G38: FALSE | H38: FALSE | I38: 0 | J38: 0 | L38: 0 | M38: Never onboarded | N38: Linet Haratunian and Shikha | O38: TRUE
A39: Lash and Skin Studio | B39: erica.business14@gmail.com | C39: 2026-01 | D39: 46042 | G39: FALSE | H39: FALSE | I39: 0 | J39: 0 | L39: 0 | M39: Never onboarded | N39: Check in Call X Lash and skin studio | O39: TRUE
A40: ConcreteWood Studio | B40: junjie.du1010@gmail.com | C40: 2026-01 | D40: 46052 | G40: FALSE | H40: FALSE | I40: 0 | J40: 0 | L40: 0 | M40: Never onboarded | N40: Jun jie du and Atharv Yadav | O40: FALSE
A41: Lash Wonderland | Eyelash | Facial | Brow | Lash Lift | B41: lashwonderlandnyc@gmail.com | C41: 2026-01 | D41: 46042 | G41: FALSE | H41: FALSE | I41: 0 | J41: 0 | L41: 0 | M41: Never onboarded | N41: sophie and Shikha | O41: FALSE
A42: Emporio African Braids | B42: ayanniyitemitope10@gmail.com | C42: 2026-02 | D42: 46063 | E42: 46065 | F42: 2 | G42: TRUE | H42: TRUE | I42: 67 | J42: 57 | K42: 46237 | L42: 1803.6 | M42: Booking | N42: Temmy <> Check - in | O42: TRUE
A43: Miracle hands braiding Studio | B43: andrianaowu47@gmail.com | C43: 2026-02 | D43: 46059 | E43: 46077 | F43: 18 | G43: TRUE | H43: FALSE | I43: 52 | J43: 33 | K43: 46237 | L43: 0 | M43: Booking | N43: User Research <> Zoca | O43: TRUE
A44: RCs Waxing & Threading Stockbridge | B44: biznessoffersga@gmail.com | C44: 2026-02 | D44: 46072 | E44: 46197 | F44: 125 | G44: TRUE | H44: FALSE | I44: 25 | J44: 25 | K44: 46237 | L44: 85 | M44: Booking | N44: Riyaz <> Zoca | O44: TRUE
A45: Bodies-N-Motion LLC | B45: bodies.n.motionllc@gmail.com | C45: 2026-02 | D45: 46065 | E45: 46182 | F45: 117 | G45: TRUE | H45: TRUE | I45: 2 | J45: 2 | K45: 46185 | L45: 210 | M45: Booking | N45: bodies n motion llc | O45: TRUE
A46: Connected Health Plano | B46: plano@connectedhealthcenter.com | C46: 2026-02 | D46: 46063 | E46: 46226 | F46: 163 | G46: FALSE | H46: FALSE | I46: 2 | J46: 2 | K46: 46234 | L46: 0 | M46: Booking | N46: Connected Health Plano <> Zoca | O46: TRUE
A47: Vita Aesthetics & Wellness | B47: nick@montesmedical.com | C47: 2026-02 | D47: 46073 | G47: FALSE | H47: FALSE | I47: 0 | J47: 0 | L47: 0 | M47: Never onboarded | N47: Nick montes and SHRUTI | O47: TRUE
A48: Lady Grace Beauty Spa | B48: parulrshah@hotmail.com | C48: 2026-02 | D48: 46079 | G48: FALSE | H48: FALSE | I48: 0 | J48: 0 | L48: 0 | M48: Never onboarded | N48: Parul <> Zoca | O48: TRUE
A49: Alpha Massage & Wellness | B49: book@alphamassage.co | C49: 2026-02 | D49: 46056 | G49: FALSE | H49: FALSE | I49: 0 | J49: 0 | L49: 0 | M49: Never onboarded | N49: Caroline nyakundi and Bikash Chandra | O49: TRUE
A50: SUMMER'S HAIR BRAIDING | B50: summerbraidinghairsalon@gmail.com | C50: 2026-02 | D50: 46079 | G50: FALSE | H50: FALSE | I50: 0 | J50: 0 | L50: 0 | M50: Never onboarded | N50: SUMMER'S HAIR BRAIDING X Zoca | Check In Febr | O50: FALSE
A51: Salon Greco The European Day Spa | B51: salongreco@aol.com | C51: 2026-02 | D51: 46069 | E51: 46226 | F51: 157 | G51: FALSE | H51: FALSE | I51: 0 | J51: 0 | L51: 0 | M51: Onboarded, not enabled | N51: Cathie and Shikha | O51: TRUE
A52: GreenLotus Spa + Med Spa | B52: sherrywei87@gmail.com | C52: 2026-02 | D52: 46080 | G52: FALSE | H52: FALSE | I52: 0 | J52: 0 | L52: 0 | M52: Never onboarded | N52: Green Lotus Spa X Zoca | Check In February | O52: TRUE
A53: Highline Aesthetics Denver | B53: jenna@highlineaestheticsdenver.com | C53: 2026-02 | D53: 46078 | G53: FALSE | H53: FALSE | I53: 0 | J53: 0 | L53: 0 | M53: Never onboarded | N53: Highline Aesthetics Denver and SHRUTI | O53: TRUE
A54: Sublime Therapy Medical Massage | B54: sublimetherapymm@gmail.com | C54: 2026-02 | D54: 46080 | G54: FALSE | H54: FALSE | I54: 0 | J54: 0 | L54: 0 | M54: Never onboarded | N54: Betty Soriano and SHRUTI | O54: FALSE
A55: Vineeta's Beauty Care | B55: ajit2k@gmail.com | C55: 2026-02 | D55: 46069 | G55: FALSE | H55: FALSE | I55: 0 | J55: 0 | L55: 0 | M55: Never onboarded | N55: Vineeta's Beauty Care <> Zoca | O55: TRUE
A56: Catalia Beauty & Wellness | B56: catalianyc@gmail.com | C56: 2026-02 | D56: 46079 | G56: FALSE | H56: FALSE | I56: 0 | J56: 0 | L56: 0 | M56: Never onboarded | N56: Avi and Hubern | O56: TRUE
A57: Leena's Laser Center | B57: desouza.leena@gmail.com | C57: 2026-03 | D57: 46106 | E57: 46113 | F57: 7 | G57: TRUE | H57: FALSE | I57: 532 | J57: 80 | K57: 46237 | L57: 0 | M57: Booking | N57: Leena <> Zoca Check In | O57: TRUE
A58: The Body Lux: Brazilian Lymphatic Drainage & Body Contouring | B58: thebodyluxspaaz@gmail.com | C58: 2026-03 | D58: 46092 | E58: 46119 | F58: 27 | G58: TRUE | H58: TRUE | I58: 350 | J58: 44 | K58: 46237 | L58: 19154.84 | M58: Booking | N58: Isabel <> Check - in | O58: TRUE
A59: Luna Lucci Hair Salon | B59: lunaluccisalon@gmail.com | C59: 2026-03 | D59: 46084 | E59: 46121 | F59: 37 | G59: TRUE | H59: TRUE | I59: 56 | J59: 56 | K59: 46234 | L59: 0 | M59: Booking | N59: Luna Lucci Hair Salon X Zoca | Check In March | O59: TRUE
A60: Shine BE Happy - Hair, Nails & Skincare | B60: kelly.shinebehappy@gmail.com | C60: 2026-03 | D60: 46083 | E60: 46195 | F60: 112 | G60: TRUE | H60: FALSE | I60: 7 | J60: 0 | K60: 46237 | L60: 0 | M60: Booking | N60: Shine BE Happy - Hair, Nails & Skincare X Zoc | O60: TRUE
A61: Journey Within Wellness Center / Spa | B61: journeywithincarlos@gmail.com | C61: 2026-03 | D61: 46090 | G61: FALSE | H61: FALSE | I61: 0 | J61: 0 | L61: 0 | M61: Never onboarded | N61: Carlos <> Check - in | O61: TRUE
A62: Faye Aesthetics, Inc. | B62: fayedodgeesthetics@gmail.com | C62: 2026-03 | D62: 46112 | G62: FALSE | H62: FALSE | I62: 0 | J62: 0 | L62: 0 | M62: Never onboarded | N62: Faye Aesthetics, Inc. X Zoca | Check In March | O62: TRUE
A63: J Madison Spa | B63: info@jmadisonspa.com | C63: 2026-03 | D63: 46084 | G63: FALSE | H63: FALSE | I63: 0 | J63: 0 | L63: 0 | M63: Never onboarded | N63: Zoca Check-in Call with Roseanne | O63: TRUE
A64: Katherine Booth skincare & Spa | B64: kboothskincare@gmail.com | C64: 2026-03 | D64: 46084 | G64: FALSE | H64: FALSE | I64: 0 | J64: 0 | L64: 0 | M64: Never onboarded | N64: Katherine Booth Skincare & Spa X Zoca | Check | O64: TRUE
A65: Shahin Javaheri, MD - Plastic Surgeon San Francisco | B65: info@sfplasticsurgeon.com | C65: 2026-03 | D65: 46104 | G65: FALSE | H65: FALSE | I65: 0 | J65: 0 | L65: 0 | M65: Never onboarded | N65: rosh patel and Shruti Sinha | O65: TRUE
A66: Angie Curly Hair Stylist at Chatters SOUTHGATE | B66: angie.d.elder@gmail.com | C66: 2026-03 | D66: 46092 | G66: FALSE | H66: FALSE | I66: 0 | J66: 0 | L66: 0 | M66: Never onboarded | N66: Angie Curly Hair Stylist <> Check in | March | O66: TRUE
A67: Ohana Sun Tanning | B67: tan@ohanasuntanning.com | C67: 2026-03 | D67: 46086 | G67: FALSE | H67: FALSE | I67: 0 | J67: 0 | L67: 0 | M67: Never onboarded | N67: zoca check in | O67: TRUE
A68: Serenity Nails And Spa LLC | B68: serenitynails1@yahoo.com | C68: 2026-03 | D68: 46083 | G68: FALSE | H68: FALSE | I68: 0 | J68: 0 | L68: 0 | M68: Never onboarded | N68: Janan Kaoud and Apurvaa Biswas | O68: TRUE
A69: Ivy and Mane Salon & Spa | B69: ivyandmane.beauty@gmail.com | C69: 2026-03 | D69: 46085 | G69: FALSE | H69: FALSE | I69: 0 | J69: 0 | L69: 0 | M69: Never onboarded | N69: Rebecca and Hubern | O69: TRUE
A70: Kinkology Locs & Natural Haircare | B70: noelette@kinkologyhaircare.com | C70: 2026-03 | D70: 46106 | G70: FALSE | H70: FALSE | I70: 0 | J70: 0 | L70: 0 | M70: Never onboarded | N70: Kinkology Locs & Natural Haircare X Zoca | Ch | O70: TRUE
A71: OBNoxious Beauty MedSpa | B71: obnbeauty@gmail.com | C71: 2026-03 | D71: 46084 | G71: FALSE | H71: FALSE | I71: 0 | J71: 0 | L71: 0 | M71: Never onboarded | N71: OBNoxious Beauty MedSpa | O71: FALSE
A72: Naree Massage & Spa | B72: oysaisit@yahoo.com | C72: 2026-03 | D72: 46087 | G72: FALSE | H72: FALSE | I72: 0 | J72: 0 | L72: 0 | M72: Never onboarded | N72: Zoca Scheduling Onboarding (Sapha Pickering) | O72: FALSE
... A74: Designer Nails | B74: apasion01@gmail.com | C74: 2026-03 | D74: 46091 | G74: FALSE | H74: FALSE | I74: 0 | J74: 0 | L74: 0 | M74: Never onboarded | N74: Designer Nails x Zoca | O74: TRUE
A75: Garden Glam Beauty | B75: gardenglambeauty089@gmail.com | C75: 2026-04 | D75: 46129 | E75: 46185 | F75: 56 | G75: TRUE | H75: FALSE | I75: 53 | J75: 17 | K75: 46235 | L75: 0 | M75: Booking | N75: Garden Glam Beauty X Zoca | Check In April | O75: TRUE
A76: Golden Jade Massage & Healing | B76: goldenjade.mh@gmail.com | C76: 2026-04 | D76: 46134 | E76: 46232 | F76: 98 | G76: TRUE | H76: FALSE | I76: 10 | J76: 6 | K76: 46236 | L76: 171479 | M76: Booking | N76: Golden Jade Massage & Healing X Zoca | Check | O76: TRUE
A77: Worldwide Stretch Therapy | B77: philoy.williams@gmail.com | C77: 2026-04 | D77: 46135 | E77: 46227 | F77: 92 | G77: TRUE | H77: TRUE | I77: 1 | J77: 1 | K77: 46236 | L77: 0 | M77: Booking | N77: Worldwide Stretch Therapy X Zoca | Check In A | O77: TRUE
A78: Houston braid and weave lounge | B78: dd.anta22@gmail.com | C78: 2026-04 | D78: 46119 | G78: FALSE | H78: FALSE | I78: 0 | J78: 0 | L78: 0 | M78: Never onboarded | N78: Houston braid and weave lounge X Zoca | Check | O78: TRUE
A79: Hair N' Bloom | B79: veronicaeli7@gmail.com | C79: 2026-04 | D79: 46120 | G79: FALSE | H79: FALSE | I79: 0 | J79: 0 | L79: 0 | M79: Never onboarded | N79: Hair N' Bloom X Zoca | Check In April | O79: TRUE
A80: Nilora beauty hair salon | B80: nilorabyniloo@gmail.com | C80: 2026-04 | D80: 46140 | G80: FALSE | H80: FALSE | I80: 0 | J80: 0 | L80: 0 | M80: Never onboarded | N80: Zoca Check In <> Niloo | O80: FALSE
A81: Salon Care By Tina | B81: joanncatina@yahoo.com | C81: 2026-04 | D81: 46128 | G81: FALSE | H81: FALSE | I81: 0 | J81: 0 | L81: 0 | M81: Never onboarded | N81: Zoca <><>Tina | O81: FALSE
A82: D'Venus Spa | B82: meredithaugustine@yahoo.com | C82: 2026-04 | D82: 46141 | G82: FALSE | H82: FALSE | I82: 0 | J82: 0 | L82: 0 | M82: Never onboarded | N82: D'Venus Spa <> Zoca (Win Agent) | O82: FALSE
A83: Nex Med Aesthetics | B83: info@nexmedaesthetics.com | C83: 2026-04 | D83: 46128 | G83: FALSE | H83: FALSE | I83: 0 | J83: 0 | L83: 0 | M83: Never onboarded | N83: Nex Med Aesthetics | Check in | O83: TRUE
A84: The Wax Place | B84: ginatibbs@gmail.com | C84: 2026-04 | D84: 46127 | G84: FALSE | H84: FALSE | I84: 0 | J84: 0 | L84: 0 | M84: Never onboarded | N84: Anu & Gina Catchup | O84: TRUE
A85: JL Studio | B85: jackie.leveille@gmail.com | C85: 2026-04 | D85: 46126 | E85: 46156 | F85: 30 | G85: FALSE | H85: FALSE | I85: 0 | J85: 0 | L85: 0 | M85: Onboarded, not enabled | N85: jackie <> Zoca | O85: TRUE
A86: Planet Color Hair Salon | B86: eric@wwbe.us | C86: 2026-04 | D86: 46122 | G86: FALSE | H86: FALSE | I86: 0 | J86: 0 | L86: 0 | M86: Never onboarded | N86: Zoca <> Eric | O86: TRUE
A87: NewYou Skin and Body Med Spa | B87: jennifernguyen10884@gmail.com | C87: 2026-04 | D87: 46113 | G87: FALSE | H87: FALSE | I87: 0 | J87: 0 | L87: 0 | M87: Never onboarded | N87: NewYou Skin and Body Med Spa X Zoca | Check I | O87: TRUE
A88: Dash Hair & Company, LLC | B88: ellistatamiatta@gmail.com | C88: 2026-04 | D88: 46140 | E88: 46237 | F88: 97 | G88: FALSE | H88: FALSE | I88: 0 | J88: 0 | L88: 0 | M88: Onboarded, not enabled | N88: Zoca Check In <> Dash Hair & Company | O88: TRUE
A89: Skinsation Medspa | B89: sharmeeng@gmail.com | C89: 2026-04 | D89: 46113 | G89: FALSE | H89: FALSE | I89: 0 | J89: 0 | L89: 0 | M89: Never onboarded | N89: Catchup with Sharmin | O89: TRUE
A90: Sole Pilates | B90: spmaxxformer@gmail.com | C90: 2026-04 | D90: 46125 | G90: FALSE | H90: FALSE | I90: 0 | J90: 0 | L90: 0 | M90: Never onboarded | N90: Sole Pilates X Zoca | Check In April | O90: TRUE
A91: Skin by Nesrin | B91: skinbynesrin@gmail.com | C91: 2026-04 | D91: 46133 | G91: FALSE | H91: FALSE | I91: 0 | J91: 0 | L91: 0 | M91: Never onboarded | N91: Skin by Nesrin X Zoca | Check In April | O91: TRUE
A92: The Nail Bar | B92: robertgadimian@gmail.com | C92: 2026-04 | D92: 46118 | G92: FALSE | H92: FALSE | I92: 0 | J92: 0 | L92: 0 | M92: Never onboarded | N92: Zoca <>The Nail Bar<>Robert | O92: TRUE
A93: SUR MedSpa (Medical Spa) - Marietta, GA | B93: admin@surmedspa.com | C93: 2026-05 | D93: 46167 | E93: 46182 | F93: 15 | G93: TRUE | H93: TRUE | I93: 32 | J93: 32 | K93: 46237 | L93: 0 | M93: Booking | N93: SUR MedSpa <> Zoca | O93: TRUE
A94: Bryant Salon & Spa | B94: bryantsalonandspa@gmail.com | C94: 2026-05 | D94: 46147 | G94: FALSE | H94: FALSE | I94: 0 | J94: 0 | L94: 0 | M94: Never onboarded | N94: Bryant Salon & Spa X Zoca | Check In May | O94: TRUE
A95: Aliana Salon | B95: irfan.allana@gmail.com | C95: 2026-05 | D95: 46161 | G95: FALSE | H95: FALSE | I95: 0 | J95: 0 | L95: 0 | M95: Never onboarded | N95: Aliana Salon <> Zoca | O95: TRUE
A96: Salt For Your Soul | B96: shaunathale@gmail.com | C96: 2026-05 | D96: 46148 | G96: FALSE | H96: FALSE | I96: 0 | J96: 0 | L96: 0 | M96: Never onboarded | N96: Anu & Shauna | O96: TRUE
A97: Hairbygino | B97: ginomagnarelli@gmail.com | C97: 2026-05 | D97: 46153 | E97: 46225 | F97: 72 | G97: TRUE | H97: FALSE | I97: 0 | J97: 0 | L97: 0 | M97: Enabled, no bookings | N97: Hairbygino X Zoca | Check In May | O97: TRUE
A98: Le Chic Hair Studio | B98: 1332lchs@gmail.com | C98: 2026-05 | D98: 46161 | G98: FALSE | H98: FALSE | I98: 0 | J98: 0 | L98: 0 | M98: Never onboarded | N98: Le Chic Hair Studio X Zoca | Check In May | O98: FALSE
A99: Blue Birdie Beauty | B99: bluebirdiebeauty@gmail.com | C99: 2026-05 | D99: 46148 | G99: FALSE | H99: FALSE | I99: 0 | J99: 0 | L99: 0 | M99: Never onboarded | N99: Blue Birdie Beauty X Zoca | Check In May | O99: TRUE
A100: Korean Massage by Maya | B100: koreanmassagebymaya@gmail.com | C100: 2026-06 | D100: 46189 | E100: 46224 | F100: 35 | G100: TRUE | H100: FALSE | I100: 60 | J100: 2 | K100: 46237 | L100: 0 | M100: Booking | N100: Korean Massage by Maya X Zoca | Check In June | O100: TRUE
A101: Just Because Hair Therapy Salon | B101: justbecausesalon@me.com | C101: 2026-06 | D101: 46191 | E101: 46210 | F101: 19 | G101: TRUE | H101: TRUE | I101: 15 | J101: 6 | K101: 46234 | L101: 768.92 | M101: Booking | N101: Just Because Hair Therapy Salon X Zoca | Chec | O101: TRUE
A102: Forever Balanced Massage | B102: darrinlane0@gmail.com | C102: 2026-06 | D102: 46184 | E102: 46210 | F102: 26 | G102: TRUE | H102: FALSE | I102: 14 | J102: 7 | K102: 46237 | L102: 0 | M102: Booking | N102: Forever Balanced Massage X Zoca | Check In Ju | O102: TRUE
A103: Hoboken Wellness Spa | B103: info@shascreation.com | C103: 2026-06 | D103: 46195 | G103: FALSE | H103: FALSE | I103: 0 | J103: 0 | L103: 0 | M103: Never onboarded | N103: Hoboken Wellness Spa X Zoca | Check In June | O103: TRUE
...

Sheet Adoption Funnel
A1: Scheduling adoption funnel — 178 legitimate locations
A2: Test and inactive entities removed. Earlier versions showed 444, of which 237 were is_test=TRUE. Every count calculates from the Locations sheet.
A4: Stage | B4: Locations | C4: % of entered | D4: Reading
A5: Entered onboarding | B5: =COUNTA(Locations!$A$2:$A$179) | C5: =B5/$B$5 | D5: Denominator — legitimate only
A6: Opted in | B6: =SUMPRODUCT(--(Locations!$E$2:$E$179=TRUE)) | C6: =B6/$B$5
A7: Business details set | B7: =SUMPRODUCT(--(Locations!$F$2:$F$179=TRUE)) | C7: =B7/$B$5
A8: Services configured | B8: =SUMPRODUCT(--(Locations!$G$2:$G$179=TRUE)) | C8: =B8/$B$5
A9: Booking rules configured | B9: =SUMPRODUCT(--(Locations!$H$2:$H$179=TRUE)) | C9: =B9/$B$5
A10: Booking policies configured | B10: =SUMPRODUCT(--(Locations!$I$2:$I$179=TRUE)) | C10: =B10/$B$5
A11: Website flipped to Zoca booking | B11: =SUMPRODUCT(--(Locations!$N$2:$N$179=TRUE)) | C11: =B11/$B$5
A12: Onboarding completed | B12: =SUMPRODUCT(--(Locations!$L$2:$L$179=TRUE)) | C12: =B12/$B$5
A13: Enabled (config flag) | B13: =SUMPRODUCT(--(Locations!$M$2:$M$179=TRUE)) | C13: =B13/$B$5 | D13: SETUP conversion
A14: Payments configured | B14: =SUMPRODUCT(--(Locations!$J$2:$J$179=TRUE)) | C14: =B14/$B$5 | D14: The wall
A15: Payments explicitly skipped | B15: =SUMPRODUCT(--(Locations!$K$2:$K$179=TRUE)) | C15: =B15/$B$5 | D15: The wall
A16: Operationally live (>=1 earned booking) | B16: =SUMPRODUCT(--(Locations!$T$2:$T$179=TRUE)) | C16: =B16/$B$5 | D16: ACTIVATION conversion
A17: …took a customer-made booking | B17: =SUMPRODUCT(--(Locations!$P$2:$P$179>0)) | C17: =B17/$B$5
A18: Live in last 90 days | B18: =SUMPRODUCT(--(Locations!$S$2:$S$179>=Summary!$B$3-90)) | C18: =B18/$B$5
A19: Live in last 30 days | B19: =SUMPRODUCT(--(Locations!$S$2:$S$179>=Summary!$B$3-30)) | C19: =B19/$B$5 | D19: SUSTAINED conversion

Sheet Locations
A1: Location entity id | B1: Business name | C1: Onboarding started | D1: Cohort | E1: Opted in | F1: Business details | G1: Services configured | H1: Booking rules | I1: Booking policies | J1: Payments configured | K1: Payments skipped | L1: Onboarding completed | M1: Enabled (flag) | N1: Website flipped | O1: Earned bookings | P1: Customer-made | Q1: Staff-made | R1: Migration source | S1: Last earned booking | T1: Operationally live | U1: Live in last 30d | V1: Paid transactions | W1: Paid amount post-launch (USD) | X1: Chargebee customer id | Y1: MRR (USD) | Z1: Subscription status
A2: f2930e96-c10f-4273-834d-948790dcb785 | B2: Nbraidstyles | C2: 46052 | D2: 2026-01 | E2: TRUE | F2: TRUE | G2: TRUE | H2: TRUE | I2: TRUE | J2: TRUE | K2: FALSE | L2: TRUE | M2: TRUE | N2: TRUE | O2: 75 | P2: 73 | Q2: 2 | S2: 46237 | T2: TRUE | U2: TRUE | V2: 69 | W2: 2627 | X2: cus_OGiPoqL0Cu6SL2 | Y2: 135 | Z2: active
A3: 0a3e4ac6-9bdb-4e76-b354-7e2f2d6bb72c | B3: (name not on file) | C3: 46053 | D3: 2026-01 | E3: TRUE | F3: TRUE | G3: FALSE | H3: FALSE | I3: FALSE | J3: FALSE | K3: FALSE | L3: FALSE | M3: FALSE | N3: FALSE | O3: 0 | P3: 0 | Q3: 0 | T3: FALSE | U3: FALSE | V3: 0 | W3: 0
A4: d1983fab-fb1b-43c6-af50-2e25684bdc16 | B4: (name not on file) | C4: 46053 | D4: 2026-01 | E4: TRUE | F4: TRUE | G4: TRUE | H4: TRUE | I4: TRUE | J4: FALSE | K4: TRUE | L4: TRUE | M4: TRUE | N4: TRUE | O4: 5 | P4: 0 | Q4: 5 | S4: 46053 | T4: TRUE | U4: FALSE | V4: 0 | W4: 0
A5: 61bcfc8a-d56d-4b46-a4a3-658ce60aa48f | B5: (name not on file) | C5: 46053 | D5: 2026-01 | E5: TRUE | F5: TRUE | G5: TRUE | H5: TRUE | I5: TRUE | J5: FALSE | K5: TRUE | L5: TRUE | M5: TRUE | N5: TRUE | O5: 3 | P5: 0 | Q5: 3 | S5: 46055 | T5: TRUE | U5: FALSE | V5: 0 | W5: 0
A6: 07233b3c-c922-40a7-8ac3-e57986ffb675 | B6: (name not on file) | C6: 46055 | D6: 2026-02 | E6: TRUE | F6: TRUE | G6: TRUE | H6: TRUE | I6: TRUE | J6: FALSE | K6: TRUE | L6: TRUE | M6: TRUE | N6: TRUE | O6: 17 | P6: 9 | Q6: 8 | S6: 46056 | T6: TRUE | U6: FALSE | V6: 0 | W6: 0
A7: 736264eb-3de6-49d0-a1fb-6706edc2ac61 | B7: Creations Art and Beauty | C7: 46055 | D7: 2026-02 | E7: TRUE | F7: TRUE | G7: TRUE | H7: TRUE | I7: TRUE | J7: TRUE | K7: FALSE | L7: TRUE | M7: TRUE | N7: TRUE | O7: 23 | P7: 12 | Q7: 11 | S7: 46233 | T7: TRUE | U7: TRUE | V7: 1 | W7: 1.4 | X7: AzqhpEUzYFk7hC0ut | Y7: 350 | Z7: active
A8: 410b7b26-6680-425d-8f37-642290a08d52 | B8: (name not on file) | C8: 46056 | D8: 2026-02 | E8: TRUE | F8: TRUE | G8: TRUE | H8: TRUE | I8: TRUE | J8: FALSE | K8: TRUE | L8: TRUE | M8: TRUE | N8: TRUE | O8: 14 | P8: 8 | Q8: 6 | S8: 46057 | T8: TRUE | U8: FALSE | V8: 0 | W8: 0
A9: f72ac231-6a87-43ef-b01d-60f1ba670cc9 | B9: (name not on file) | C9: 46057 | D9: 2026-02 | E9: TRUE | F9: TRUE | G9: TRUE | H9: TRUE | I9: TRUE | J9: FALSE | K9: TRUE | L9: TRUE | M9: TRUE | N9: TRUE | O9: 15 | P9: 1 | Q9: 14 | S9: 46063 | T9: TRUE | U9: FALSE | V9: 2 | W9: 246
A10: 67e3523d-dff6-47d4-bebf-55bba69ef991 | B10: ponceluxe laser studio | C10: 46058 | D10: 2026-02 | E10: TRUE | F10: TRUE | G10: TRUE | H10: TRUE | I10: TRUE | J10: FALSE | K10: TRUE | L10: TRUE | M10: TRUE | N10: TRUE | O10: 434 | P10: 55 | Q10: 379 | S10: 46237 | T10: TRUE | U10: TRUE | V10: 1 | W10: 3500 | X10: AzZkqoV5Dtkn82au8 | Y10: 100 | Z10: active
A11: f774f9a1-e3df-458b-949f-a1cd9a346214 | B11: Jeans lash lounge | C11: 46059 | D11: 2026-02 | E11: TRUE | F11: TRUE | G11: TRUE | H11: TRUE | I11: TRUE | J11: TRUE | K11: FALSE | L11: TRUE | M11: TRUE | N11: TRUE | O11: 24 | P11: 22 | Q11: 2 | S11: 46223 | T11: TRUE | U11: TRUE | V11: 0 | W11: 0 | X11: AzqKGMUj2VY405ZFf | Y11: 399 | Z11: active
A12: 8516a713-7500-4ad6-9dde-d49f249abbb4 | B12: Lord of Locs | C12: 46062 | D12: 2026-02 | E12: TRUE | F12: TRUE | G12: TRUE | H12: TRUE | I12: TRUE | J12: TRUE | K12: TRUE | L12: TRUE | M12: TRUE | N12: TRUE | O12: 77 | P12: 67 | Q12: 10 | S12: 46237 | T12: TRUE | U12: TRUE | V12: 72 | W12: 3956 | X12: cus_Q0yzaP9rDqi7TT | Y12: 150 | Z12: active
A13: db2e88b9-af6a-4d47-8900-9fcca27925a9 | B13: The Beauty Bar Salon and Spa | C13: 46062 | D13: 2026-02 | E13: TRUE | F13: TRUE | G13: TRUE | H13: TRUE | I13: TRUE | J13: TRUE | K13: FALSE | L13: TRUE | M13: TRUE | N13: TRUE | O13: 459 | P13: 415 | Q13: 44 | S13: 46237 | T13: TRUE | U13: TRUE | V13: 271 | W13: 8558.5 | X13: cus_OUyjtBRaU7IAeF | Y13: 162.94 | Z13: active
A14: ccf27c15-8215-40aa-8204-aa7573903d30 | B14: Premium African Braids | C14: 46063 | D14: 2026-02 | E14: TRUE | F14: TRUE | G14: TRUE | H14: TRUE | I14: TRUE | J14: TRUE | K14: FALSE | L14: TRUE | M14: TRUE | N14: TRUE | O14: 7 | P14: 6 | Q14: 1 | S14: 46172 | T14: TRUE | U14: FALSE | V14: 0 | W14: 0 | X14: cus_RR29SxTsdXcDRw | Y14: 108.62 | Z14: active
A15: b5974616-7dcd-4f9f-91f7-d27f886d343d | B15: (name not on file) | C15: 46064 | D15: 2026-02 | E15: TRUE | F15: TRUE | G15: TRUE | H15: TRUE | I15: TRUE | J15: FALSE | K15: TRUE | L15: TRUE | M15: TRUE | N15: TRUE | O15: 1 | P15: 1 | Q15: 0 | S15: 46064 | T15: TRUE | U15: FALSE | V15: 0 | W15: 0
A16: 07a8e1fa-f005-4cf5-9182-f1d48d82fa2e | B16: Emporio African Braids | C16: 46065 | D16: 2026-02 | E16: TRUE | F16: TRUE | G16: TRUE | H16: TRUE | I16: TRUE | J16: TRUE | K16: FALSE | L16: TRUE | M16: TRUE | N16: TRUE | O16: 67 | P16: 57 | Q16: 10 | S16: 46237 | T16: TRUE | U16: TRUE | V16: 40 | W16: 1803.6 | X16: cus_Q7pV871MpzSuGB | Y16: 50 | Z16: active
A17: 4ebee20a-db99-4e09-b3f0-afa88cb49861 | B17: Adel braids | C17: 46066 | D17: 2026-02 | E17: TRUE | F17: TRUE | G17: TRUE | H17: TRUE | I17: TRUE | J17: TRUE | K17: FALSE | L17: TRUE | M17: TRUE | N17: TRUE | O17: 19 | P17: 17 | Q17: 2 | S17: 46220 | T17: TRUE | U17: TRUE | V17: 9 | W17: 396 | X17: AzqH9DV2H2LEsW8T | Y17: 199 | Z17: active
A18: 2223edcb-30e6-4131-ad63-42d5a3b2d50f | B18: (name not on file) | C18: 46066 | D18: 2026-02 | E18: TRUE | F18: TRUE | G18: TRUE | H18: TRUE | I18: TRUE | J18: FALSE | K18: TRUE | L18: TRUE | M18: TRUE | N18: TRUE | O18: 8 | P18: 8 | Q18: 0 | S18: 46067 | T18: TRUE | U18: FALSE | V18: 1 | W18: 90
A19: 383a7fdd-b410-414b-a3db-82c1774616fb | B19: Hair By Camille | C19: 46070 | D19: 2026-02 | E19: TRUE | F19: TRUE | G19: TRUE | H19: TRUE | I19: TRUE | J19: TRUE | K19: FALSE | L19: TRUE | M19: TRUE | N19: TRUE | O19: 192 | P19: 48 | Q19: 65 | S19: 46237 | T19: TRUE | U19: TRUE | V19: 0 | W19: 0 | X19: cus_RiJ2uhBiBlg9ZH | Y19: 179 | Z19: active
A20: 3be18092-1615-4c48-915c-f83e8ba38950 | B20: (name not on file) | C20: 46071 | D20: 2026-02 | E20: TRUE | F20: TRUE | G20: TRUE | H20: TRUE | I20: TRUE | J20: FALSE | K20: TRUE | L20: TRUE | M20: TRUE | N20: TRUE | O20: 3 | P20: 3 | Q20: 0 | S20: 46071 | T20: TRUE | U20: FALSE | V20: 0 | W20: 0
A21: cee7df4b-ba3b-43df-858d-9304187b4723 | B21: (name not on file) | C21: 46072 | D21: 2026-02 | E21: TRUE | F21: TRUE | G21: TRUE | H21: TRUE | I21: TRUE | J21: FALSE | K21: TRUE | L21: TRUE | M21: TRUE | N21: TRUE | O21: 2 | P21: 2 | Q21: 0 | S21: 46073 | T21: TRUE | U21: FALSE | V21: 0 | W21: 0
A22: fa2619ea-5509-4815-8b9e-a933e26321bf | B22: (name not on file) | C22: 46073 | D22: 2026-02 | E22: TRUE | F22: TRUE | G22: TRUE | H22: TRUE | I22: TRUE | J22: FALSE | K22: TRUE | L22: TRUE | M22: TRUE | N22: TRUE | O22: 0 | P22: 0 | Q22: 0 | T22: FALSE | U22: FALSE | V22: 0 | W22: 0
A23: 54a27121-0b23-4ed0-9153-aec06840a7f7 | B23: it's Waxing & Threading | C23: 46074 | D23: 2026-02 | E23: TRUE | F23: TRUE | G23: TRUE | H23: TRUE | I23: TRUE | J23: FALSE | K23: TRUE | L23: TRUE | M23: TRUE | N23: TRUE | O23: 106 | P23: 76 | Q23: 30 | S23: 46235 | T23: TRUE | U23: TRUE | V23: 14 | W23: 903 | X23: 16AflPVAZLsIpMXS4 | Y23: 1250.07 | Z23: active
A24: 11e81849-6bde-4d33-855d-927f443698bd | B24: Miracle hands braiding Studio | C24: 46077 | D24: 2026-02 | E24: TRUE | F24: TRUE | G24: TRUE | H24: TRUE | I24: TRUE | J24: FALSE | K24: TRUE | L24: TRUE | M24: TRUE | N24: TRUE | O24: 52 | P24: 33 | Q24: 19 | S24: 46237 | T24: TRUE | U24: TRUE | V24: 0 | W24: 0 | X24: cus_PU3NzApnWkMxob | Y24: 150 | Z24: active
A25: 1b26e354-eb83-433b-a77c-7f2b3f9355f3 | B25: (name not on file) | C25: 46078 | D25: 2026-02 | E25: TRUE | F25: TRUE | G25: TRUE | H25: TRUE | I25: TRUE | J25: FALSE | K25: TRUE | L25: TRUE | M25: TRUE | N25: TRUE | O25: 21 | P25: 21 | Q25: 0 | S25: 46079 | T25: TRUE | U25: FALSE | V25: 0 | W25: 0
A26: bdcb9096-7934-440c-bc24-57268f63b08b | B26: Vida Beauty Bar | C26: 46078 | D26: 2026-02 | E26: TRUE | F26: TRUE | G26: TRUE | H26: TRUE | I26: TRUE | J26: FALSE | K26: TRUE | L26: TRUE | M26: TRUE | N26: TRUE | O26: 694 | P26: 191 | Q26: 503 | S26: 46237 | T26: TRUE | U26: TRUE | V26: 0 | W26: 0 | X26: 16BXdwUvalf4c3pdW | Y26: 199 | Z26: active
A27: 3a38f3a3-b66e-4f62-b841-3e9ce14350ad | B27: Golden Hair Braiding | C27: 46079 | D27: 2026-02 | E27: TRUE | F27: TRUE | G27: TRUE | H27: TRUE | I27: TRUE | J27: FALSE | K27: TRUE | L27: TRUE | M27: TRUE | N27: TRUE | O27: 128 | P27: 128 | Q27: 0 | S27: 46234 | T27: TRUE | U27: TRUE | V27: 0 | W27: 0 | X27: AzqO4bV13axpA8JbC | Y27: 200 | Z27: active
A28: 04d19914-49c8-44f2-b251-5fbd643a2300 | B28: Jamila African Hair Braiding | C28: 46079 | D28: 2026-02 | E28: TRUE | F28: TRUE | G28: TRUE | H28: TRUE | I28: TRUE | J28: FALSE | K28: TRUE | L28: TRUE | M28: TRUE | N28: TRUE | O28: 114 | P28: 114 | Q28: 0 | S28: 46237 | T28: TRUE | U28: TRUE | V28: 0 | W28: 0 | X28: AzqbodV0xNjaWDWp0 | Y28: 150 | Z28: active
A29: 65dd98d3-43be-49f3-93f4-ef35117d66b3 | B29: (name not on file) | C29: 46080 | D29: 2026-02 | E29: TRUE | F29: TRUE | G29: TRUE | H29: TRUE | I29: TRUE | J29: FALSE | K29: TRUE | L29: TRUE | M29: TRUE | N29: TRUE | O29: 14 | P29: 14 | Q29: 0 | S29: 46083 | T29: TRUE | U29: FALSE | V29: 1 | W29: 55
A30: 059e2eba-670d-4618-bd84-63b3a685bad1 | B30: Naomi's African Hair Braiding Salon | C30: 46080 | D30: 2026-02 | E30: TRUE | F30: TRUE | G30: TRUE | H30: TRUE | I30: TRUE | J30: FALSE | K30: FALSE | L30: FALSE | M30: FALSE | N30: FALSE | O30: 0 | P30: 0 | Q30: 0 | T30: FALSE | U30: FALSE | V30: 0 | W30: 0 | X30: cus_PjQE46ZlgRsQvY | Y30: 100 | Z30: active
A31: b7c19608-d68c-4f1d-860d-ff6f70d4a564 | B31: The Moon Beauty | Facial Spa | C31: 46083 | D31: 2026-03 | E31: TRUE | F31: TRUE | G31: FALSE | H31: FALSE | I31: FALSE | J31: FALSE | K31: FALSE | L31: FALSE | M31: FALSE | N31: FALSE | O31: 0 | P31: 0 | Q31: 0 | T31: FALSE | U31: FALSE | V31: 0 | W31: 0 | X31: cus_Q265iKOdiQIKnz | Y31: 200 | Z31: active
A32: 7c02b584-78b6-4c2e-b105-a8f6f51ad7f7 | B32: The Sculpt Spa | C32: 46083 | D32: 2026-03 | E32: TRUE | F32: TRUE | G32: TRUE | H32: TRUE | I32: TRUE | J32: TRUE | K32: FALSE | L32: TRUE | M32: TRUE | N32: TRUE | O32: 6 | P32: 6 | Q32: 0 | S32: 46199 | T32: TRUE | U32: FALSE | V32: 0 | W32: 0 | X32: cus_U3eC0paE9t3LVN | Y32: 150 | Z32: active
A33: 6d08968b-164f-49ed-8832-0e7590d22863 | B33: (name not on file) | C33: 46084 | D33: 2026-03 | E33: TRUE | F33: TRUE | G33: TRUE | H33: TRUE | I33: TRUE | J33: FALSE | K33: TRUE | L33: TRUE | M33: TRUE | N33: TRUE | O33: 21 | P33: 21 | Q33: 0 | S33: 46087 | T33: TRUE | U33: FALSE | V33: 3 | W33: 285.5
A34: ba888c97-7ef0-458b-9509-f43966d256aa | B34: Kindness Massage | C34: 46086 | D34: 2026-03 | E34: TRUE | F34: TRUE | G34: TRUE | H34: TRUE | I34: TRUE | J34: TRUE | K34: FALSE | L34: TRUE | M34: TRUE | N34: TRUE | O34: 164 | P34: 103 | Q34: 61 | S34: 46236 | T34: TRUE | U34: TRUE | V34: 0 | W34: 0 | X34: 169m4nUy2hjFi1Vuz | Y34: 248 | Z34: active
A35: 78303b7a-d9cd-4399-a2a0-7fe3324fc2a7 | B35: Flawless Face & Wax by Felecia | C35: 46086 | D35: 2026-03 | E35: TRUE | F35: TRUE | G35: TRUE | H35: TRUE | I35: TRUE | J35: FALSE | K35: FALSE | L35: FALSE | M35: FALSE | N35: FALSE | O35: 0 | P35: 0 | Q35: 0 | T35: FALSE | U35: FALSE | V35: 0 | W35: 0
A36: b105cf01-8be7-4c7e-a158-c9e4deb10a1d | B36: Heavenly Touch by Donna | C36: 46086 | D36: 2026-03 | E36: TRUE | F36: TRUE | G36: TRUE | H36: TRUE | I36: TRUE | J36: TRUE | K36: FALSE | L36: TRUE | M36: TRUE | N36: TRUE | O36: 32 | P36: 8 | Q36: 24 | S36: 46237 | T36: TRUE | U36: TRUE | V36: 0 | W36: 0 | X36: 16BcgdV2pu06pjj0 | Y36: 199 | Z36: active
A37: c2df4b6a-2c1d-4a33-bc7c-af3af4d1fcce | B37: Charlotte African hair braiding | C37: 46087 | D37: 2026-03 | E37: TRUE | F37: TRUE | G37: TRUE | H37: TRUE | I37: TRUE | J37: FALSE | K37: FALSE | L37: FALSE | M37: FALSE | N37: FALSE | O37: 0 | P37: 0 | Q37: 0 | T37: FALSE | U37: FALSE | V37: 0 | W37: 0 | X37: cus_P9D8q6qIZmvzmr | Y37: 90 | Z37: active
A38: 1a594d9e-0d13-4235-9ff7-69e8a4ac1a5b | B38: (name not on file) | C38: 46092 | D38: 2026-03 | E38: TRUE | F38: TRUE | G38: TRUE | H38: TRUE | I38: TRUE | J38: FALSE | K38: TRUE | L38: TRUE | M38: TRUE | N38: TRUE | O38: 0 | P38: 0 | Q38: 0 | T38: FALSE | U38: FALSE | V38: 0 | W38: 0
A39: e3dc5b9f-56fa-4ee4-a974-84f4dfabed48 | B39: African Hair Braiding by Hawa | C39: 46092 | D39: 2026-03 | E39: TRUE | F39: TRUE | G39: TRUE | H39: TRUE | I39: TRUE | J39: TRUE | K39: FALSE | L39: TRUE | M39: TRUE | N39: TRUE | O39: 17 | P39: 17 | Q39: 0 | S39: 46230 | T39: TRUE | U39: TRUE | V39: 17 | W39: 540 | X39: 16CKWJUpdCJRi1kZB | Y39: 100 | Z39: active
A40: 12d1230a-7f02-467f-b32c-ccefbe2d268a | B40: ChinnysFlair | C40: 46092 | D40: 2026-03 | E40: TRUE | F40: TRUE | G40: TRUE | H40: TRUE | I40: TRUE | J40: FALSE | K40: TRUE | L40: TRUE | M40: TRUE | N40: TRUE | O40: 33 | P40: 25 | Q40: 8 | S40: 46233 | T40: TRUE | U40: TRUE | V40: 4 | W40: 687.5 | X40: 169z91UzihO0y1liT | Y40: 199 | Z40: active
A41: 52e57b9c-3fbc-477c-a213-72507c3e9ff4 | B41: JOSIE HAIR BRAIDING | C41: 46097 | D41: 2026-03 | E41: TRUE | F41: TRUE | G41: TRUE | H41: TRUE | I41: TRUE | J41: TRUE | K41: TRUE | L41: TRUE | M41: TRUE | N41: TRUE | O41: 147 | P41: 109 | Q41: 38 | S41: 46237 | T41: TRUE | U41: TRUE | V41: 0 | W41: 0 | X41: AziGWlVCYg58OJKQ | Y41: 150 | Z41: active
A42: 9111fc32-8e88-43e8-aadd-ab758a436542 | B42: Pams Hair Designs, LLC | Extensions, Weaves | C42: 46097 | D42: 2026-03 | E42: TRUE | F42: TRUE | G42: TRUE | H42: TRUE | I42: TRUE | J42: TRUE | K42: FALSE | L42: TRUE | M42: TRUE | N42: TRUE | O42: 31 | P42: 15 | Q42: 16 | S42: 46216 | T42: TRUE | U42: TRUE | V42: 9 | W42: 1850 | X42: cus_RXm6Cc6VEwACRn | Y42: 100 | Z42: active
A43: caa597b2-84b3-4cae-b33b-bcadd9f03a16 | B43: African hair braiding by beju | C43: 46097 | D43: 2026-03 | E43: TRUE | F43: TRUE | G43: TRUE | H43: TRUE | I43: TRUE | J43: FALSE | K43: TRUE | L43: TRUE | M43: TRUE | N43: TRUE | O43: 104 | P43: 103 | Q43: 1 | S43: 46235 | T43: TRUE | U43: TRUE | V43: 0 | W43: 0 | X43: 169kD2VDrQFRLKPr | Y43: 250 | Z43: active
A44: 007fc36c-ee3c-423a-92d0-7d98a198a3fb | B44: Efflorescence Aesthetic and Cellulite Reduction Spa | C44: 46097 | D44: 2026-03 | E44: TRUE | F44: TRUE | G44: TRUE | H44: TRUE | I44: TRUE | J44: FALSE | K44: TRUE | L44: TRUE | M44: FALSE | N44: FALSE | O44: 0 | P44: 0 | Q44: 0 | T44: FALSE | U44: FALSE | V44: 0 | W44: 0 | X44: AzqR82UzF6jBKHvg | Y44: 150 | Z44: active
A45: 251ff639-6c23-4a42-913e-e8e007b20e36 | B45: Milona Hair Braiding & Weaving | C45: 46097 | D45: 2026-03 | E45: TRUE | F45: TRUE | G45: TRUE | H45: TRUE | I45: TRUE | J45: FALSE | K45: TRUE | L45: TRUE | M45: TRUE | N45: TRUE | O45: 198 | P45: 133 | Q45: 65 | S45: 46237 | T45: TRUE | U45: TRUE | V45: 69 | W45: 2752.5 | X45: cus_RUjxoTAwPCZo11 | Y45: 162.94 | Z45: active
A46: 16ce9985-3536-4a72-bedb-dfacb2f6c80d | B46: Michele Did My Hair LLC | C46: 46101 | D46: 2026-03 | E46: TRUE | F46: TRUE | G46: FALSE | H46: FALSE | I46: FALSE | J46: FALSE | K46: FALSE | L46: FALSE | M46: FALSE | N46: FALSE | O46: 0 | P46: 0 | Q46: 0 | T46: FALSE | U46: FALSE | V46: 0 | W46: 0 | X46: AzZf8YUwDmiGVhnx | Y46: 150 | Z46: active
A47: 72cb8150-fedc-4e26-951d-55ae903fca69 | B47: Simply Facials | Thousand Oaks Esthetician | C47: 46104 | D47: 2026-03 | E47: TRUE | F47: TRUE | G47: TRUE | H47: TRUE | I47: TRUE | J47: TRUE | K47: FALSE | L47: TRUE | M47: TRUE | N47: TRUE | O47: 130 | P47: 3 | Q47: 9 | S47: 46140 | T47: TRUE | U47: FALSE | V47: 6 | W47: 187 | X47: 16BRpkUehYZau6veC | Y47: 199 | Z47: active
A48: 19e48d70-804e-4736-a855-0d998216db92 | B48: Alice African Braids and Locs | C48: 46105 | D48: 2026-03 | E48: TRUE | F48: TRUE | G48: TRUE | H48: TRUE | I48: TRUE | J48: FALSE | K48: TRUE | L48: TRUE | M48: TRUE | N48: TRUE | O48: 117 | P48: 115 | Q48: 2 | S48: 46236 | T48: TRUE | U48: TRUE | V48: 2 | W48: 117.5 | X48: cus_UB42IaUsjzv9OA | Y48: 150 | Z48: active
A49: 49d7400a-b815-425d-bf46-f90b57067ba2 | B49: Giorgio Hair Salon LLC | C49: 46105 | D49: 2026-03 | E49: TRUE | F49: TRUE | G49: TRUE | H49: TRUE | I49: TRUE | J49: FALSE | K49: TRUE | L49: TRUE | M49: TRUE | N49: TRUE | O49: 12 | P49: 6 | Q49: 6 | S49: 46210 | T49: TRUE | U49: TRUE | V49: 0 | W49: 0 | X49: cus_PdqKmBxkmOKSUQ | Y49: 100 | Z49: active
A50: 5cbc3251-3e52-43cf-998c-1477406b47d9 | B50: All About-Extensions&LocsLLC | C50: 46112 | D50: 2026-03 | E50: TRUE | F50: TRUE | G50: TRUE | H50: TRUE | I50: TRUE | J50: TRUE | K50: FALSE | L50: TRUE | M50: TRUE | N50: TRUE | O50: 2 | P50: 2 | Q50: 0 | S50: 46184 | T50: TRUE | U50: FALSE | V50: 1 | W50: 60 | X50: AzhqEzV0YiTbpBg5 | Y50: 150 | Z50: active
A51: c731a2f0-8992-4015-ae9e-73a6598b3703 | B51: Envious Appeal LLC | C51: 46112 | D51: 2026-03 | E51: TRUE | F51: TRUE | G51: TRUE | H51: TRUE | I51: TRUE | J51: FALSE | K51: TRUE | L51: TRUE | M51: TRUE | N51: TRUE | O51: 13 | P51: 13 | Q51: 0 | S51: 46227 | T51: TRUE | U51: TRUE | V51: 0 | W51: 0 | X51: 169wVhUuWV43u2DRJ | Y51: 199 | Z51: active
A52: 48437d71-194e-4c55-b1b7-583302023e62 | B52: Leena's Laser Center | C52: 46113 | D52: 2026-04 | E52: TRUE | F52: TRUE | G52: TRUE | H52: TRUE | I52: TRUE | J52: FALSE | K52: TRUE | L52: TRUE | M52: TRUE | N52: TRUE | O52: 532 | P52: 80 | Q52: 452 | S52: 46237 | T52: TRUE | U52: TRUE | V52: 0 | W52: 0 | X52: cus_Ty1RXXKr0uLIVE | Y52: 200 | Z52: active
A53: d6a83e99-61d7-4259-abf2-cf9c75aa5dfa | B53: Derma Aesthetics Spa | C53: 46113 | D53: 2026-04 | E53: TRUE | F53: TRUE | G53: TRUE | H53: TRUE | I53: TRUE | J53: FALSE | K53: TRUE | L53: TRUE | M53: TRUE | N53: TRUE | O53: 45 | P53: 8 | Q53: 37 | S53: 46233 | T53: TRUE | U53: TRUE | V53: 1 | W53: 150 | X53: 16AtpJV0O0YzjFyg | Y53: 199 | Z53: active
A54: 12910010-c9c1-41bd-8084-f28fbdde7883 | B54: kosme Nails Studio & Academy | C54: 46116 | D54: 2026-04 | E54: TRUE | F54: TRUE | G54: FALSE | H54: FALSE | I54: FALSE | J54: FALSE | K54: FALSE | L54: FALSE | M54: FALSE | N54: FALSE | O54: 0 | P54: 0 | Q54: 0 | T54: FALSE | U54: FALSE | V54: 0 | W54: 0 | X54: AzZh3UVFTNbpy35uA | Y54: 149 | Z54: active
A55: 59bf571d-920f-42b3-a50e-ea97b0d9feec | B55: Braids On Point | C55: 46119 | D55: 2026-04 | E55: TRUE | F55: TRUE | G55: TRUE | H55: TRUE | I55: TRUE | J55: TRUE | K55: FALSE | L55: TRUE | M55: TRUE | N55: TRUE | O55: 58 | P55: 58 | Q55: 0 | S55: 46233 | T55: TRUE | U55: TRUE | V55: 57 | W55: 1728 | X55: AzqPexVFOlArabcsQ | Y55: 150 | Z55: active
A56: 3418fff6-cf58-4e6e-9ba2-d7ebcec6660d | B56: The Body Lux: Brazilian Lymphatic Drainage & Body Contouring | C56: 46119 | D56: 2026-04 | E56: TRUE | F56: TRUE | G56: TRUE | H56: TRUE | I56: TRUE | J56: TRUE | K56: FALSE | L56: TRUE | M56: TRUE | N56: TRUE | O56: 350 | P56: 44 | Q56: 306 | S56: 46237 | T56: TRUE | U56: TRUE | V56: 97 | W56: 19154.84 | X56: AzyYF8UxkuGnF4HSg | Y56: 99 | Z56: active
A57: 43b477ab-a0ed-4fab-989a-1bfb423958a5 | B57: Robin Brooks Studio Salon | C57: 46120 | D57: 2026-04 | E57: TRUE | F57: TRUE | G57: FALSE | H57: FALSE | I57: FALSE | J57: FALSE | K57: FALSE | L57: FALSE | M57: FALSE | N57: FALSE | O57: 0 | P57: 0 | Q57: 0 | T57: FALSE | U57: FALSE | V57: 0 | W57: 0 | X57: 169qwZVG3vew95jc | Z57: cancelled
A58: c6779212-79b9-4ece-abba-9bffc8ad9da8 | B58: Luna Lucci Hair Salon | C58: 46121 | D58: 2026-04 | E58: TRUE | F58: TRUE | G58: TRUE | H58: TRUE | I58: TRUE | J58: TRUE | K58: FALSE | L58: TRUE | M58: TRUE | N58: TRUE | O58: 56 | P58: 56 | Q58: 0 | S58: 46234 | T58: TRUE | U58: TRUE | V58: 0 | W58: 0 | X58: AzqLyvV4LMNpW3BH | Y58: 100 | Z58: active
A59: 8c0837a5-8fa6-40a0-a408-11660e70c12d | B59: Abundance Beauty Salon & Lash Studio, Darien IL | C59: 46122 | D59: 2026-04 | E59: TRUE | F59: TRUE | G59: TRUE | H59: FALSE | I59: FALSE | J59: FALSE | K59: FALSE | L59: FALSE | M59: FALSE | N59: FALSE | O59: 0 | P59: 0 | Q59: 0 | T59: FALSE | U59: FALSE | V59: 0 | W59: 0 | X59: 16A0CZV5J1Am0HHy | Y59: 199 | Z59: active
A60: 00a7859a-ccbe-407f-a7a7-a907dfdcaedb | B60: Zen Hair Studio & Day Spa | C60: 46125 | D60: 2026-04 | E60: TRUE | F60: TRUE | G60: FALSE | H60: FALSE | I60: FALSE | J60: FALSE | K60: FALSE | L60: FALSE | M60: FALSE | N60: FALSE | O60: 0 | P60: 0 | Q60: 0 | T60: FALSE | U60: FALSE | V60: 0 | W60: 0 | X60: AzqgWYUxGx0mB1bjj | Y60: 249 | Z60: active
A61: c1a37a77-abf8-4560-b725-1309c7208b04 | B61: Kenny Braids | C61: 46127 | D61: 2026-04 | E61: TRUE | F61: TRUE | G61: TRUE | H61: TRUE | I61: TRUE | J61: TRUE | K61: TRUE | L61: TRUE | M61: TRUE | N61: TRUE | O61: 24 | P61: 22 | Q61: 2 | S61: 46237 | T61: TRUE | U61: TRUE | V61: 19 | W61: 452 | X61: 16BmDFUmp8xMxArlA | Y61: 120 | Z61: active
A62: d6b3c88a-6f69-404b-bee9-4097d7a3a949 | B62: Looks Threading & Hair Salon | C62: 46127 | D62: 2026-04 | E62: TRUE | F62: TRUE | G62: TRUE | H62: TRUE | I62: TRUE | J62: TRUE | K62: FALSE | L62: TRUE | M62: TRUE | N62: TRUE | O62: 30 | P62: 30 | Q62: 0 | S62: 46235 | T62: TRUE | U62: TRUE | V62: 1 | W62: 95 | X62: Azi8ufV9j8pF94XK | Y62: 200 | Z62: active
A63: c2561bac-445a-499b-94d3-02d7053bba8e | B63: Colors By Kyla | C63: 46128 | D63: 2026-04 | E63: TRUE | F63: TRUE | G63: TRUE | H63: TRUE | I63: TRUE | J63: FALSE | K63: TRUE | L63: TRUE | M63: TRUE | N63: TRUE | O63: 83 | P63: 25 | Q63: 58 | S63: 46232 | T63: TRUE | U63: TRUE | V63: 0 | W63: 0 | X63: cus_QOCBjvgZ2GNtel | Y63: 150 | Z63: active
A64: 1bc6e30e-65e2-4764-ab83-a91fbafb0ada | B64: Signature Beauty Clinic | C64: 46128 | D64: 2026-04 | E64: TRUE | F64: TRUE | G64: TRUE | H64: TRUE | I64: TRUE | J64: TRUE | K64: FALSE | L64: TRUE | M64: TRUE | N64: TRUE | O64: 9 | P64: 7 | Q64: 2 | S64: 46217 | T64: TRUE | U64: TRUE | V64: 6 | W64: 187
A65: 52a35418-3cfa-47ba-a975-75b14e81fe74 | B65: American Braids & Beauty | C65: 46133 | D65: 2026-04 | E65: TRUE | F65: TRUE | G65: TRUE | H65: TRUE | I65: TRUE | J65: TRUE | K65: FALSE | L65: TRUE | M65: TRUE | N65: TRUE | O65: 42 | P65: 42 | Q65: 0 | S65: 46237 | T65: TRUE | U65: TRUE | V65: 45 | W65: 1975 | X65: AzZq5zV8DDPrQ2335 | Y65: 249 | Z65: active
A66: c867f830-c111-49c7-add6-b3bd303897b0 | B66: Inner Bag Nail Spa | C66: 46134 | D66: 2026-04 | E66: TRUE | F66: TRUE | G66: FALSE | H66: FALSE | I66: FALSE | J66: FALSE | K66: FALSE | L66: FALSE | M66: FALSE | N66: FALSE | O66: 0 | P66: 0 | Q66: 0 | T66: FALSE | U66: FALSE | V66: 0 | W66: 0
A67: b72ca03c-b418-4540-930b-f88c26b6ebe4 | B67: Alyssa's Eyelash | C67: 46136 | D67: 2026-04 | E67: TRUE | F67: TRUE | G67: TRUE | H67: TRUE | I67: TRUE | J67: FALSE | K67: TRUE | L67: TRUE | M67: TRUE | N67: TRUE | O67: 35 | P67: 35 | Q67: 0 | S67: 46234 | T67: TRUE | U67: TRUE | V67: 0 | W67: 0 | X67: 169mwoVHYOJhhXJi | Y67: 250 | Z67: active
A68: 434295e9-2e31-4490-b218-c6afdb495cd7 | B68: Lineth balza skin care & massage | C68: 46140 | D68: 2026-04 | E68: TRUE | F68: TRUE | G68: FALSE | H68: FALSE | I68: FALSE | J68: FALSE | K68: FALSE | L68: FALSE | M68: FALSE | N68: FALSE | O68: 0 | P68: 0 | Q68: 0 | T68: FALSE | U68: FALSE | V68: 0 | W68: 0
A69: 6e29f2a1-f4b4-4502-b166-3be03192fd0e | B69: Eclipse Body Sculpting Studio | C69: 46146 | D69: 2026-05 | E69: TRUE | F69: TRUE | G69: TRUE | H69: TRUE | I69: TRUE | J69: FALSE | K69: TRUE | L69: TRUE | M69: TRUE | N69: TRUE | O69: 14 | P69: 12 | Q69: 2 | S69: 46228 | T69: TRUE | U69: TRUE | V69: 0 | W69: 0 | X69: cus_R0pWX1TjkTJs1x | Y69: 500 | Z69: active
A70: 183f1663-e374-4586-81ab-34f0060edeed | B70: Arch 4 U Threading Lounge (Lakeshore Publix) | C70: 46150 | D70: 2026-05 | E70: TRUE | F70: TRUE | G70: TRUE | H70: TRUE | I70: TRUE | J70: FALSE | K70: TRUE | L70: TRUE | M70: TRUE | N70: TRUE | O70: 7 | P70: 6 | Q70: 1 | S70: 46234 | T70: TRUE | U70: TRUE | V70: 0 | W70: 0 | X70: AzqfWHV32IOC1Y1U | Y70: 199 | Z70: active
A71: 7cd22cf7-382e-4ebd-a375-5c23b203368d | B71: JL Studio | C71: 46156 | D71: 2026-05 | E71: TRUE | F71: TRUE | G71: FALSE | H71: FALSE | I71: FALSE | J71: FALSE | K71: FALSE | L71: FALSE | M71: FALSE | N71: FALSE | O71: 0 | P71: 0 | Q71: 0 | T71: FALSE | U71: FALSE | V71: 0 | W71: 0 | X71: AzqeNwVGyY6ckRDO | Y71: 150 | Z71: active
A72: 00ea7e44-3e43-48f1-b728-b6caecc5a116 | B72: Vaibhav's Spa & Wellness | C72: 46157 | D72: 2026-05 | E72: TRUE | F72: TRUE | G72: TRUE | H72: TRUE | I72: TRUE | J72: FALSE | K72: TRUE | L72: TRUE | M72: TRUE | N72: TRUE | O72: 1 | P72: 1 | Q72: 0 | S72: 46204 | T72: TRUE | U72: FALSE | V72: 0 | W72: 0 | X72: AzqSZPVOoDjBq26dz
A73: 5d1e29d2-3af1-4ef4-881b-031d38fc937d | B73: Salon Studios By Christine | C73: 46161 | D73: 2026-05 | E73: TRUE | F73: TRUE | G73: TRUE | H73: TRUE | I73: TRUE | J73: TRUE | K73: FALSE | L73: TRUE | M73: TRUE | N73: TRUE | O73: 152 | P73: 6 | Q73: 146 | S73: 46235 | T73: TRUE | U73: TRUE | V73: 12 | W73: 773 | X73: AzhnbgV2w5t5yAGW | Y73: 199 | Z73: active
A74: 703a8130-0293-4c00-9cf0-bae2ddd72d33 | B74: Zoca Seed Spa - Los Angeles | C74: 46162 | D74: 2026-05 | E74: TRUE | F74: TRUE | G74: TRUE | H74: TRUE | I74: TRUE | J74: FALSE | K74: TRUE | L74: TRUE | M74: TRUE | N74: TRUE | O74: 30 | P74: 30 | Q74: 0 | S74: 46233 | T74: TRUE | U74: TRUE | V74: 0 | W74: 0 | X74: AzqRJiVK7p8kW3F4
A75: acad0f36-4617-4328-9c14-f8f04a598f69 | B75: Donna Skin and Body Care | C75: 46169 | D75: 2026-05 | E75: TRUE | F75: TRUE | G75: TRUE | H75: TRUE | I75: TRUE | J75: TRUE | K75: FALSE | L75: TRUE | M75: TRUE | N75: TRUE | O75: 105 | P75: 6 | Q75: 99 | S75: 46237 | T75: TRUE | U75: TRUE | V75: 0 | W75: 0 | X75: cus_Poh76IIXOBeYB0 | Y75: 150 | Z75: active
A76: 3a408f97-0f25-4863-ae1a-f059dde336ba | B76: Glow Beauty Bar | C76: 46174 | D76: 2026-06 | E76: TRUE | F76: TRUE | G76: TRUE | H76: TRUE | I76: TRUE | J76: TRUE | K76: TRUE | L76: TRUE | M76: TRUE | N76: TRUE | O76: 8 | P76: 2 | Q76: 4 | S76: 46234 | T76: TRUE | U76: TRUE | V76: 0 | W76: 0 | X76: AzykNvVLKf3tg2rDT | Z76: in_trial
A77: 87cdf2bb-2a1a-4aaf-be18-c564cb0b1380 | B77: Unique Beauty Salon | C77: 46175 | D77: 2026-06 | E77: TRUE | F77: TRUE | G77: TRUE | H77: TRUE | I77: TRUE | J77: FALSE | K77: TRUE | L77: TRUE | M77: TRUE | N77: TRUE | O77: 52 | P77: 12 | Q77: 40 | S77: 46237 | T77: TRUE | U77: TRUE | V77: 0 | W77: 0 | X77: 16BXJoVGR3oRAngO | Y77: 200 | Z77: active
A78: 8afb25bc-7109-4d13-b57a-8a4a783cf42c | B78: Reera skincare by Sahar | C78: 46178 | D78: 2026-06 | E78: TRUE | F78: TRUE | G78: TRUE | H78: TRUE | I78: TRUE | J78: TRUE | K78: TRUE | L78: TRUE | M78: TRUE | N78: TRUE | O78: 148 | P78: 4 | Q78: 144 | S78: 46236 | T78: TRUE | U78: TRUE | V78: 1 | W78: 155 | X78: Azyb1ZVLhB7phzpC | Y78: 149 | Z78: active
A79: a6fe6e5f-a5ef-48c7-8c68-2a3e3c4ec60b | B79: Lola’s Beauty Salon & Spa | C79: 46181 | D79: 2026-06 | E79: TRUE | F79: FALSE | G79: FALSE | H79: FALSE | I79: FALSE | J79: FALSE | K79: FALSE | L79: FALSE | M79: FALSE | N79: FALSE | O79: 0 | P79: 0 | Q79: 0 | T79: FALSE | U79: FALSE | V79: 0 | W79: 0 | X79: AzyXqCVLxat1b1Dk4
A80: 3b4edf59-dc89-4a5c-b715-210952a269d8 | B80: Signature PMU by Tara | C80: 46181 | D80: 2026-06 | E80: TRUE | F80: TRUE | G80: TRUE | H80: TRUE | I80: TRUE | J80: TRUE | K80: TRUE | L80: TRUE | M80: TRUE | N80: TRUE | O80: 25 | P80: 1 | Q80: 23 | S80: 46231 | T80: TRUE | U80: TRUE | V80: 17 | W80: 4678 | X80: AzqSUYVLxyVyl1Sto | Y80: 149 | Z80: active
A81: 001ab98f-78dd-4c5f-be56-33c5cbb6ca51 | B81: L&R Beauty | C81: 46181 | D81: 2026-06 | E81: TRUE | F81: TRUE | G81: TRUE | H81: TRUE | I81: TRUE | J81: TRUE | K81: FALSE | L81: TRUE | M81: TRUE | N81: TRUE | O81: 11 | P81: 4 | Q81: 7 | S81: 46226 | T81: TRUE | U81: TRUE | V81: 1 | W81: 17 | X81: AzqVnTUtlj7Ua2MIu | Y81: 199 | Z81: active
A82: 533bbd60-2581-4a79-9624-2bcd8fc6c044 | B82: SUR MedSpa (Medical Spa) - Marietta, GA | C82: 46182 | D82: 2026-06 | E82: TRUE | F82: TRUE | G82: TRUE | H82: TRUE | I82: TRUE | J82: TRUE | K82: TRUE | L82: TRUE | M82: TRUE | N82: TRUE | O82: 32 | P82: 32 | Q82: 0 | S82: 46237 | T82: TRUE | U82: TRUE | V82: 0 | W82: 0 | X82: 6oZmhVLgAthnMfr | Y82: 297 | Z82: active
A83: 966f3e29-ea65-4c8a-96ef-53427422882d | B83: Bodies-N-Motion LLC | C83: 46182 | D83: 2026-06 | E83: TRUE | F83: TRUE | G83: TRUE | H83: TRUE | I83: TRUE | J83: TRUE | K83: FALSE | L83: TRUE | M83: TRUE | N83: TRUE | O83: 2 | P83: 2 | Q83: 0 | S83: 46185 | T83: TRUE | U83: FALSE | V83: 2 | W83: 210 | X83: AzhqL2V2XHc6D8wEA | Y83: 249 | Z83: active
A84: 82ce3fbb-32b8-489f-ae35-4cd0efe34fa8 | B84: Lumiere Medspa LLC | C84: 46182 | D84: 2026-06 | E84: TRUE | F84: TRUE | G84: TRUE | H84: TRUE | I84: TRUE | J84: TRUE | K84: TRUE | L84: TRUE | M84: TRUE | N84: TRUE | O84: 8 | P84: 8 | Q84: 0 | S84: 46224 | T84: TRUE | U84: TRUE | V84: 1 | W84: 100 | X84: AzqDccVM5Cfjg2SXT | Y84: 248 | Z84: active
A85: ef9e7a97-edfa-4db3-94d1-dc7fdbce7bb0 | B85: Peggy's Mobile Hair Braiding and Dreadlocks | C85: 46183 | D85: 2026-06 | E85: TRUE | F85: TRUE | G85: TRUE | H85: TRUE | I85: TRUE | J85: FALSE | K85: TRUE | L85: TRUE | M85: TRUE | N85: TRUE | O85: 6 | P85: 6 | Q85: 0 | S85: 46236 | T85: TRUE | U85: TRUE | V85: 0 | W85: 0 | X85: 16CH9nUnpd0zW45NH | Y85: 199 | Z85: non_renewing
A86: 2153eaf7-af4e-45f1-bc4e-0be39b8e57bf | B86: Level up with Sam | C86: 46184 | D86: 2026-06 | E86: TRUE | F86: TRUE | G86: FALSE | H86: FALSE | I86: FALSE | J86: FALSE | K86: FALSE | L86: FALSE | M86: FALSE | N86: FALSE | O86: 0 | P86: 0 | Q86: 0 | T86: FALSE | U86: FALSE | V86: 0 | W86: 0 | X86: AzhjxVVJLCLQCadW | Y86: 150 | Z86: active
A87: bc1211a0-0a9f-46ad-8419-6fb46149ca94 | B87: Garden Glam Beauty | C87: 46185 | D87: 2026-06 | E87: TRUE | F87: TRUE | G87: TRUE | H87: TRUE | I87: TRUE | J87: FALSE | K87: TRUE | L87: TRUE | M87: TRUE | N87: TRUE | O87: 53 | P87: 17 | Q87: 36 | S87: 46235 | T87: TRUE | U87: TRUE | V87: 0 | W87: 0 | X87: 16CJlsUuvECiE1f2i | Y87: 249 | Z87: active
A88: 358e8178-6044-4c44-b28d-9400f6dcefa3 | B88: Sankofa Braiding & Natural HairCare | C88: 46188 | D88: 2026-06 | E88: TRUE | F88: FALSE | G88: FALSE | H88: FALSE | I88: FALSE | J88: FALSE | K88: FALSE | L88: FALSE | M88: FALSE | N88: FALSE | O88: 0 | P88: 0 | Q88: 0 | T88: FALSE | U88: FALSE | V88: 0 | W88: 0 | X88: AzZXJJVMdLCmN1qhl
A89: 7c1e0100-3a01-4b8b-91e2-643fc6c844b4 | B89: Heights Retreat Salon and Spa - facial massage pedicure manicure & lash Houston TX | C89: 46189 | D89: 2026-06 | E89: TRUE | F89: TRUE | G89: TRUE | H89: TRUE | I89: TRUE | J89: TRUE | K89: FALSE | L89: TRUE | M89: TRUE | N89: TRUE | O89: 14 | P89: 8 | Q89: 4 | S89: 46236 | T89: TRUE | U89: TRUE | V89: 8 | W89: 412 | X89: 16BZ98Ur9O82a3o07 | Y89: 249 | Z89: active
A90: 7e641122-2d20-48f5-a6c7-1ba4ff5b991d | B90: Natasha salon | C90: 46190 | D90: 2026-06 | E90: TRUE | F90: TRUE | G90: TRUE | H90: TRUE | I90: TRUE | J90: FALSE | K90: TRUE | L90: TRUE | M90: TRUE | N90: TRUE | O90: 4 | P90: 3 | Q90: 1 | S90: 46193 | T90: TRUE | U90: FALSE | V90: 1 | W90: 200
A91: 86cc7d1a-6d76-4a49-8f3c-11ad32431417 | B91: Viora Beauty Spa | C91: 46190 | D91: 2026-06 | E91: TRUE | F91: TRUE | G91: TRUE | H91: TRUE | I91: TRUE | J91: TRUE | K91: TRUE | L91: TRUE | M91: TRUE | N91: TRUE | O91: 318 | P91: 35 | Q91: 43 | S91: 46237 | T91: TRUE | U91: TRUE | V91: 45 | W91: 4026.35 | X91: 16BSCSVMp7TmJ2IC1 | Y91: 149 | Z91: active
A92: 558729b7-6f19-4de4-b76a-59cb9192f294 | B92: Designs by Terrie | Hair Salon | C92: 46190 | D92: 2026-06 | E92: TRUE | F92: TRUE | G92: TRUE | H92: TRUE | I92: TRUE | J92: FALSE | K92: TRUE | L92: TRUE | M92: TRUE | N92: TRUE | O92: 3 | P92: 3 | Q92: 0 | S92: 46211 | T92: TRUE | U92: TRUE | V92: 0 | W92: 0 | X92: cus_PSCqp2cfPX10XX | Y92: 70 | Z92: active
A93: 71031ed6-149b-4398-9244-5b90c7a565ff | B93: Amenity Wax Spot & Spa | C93: 46190 | D93: 2026-06 | E93: TRUE | F93: TRUE | G93: TRUE | H93: TRUE | I93: TRUE | J93: FALSE | K93: TRUE | L93: TRUE | M93: TRUE | N93: TRUE | O93: 34 | P93: 23 | Q93: 10 | S93: 46234 | T93: TRUE | U93: TRUE | V93: 6 | W93: 155 | X93: 16BaFTVFSXmKn57oO | Y93: 150 | Z93: active
A94: 43d2e527-f67d-4c2a-8f20-b399b82640c6 | B94: Sinkor Beauty Salon - Hair, Spa & Beauty | C94: 46192 | D94: 2026-06 | E94: TRUE | F94: TRUE | G94: TRUE | H94: TRUE | I94: FALSE | J94: FALSE | K94: FALSE | L94: FALSE | M94: FALSE | N94: FALSE | O94: 0 | P94: 0 | Q94: 0 | T94: FALSE | U94: FALSE | V94: 0 | W94: 0 | X94: AzZcOiUwRg8tf3wBX | Y94: 100 | Z94: active
A95: ceebf0e9-19ca-4f99-8adc-b34f9e75b1bd | B95: Shine BE Happy - Hair, Nails & Skincare | C95: 46195 | D95: 2026-06 | E95: TRUE | F95: TRUE | G95: TRUE | H95: TRUE | I95: TRUE | J95: FALSE | K95: TRUE | L95: TRUE | M95: TRUE | N95: TRUE | O95: 7 | P95: 0 | Q95: 3 | S95: 46237 | T95: TRUE | U95: TRUE | V95: 0 | W95: 0 | X95: cus_PM7OMgw7oXsQfD | Y95: 120 | Z95: active
A96: 1d25fd64-ff11-478c-b68c-fd6f6fc94bce | B96: The Allure Marian Unisex Salon | C96: 46195 | D96: 2026-06 | E96: TRUE | F96: TRUE | G96: TRUE | H96: TRUE | I96: TRUE | J96: FALSE | K96: TRUE | L96: TRUE | M96: TRUE | N96: TRUE | O96: 5 | P96: 5 | Q96: 0 | R96: SQUARE | S96: 46237 | T96: TRUE | U96: TRUE | V96: 0 | W96: 0 | X96: 16CG1rUtZh3UL1rnM | Y96: 249 | Z96: active
A97: d8a536db-871e-4331-b328-027d4b5c17a4 | B97: Kismet Beauty Collection | C97: 46195 | D97: 2026-06 | E97: TRUE | F97: TRUE | G97: TRUE | H97: TRUE | I97: TRUE | J97: TRUE | K97: TRUE | L97: TRUE | M97: TRUE | N97: TRUE | O97: 98 | P97: 13 | Q97: 77 | S97: 46237 | T97: TRUE | U97: TRUE | V97: 56 | W97: 3741.55 | X97: 169zslVNIkWBg2ChA | Y97: 149 | Z97: active
A98: 601f25e3-f49e-433f-8d64-7e1f1f11b188 | B98: Ksweetshaircompany® Medical Wigs & Hair Restoration | C98: 46195 | D98: 2026-06 | E98: TRUE | F98: TRUE | G98: TRUE | H98: TRUE | I98: TRUE | J98: FALSE | K98: TRUE | L98: TRUE | M98: TRUE | N98: TRUE | O98: 0 | P98: 0 | Q98: 0 | T98: FALSE | U98: FALSE | V98: 0 | W98: 0 | X98: 169sM2UwERmUE1Jta | Y98: 99 | Z98: active
A99: 94675ce6-a2ed-4680-b6be-05623a45e196 | B99: Celebrityz Barbershop | C99: 46196 | D99: 2026-06 | E99: TRUE | F99: TRUE | G99: TRUE | H99: TRUE | I99: TRUE | J99: FALSE | K99: TRUE | L99: TRUE | M99: TRUE | N99: TRUE | O99: 39 | P99: 39 | Q99: 0 | S99: 46237 | T99: TRUE | U99: TRUE | V99: 4 | W99: 230 | X99: cus_QZsLOmGGygvs4X | Y99: 774 | Z99: active
A100: 4fa91a08-d4af-4e73-a8aa-e69e8c12996b | B100: CELEBRITYZ BARBERSHOP | C100: 46196 | D100: 2026-06 | E100: TRUE | F100: TRUE | G100: TRUE | H100: TRUE | I100: TRUE | J100: FALSE | K100: TRUE | L100: TRUE | M100: TRUE | N100: TRUE | O100: 22 | P100: 21 | Q100: 1 | S100: 46236 | T100: TRUE | U100: TRUE | V100: 2 | W100: 100 | X100: cus_QZsLOmGGygvs4X | Y100: 774 | Z100: active
...

Sheet Cohort Retention
A1: Cohort retention — 178 legitimate locations
A2: Same definitions as Adoption Funnel; TOTAL reconciles to it exactly.
A4: Cohort | B4: Entered | C4: Enabled (flag) | D4: Operationally live | E4: Live in last 30d | F4: % of op. live still live
A5: 2026-01 | B5: =SUMPRODUCT(--(Locations!$D$2:$D$179=$A5)) | C5: =SUMPRODUCT(--(Locations!$D$2:$D$179=$A5),--(Locations!$M$2:$M$179=TRUE)) | D5: =SUMPRODUCT(--(Locations!$D$2:$D$179=$A5),--(Locations!$T$2:$T$179=TRUE)) | E5: =SUMPRODUCT(--(Locations!$D$2:$D$179=$A5),--(Locations!$S$2:$S$179>=Summary!$B$3-30)) | F5: =IFERROR(E5/D5,0)
A6: 2026-02 | B6: =SUMPRODUCT(--(Locations!$D$2:$D$179=$A6)) | C6: =SUMPRODUCT(--(Locations!$D$2:$D$179=$A6),--(Locations!$M$2:$M$179=TRUE)) | D6: =SUMPRODUCT(--(Locations!$D$2:$D$179=$A6),--(Locations!$T$2:$T$179=TRUE)) | E6: =SUMPRODUCT(--(Locations!$D$2:$D$179=$A6),--(Locations!$S$2:$S$179>=Summary!$B$3-30)) | F6: =IFERROR(E6/D6,0)
A7: 2026-03 | B7: =SUMPRODUCT(--(Locations!$D$2:$D$179=$A7)) | C7: =SUMPRODUCT(--(Locations!$D$2:$D$179=$A7),--(Locations!$M$2:$M$179=TRUE)) | D7: =SUMPRODUCT(--(Locations!$D$2:$D$179=$A7),--(Locations!$T$2:$T$179=TRUE)) | E7: =SUMPRODUCT(--(Locations!$D$2:$D$179=$A7),--(Locations!$S$2:$S$179>=Summary!$B$3-30)) | F7: =IFERROR(E7/D7,0)
A8: 2026-04 | B8: =SUMPRODUCT(--(Locations!$D$2:$D$179=$A8)) | C8: =SUMPRODUCT(--(Locations!$D$2:$D$179=$A8),--(Locations!$M$2:$M$179=TRUE)) | D8: =SUMPRODUCT(--(Locations!$D$2:$D$179=$A8),--(Locations!$T$2:$T$179=TRUE)) | E8: =SUMPRODUCT(--(Locations!$D$2:$D$179=$A8),--(Locations!$S$2:$S$179>=Summary!$B$3-30)) | F8: =IFERROR(E8/D8,0)
A9: 2026-05 | B9: =SUMPRODUCT(--(Locations!$D$2:$D$179=$A9)) | C9: =SUMPRODUCT(--(Locations!$D$2:$D$179=$A9),--(Locations!$M$2:$M$179=TRUE)) | D9: =SUMPRODUCT(--(Locations!$D$2:$D$179=$A9),--(Locations!$T$2:$T$179=TRUE)) | E9: =SUMPRODUCT(--(Locations!$D$2:$D$179=$A9),--(Locations!$S$2:$S$179>=Summary!$B$3-30)) | F9: =IFERROR(E9/D9,0)
A10: 2026-06 | B10: =SUMPRODUCT(--(Locations!$D$2:$D$179=$A10)) | C10: =SUMPRODUCT(--(Locations!$D$2:$D$179=$A10),--(Locations!$M$2:$M$179=TRUE)) | D10: =SUMPRODUCT(--(Locations!$D$2:$D$179=$A10),--(Locations!$T$2:$T$179=TRUE)) | E10: =SUMPRODUCT(--(Locations!$D$2:$D$179=$A10),--(Locations!$S$2:$S$179>=Summary!$B$3-30)) | F10: =IFERROR(E10/D10,0)
A11: 2026-07 | B11: =SUMPRODUCT(--(Locations!$D$2:$D$179=$A11)) | C11: =SUMPRODUCT(--(Locations!$D$2:$D$179=$A11),--(Locations!$M$2:$M$179=TRUE)) | D11: =SUMPRODUCT(--(Locations!$D$2:$D$179=$A11),--(Locations!$T$2:$T$179=TRUE)) | E11: =SUMPRODUCT(--(Locations!$D$2:$D$179=$A11),--(Locations!$S$2:$S$179>=Summary!$B$3-30)) | F11: =IFERROR(E11/D11,0)
A12: 2026-08 | B12: =SUMPRODUCT(--(Locations!$D$2:$D$179=$A12)) | C12: =SUMPRODUCT(--(Locations!$D$2:$D$179=$A12),--(Locations!$M$2:$M$179=TRUE)) | D12: =SUMPRODUCT(--(Locations!$D$2:$D$179=$A12),--(Locations!$T$2:$T$179=TRUE)) | E12: =SUMPRODUCT(--(Locations!$D$2:$D$179=$A12),--(Locations!$S$2:$S$179>=Summary!$B$3-30)) | F12: =IFERROR(E12/D12,0)
A13: TOTAL | B13: =SUM(B5:B12) | C13: =SUM(C5:C12) | D13: =SUM(D5:D12) | E13: =SUM(E5:E12) | F13: =IFERROR(E13/D13,0)

Sheet Bookings and Revenue
A1: Bookings, payments and displaced incumbents
A2: Booking figures use the 'earned' definition. v1 used migration_source IS NULL alone and overstated volume ~2.4x.
A4: Metric | B4: Value | C4: What it is
A5: Earned bookings since launch | B5: =SUM(Locations!$O$2:$O$445) | C5: created 30/01/26 to as-of, no migration tag
A6: Customer-made bookings | B6: =SUM(Locations!$P$2:$P$445) | C6: created_by_type EC or CLIENT — proves demand
A7: Staff-made bookings | B7: =SUM(Locations!$Q$2:$Q$445) | C7: created_by_type SP
A8: Pre-launch untagged (EXCLUDED) | B8: =SUM(Locations!$R$2:$R$445) | C8: imported history with no migration_source
A9: Tagged migration (EXCLUDED) | B9: =SUM(Locations!$S$2:$S$445) | C9: explicitly flagged imports
A10: Future-dated (EXCLUDED) | B10: =SUM(Locations!$T$2:$T$445) | C10: impossible created_at values
A11: Value processed (USD) | B11: =SUM(Locations!$AA$2:$AA$445) | C11: completed payments created on/after 30/01/26
A12: Locations that processed a payment | B12: =SUMPRODUCT(--(Locations!$Z$2:$Z$445>0))
A14: All-entity totals (whole scheduling.* schema): 9,605 earned bookings · 4,627 customer-made · $328,021 completed payments POST-LAUNCH across 139 accounts. All-time completed payments are $646,104, but $318,083 of that predates the 30/01/26 launch and must not be presented as product value. Live database, queried 04/08/26.
A16: INCUMBENT SYSTEMS MIGRATED FROM
A17: Hardcoded. Source: scheduling.bookings.migration_source, 03/08/26. Only 14 accounts imported history — the rest had nothing to move or never fully switched.
A18: Prior system | B18: Bookings migrated | C18: Accounts
A19: Zoca internal ops | B19: 15756 | C19: 2
A20: Square | B20: 7748 | C20: 4
A21: Vagaro | B21: 6321 | C21: 1
A22: Fresha | B22: 4984 | C22: 1
A23: Booksy | B23: 4088 | C23: 1
A24: GlossGenius | B24: 3978 | C24: 1
A25: Acuity | B25: 3338 | C25: 4
A26: Setmore | B26: 1158 | C26: 1
A27: GoDaddy | B27: 56 | C27: 2

Sheet Objection Themes
A1: Why accounts did not convert
A2: Mechanical evidence is proven by the funnel. Stated evidence is directional only and cannot be counted per account.
A4: MECHANICAL — proven
A5: Finding | B5: Value | C5: Why it matters
A6: Locations that skipped payment setup | B6: =SUMPRODUCT(--(Locations!$K$2:$K$445=TRUE)) | C6: No deposits, no no-show fees. Without payments it is a diary, and a diary loses to the incumbent.
A7: Locations that configured payments | B7: =SUMPRODUCT(--(Locations!$J$2:$J$445=TRUE))
A8: Enabled (flag) but never earned a booking | B8: =SUMPRODUCT(--(Locations!$M$2:$M$445=TRUE),--(Locations!$O$2:$O$445=0)) | C8: Completed every setup step, then nothing. Setup completion is being mistaken for adoption.
A9: Operationally live but dormant 30d+ | B9: =SUMPRODUCT(--(Locations!$X$2:$X$445=TRUE),--(Locations!$W$2:$W$445<Summary!$B$3-30)) | C9: The core retention problem
A10: Locations that imported from a rival | B10: =SUMPRODUCT(--(Locations!$U$2:$U$445<>"")) | C10: Very few actually moved their history across.
A13: STATED — topic prevalence across 1,829 scheduling calls, 01/11/25 to 03/08/26
A14: Hardcoded. Regex over sales.fireflies_meeting.summary. CAUTION: these calls carry no usable entity_id, so these CANNOT be counted per account. Never present as 'N accounts said X'. Counts are topic prevalence only and were NOT re-audited for the word-boundary defect — treat as indicative.
A15: Topic | B15: Calls | C15: Share of 1,829 | D15: Comment
A16: Deferred / 'not right now' | B16: 441 | C16: =B16/1829
A17: Migration or data-transfer effort | B17: 247 | C17: =B17/1829
A18: Payments, deposits, no-show fees | B18: 227 | C18: =B18/1829 | D18: Matches the mechanical finding
A19: Contract / lock-in language | B19: 215 | C19: =B19/1829 | D19: Noisy
A20: Named an incumbent competitor | B20: 303 | C20: =B20/1829 | D20: The reliable signal
A21: Explicit refusal language | B21: 174 | C21: =B21/1829
A22: Prefers phone / walk-in / manual | B22: 119 | C22: =B22/1829
A23: Price or budget | B23: 69 | C23: =B23/1829
A24: Staff resistance or complexity | B24: 42 | C24: =B24/1829
A26: Incumbents named (validated 04/08/26 with word boundaries): Square 101 in genuine product context — NOT the 269 originally reported, which matched non-product uses of the word. Vagaro 105 and Acuity 26 verified clean (bounded = unbounded). Booksy 46 · Mindbody 39 · Fresha 35 · StyleSeat 11 · GlossGenius 11 · other 43 — not individually re-audited.
A28: VERIFIED BY READING CALL EXCERPTS BY HAND
A29: • Feature gaps keep the old system alive — staff revenue and commission reporting, clock-in/out, staff permission levels, calendar column-per-staff view, selective client blocking, package and membership migration, intake forms.
A30: • Payment processor economics — Stripe rates raised as a negotiation point rather than accepted.
A31: • Base subscription price — $149/month cited as unaffordable by an account under budget freeze; a whole-platform objection, not a scheduling one.
A32: • Rollback on confusion — at least one account asked for the booking system to be revoked 'to reduce confusion and inefficiency' after enabling it.
A33: • Free is the wedge that works — where the pitch replaces a paid incumbent at no cost, it lands.

Sheet Data Quality
A1: Data quality — defects in the source data itself
A2: Read this before trusting any booking count, here or anywhere else in Zoca reporting.
A4: Defect | B4: Scale | C4: Consequence | D4: Handling in v2
A5: Imported history carries no migration_source tag | B5: =SUM(Locations!$R$2:$R$445) | C5: 33 entities' pre-launch bookings look organic. v1 counted them as earned and overstated volume ~2.4x. | D5: Excluded: earned bookings require created_at >= 30/01/26
A6: Future-dated created_at values | B6: =SUM(Locations!$T$2:$T$445) | C6: Bookings created in 2027. They automatically satisfy any 'last 30 days' test. | D6: Excluded: earned bookings require created_at <= as-of
A7: is_scheduling_enabled is unreliable | B7: =SUMPRODUCT(--(Locations!$M$2:$M$445=FALSE),--(Locations!$O$2:$O$445>0)) | C7: Locations take real bookings while flagged FALSE (all also show onboarding_completed FALSE). | D7: Reported separately as 'Operationally live'
A8: Duplicate Chargebee customer records | B8: 89 | C8: 2,026 records hold 1,799 distinct emails. Counting customer_id over-counts businesses. | D8: All account counts resolve to entity_id first
A9: scheduling.onboarding has two entity ids | B9: — | C9: entity_id = parent business (joins entities.businesses); location_entity_id = the location (joins bookings, Chargebee, GBP). Joining on the wrong one returns zero rows and no error. | D9: location_entity_id used throughout
A10: Fireflies entity_id is 1.9% populated | B10: — | C10: Calls cannot be joined to accounts directly. | D10: Attribution via participants email → chargebee.customers.email
A11: cx.open_issues / cx.churn_potential stopped writing 14/01/26 | B11: — | C11: Two account-health tables went dark two weeks before scheduling launched, so there is no qualitative feed for the rollout period. | D11: Not used; flagged for investigation
