Workbook

Sheet README
A1: SUPERSEDED - JULY PITCH FIGURES ON THIS SHEET ARE WRONG. DO NOT QUOTE.
A2: Audit 03/08/26: the offer regex had no word boundary, so 'our booking platform' also matched 'y-our booking platform'. Reps saying "YOUR booking platform" (the customer's existing system) were counted as Zoca pitches - 55% false positives on a 22-call sample. Counting was also per Chargebee customer record, and 89 emails map to multiple records. CORRECTED: 63 accounts pitched (not 98); 8 reached scheduling enabled (not 15); 12.7% conversion (not 15%).
A3: UNAFFECTED: adoption funnel (444 locations, 368 enabled, 147 booking in 30d), payments ($645,568 / 139 accounts), cohort retention and migration sources use no regex and stand as published.
A4: Scheduling — pitch, conversion and non-conversion
A7: Prepared | B7: 03/08/26
A8: Question | B8: How many accounts was scheduling pitched to, how many converted, and why did the rest not?
A9: Primary source | B9: Aurora (Postgres) via Metabase database 7 — scheduling.*, chargebee.*, sales.fireflies_meeting, cx.*
A10: Pitch window analysed | B10: 01/07/26 - 31/07/26 (July 2026)
A11: Adoption window analysed | B11: 30/01/26 - 31/07/26 (full scheduling rollout to date)
A13: HEADLINE
A14: Accounts pitched in July 2026 | B14: 98
A15: Of those, reached 'scheduling enabled' | B15: 15 (15%)
A16: Of those, never started onboarding | B16: 76 (78%)
A17: Value processed through scheduling to date | B17: $645,568 across 139 accounts
A19: HOW 'PITCHED' WAS DERIVED
A20: 1 | B20: No system records the pitch as a field. It was reconstructed from call transcripts.
A21: 2 | B21: All 1,051 July calls in sales.fireflies_meeting; 1,046 carry a transcript.
A22: 3 | B22: Attendee emails extracted from 'participants' by regex (field is inconsistently formatted - some JSON arrays, some comma-separated strings, so a JSON cast fails).
A23: 4 | B23: Internal domains dropped: zoca.com, timelyai.com, zoca.ai.
A24: 5 | B24: Remaining emails joined to chargebee.customers.email to identify the account.
A25: 6 | B25: A call counts as an OFFER if the transcript contains Zoca offering its own scheduling ('our own booking platform', 'we have launched', 'comes with a booking platform', 'no extra charges', 'included in your subscription', 'show you our scheduling platform').
A26: 7 | B26: Accounts already live on Zoca scheduling before the call are SUBTRACTED - offer language to an existing user is support, not a pitch. This step removes 12 accounts. Without it the answer is 110 and it is wrong.
A27: 8 | B27: The regex was written only after all 141 candidate excerpts were read by hand; it formalises that read.
A29: COVERAGE LIMITS - READ BEFORE QUOTING
A30: 98 is a floor, not a ceiling | B30: Only accounts whose attendee email matched a Chargebee customer record are counted. 230 of 433 distinct external emails matched (53%).
A31: Prospects excluded | B31: ~84 further external emails were pitched but match no Chargebee customer. Those are new-business pitches, not upsells to the existing book.
A32: Repeat pitching | B32: 284 individual July calls carried offer language against 98 accounts - roughly 2.9 offer-bearing calls per account.
A33: Attribution is temporal, not causal | B33: An onboarding record created after the call is attributed to the pitch. Reasonable in a one-month window; not proven.
A34: Locations vs accounts | B34: The adoption funnel counts 444 LOCATIONS. Only 156 map to an active billed account. Never quote 444 as an account count.
A36: SCHEMA TRAP
A37: Join key | B37: scheduling.onboarding.entity_id matches NOTHING - zero overlap with bookings or Chargebee. The account key is location_entity_id. A join on entity_id returns a valid-looking all-zero result rather than an error.
A39: SHEET GUIDE
A40: Summary | B40: Headline metrics, calculated live from the data sheets
A41: July Pitch Funnel | B41: 1,051 calls narrowed to 98 pitched accounts, stage by stage
A42: Pitched Accounts | B42: Account-level detail: 110 rows = 98 pitched + 12 already-live (flagged in column J)
A43: Adoption Funnel | B43: All 444 onboarding locations, stage by stage
A44: Locations | B44: Account-level detail for all 444 locations
A45: Cohort Retention | B45: Monthly cohorts and how many are still taking bookings
A46: Bookings and Revenue | B46: Booking mix, payments processed, incumbent systems migrated from
A47: Objection Themes | B47: Topic prevalence across 1,829 scheduling calls (Nov 25 - Aug 26)
A48: Instrumentation Gaps | B48: Where a pitch record should live and what is actually there
A50: CALL LINKS | B50: Pitched Accounts column I is a hyperlink to the first July call where the offer was made (sales.fireflies_meeting.transcript_url). Columns AA-AE carry the offer-call dates, call length and raw URLs. Opening a link requires a Fireflies account with access to that recording.
A52: BUSINESS NAMES | B52: Locations column B carries the business name, resolved from GBP first, then GBP logs, then Chargebee, then entities.businesses. 395 of 444 resolved (89%); 49 show '(name not on file)'. The last column records which source each name came from. Important: entities.businesses keys on the PARENT entity (scheduling.onboarding.entity_id), while gbp.locations keys on the LOCATION (location_entity_id) — the two are different entities and joining on the wrong one returns zero rows.
A54: CANONICAL SOURCE | B54: Master copy: ~/zoca-account-health-dashboard/docs/scheduling-analysis-03-08-26.xlsx • Share copy: ~/Downloads/Zoca-Scheduling-Adoption-Jul2026-v1.xlsx (v1, generated 03/08/26). If the two disagree, the master wins. Re-export from the master rather than editing the share copy; bump to v2 in the filename if the numbers are refreshed.

Sheet Summary
A1: SUPERSEDED - JULY PITCH FIGURES ON THIS SHEET ARE WRONG. DO NOT QUOTE.
A2: Audit 03/08/26: the offer regex had no word boundary, so 'our booking platform' also matched 'y-our booking platform'. Reps saying "YOUR booking platform" (the customer's existing system) were counted as Zoca pitches - 55% false positives on a 22-call sample. Counting was also per Chargebee customer record, and 89 emails map to multiple records. CORRECTED: 63 accounts pitched (not 98); 8 reached scheduling enabled (not 15); 12.7% conversion (not 15%).
A3: UNAFFECTED: adoption funnel (444 locations, 368 enabled, 147 booking in 30d), payments ($645,568 / 139 accounts), cohort retention and migration sources use no regex and stand as published.
A4: Summary — scheduling pitch and adoption
A6: As-of date (drives the 30-day activity tests) | B6: =DATE(2026,8,3) | C6: Blue = input. Change this to re-date every 30-day metric in the workbook.
A8: JULY 2026 PITCH | B8: Value | C8: Notes
A9: Accounts pitched | B9: =SUMPRODUCT(--('Pitched Accounts'!$J$2:$J$111=FALSE)) | C9: Offer made and not already live on Zoca scheduling
A10: …that started onboarding | B10: =SUMPRODUCT(--('Pitched Accounts'!$J$2:$J$111=FALSE),--('Pitched Accounts'!$K$2:$K$111<>"")) | C10: Onboarding record created after the call
A11: …that reached scheduling enabled | B11: =SUMPRODUCT(--('Pitched Accounts'!$J$2:$J$111=FALSE),--('Pitched Accounts'!$N$2:$N$111=TRUE)) | C11: The conversion number
A12: …that never started | B12: =SUMPRODUCT(--('Pitched Accounts'!$J$2:$J$111=FALSE),--('Pitched Accounts'!$K$2:$K$111=""))
A13: Pitch-to-activation rate | B13: =B8/B6 | C13: Enabled ÷ pitched
A14: Accounts excluded (already live at pitch) | B14: =SUMPRODUCT(--('Pitched Accounts'!$J$2:$J$111=TRUE)) | C14: Offer language spoken to an existing user = support
A15: Offer-bearing calls in July | B15: 284 | C15: Hardcoded. Source: count of July transcripts matching the offer regex.
A17: ADOPTION TO DATE (444 LOCATIONS) | B17: Value | C17: Notes
A18: Locations entered onboarding | B18: =COUNTA(Locations!$A$2:$A$445)
A19: Scheduling enabled | B19: =SUMPRODUCT(--(Locations!$M$2:$M$445=TRUE))
A20: Ever took a booking | B20: =SUMPRODUCT(--(Locations!$O$2:$O$445>0))
A21: Took a booking in last 30 days | B21: =SUMPRODUCT(--(Locations!$T$2:$T$445>=$B$3-30)) | C21: Relative to as-of date
A22: Dormant share of enabled | B22: =1-B18/B16 | C22: Enabled but not booking in last 30 days
A23: Payments configured | B23: =SUMPRODUCT(--(Locations!$J$2:$J$445=TRUE))
A24: Payments explicitly skipped | B24: =SUMPRODUCT(--(Locations!$K$2:$K$445=TRUE)) | C24: The single biggest drop-off in the funnel
A25: Value processed (USD) | B25: =SUM(Locations!$V$2:$V$445) | C25: Covers the 444 onboarding locations only. All-entity total is $645,568 across 139 accounts — one paying entity sits outside the onboarding table (delta $13,532).
A26: Accounts that processed a payment | B26: =SUMPRODUCT(--(Locations!$U$2:$U$445>0)) | C26: 138 here vs 139 all-entity, same reason as above.
A27: Locations linked to a billed account | B27: =SUMPRODUCT(--(Locations!$W$2:$W$445<>"")) | C27: 444 are LOCATIONS, not accounts

Sheet July Pitch Funnel
A1: SUPERSEDED - JULY PITCH FIGURES ON THIS SHEET ARE WRONG. DO NOT QUOTE.
A2: Audit 03/08/26: the offer regex had no word boundary, so 'our booking platform' also matched 'y-our booking platform'. Reps saying "YOUR booking platform" (the customer's existing system) were counted as Zoca pitches - 55% false positives on a 22-call sample. Counting was also per Chargebee customer record, and 89 emails map to multiple records. CORRECTED: 63 accounts pitched (not 98); 8 reached scheduling enabled (not 15); 12.7% conversion (not 15%).
A3: UNAFFECTED: adoption funnel (444 locations, 368 enabled, 147 booking in 30d), payments ($645,568 / 139 accounts), cohort retention and migration sources use no regex and stand as published.
A4: July 2026 — from every recorded call down to 98 pitched accounts
A5: Stages 1-5 are call-level counts fixed by the source query. Stages 6-9 calculate live from the Pitched Accounts sheet.
A7: # | B7: Stage | C7: Count | D7: Unit | E7: Note
A8: 1 | B8: Calls recorded in July 2026 | C8: 1051 | D8: calls | E8: sales.fireflies_meeting
A9: 2 | B9: …with a transcript | C9: 1046 | D9: calls | E9: 5 rows have no transcript
A10: 3 | B10: …with an external (non-Zoca) participant | C10: 777 | D10: calls | E10: 433 distinct external emails
A11: 4 | B11: …mapped to a known Chargebee account | C11: 462 | D11: calls | E11: 230 distinct accounts
A12: 5 | B12: Accounts whose call discussed booking/scheduling | C12: 141 | D12: accounts | E12: product mentioned at all
A13: 6 | B13: Accounts that heard an explicit offer | C13: =SUMPRODUCT(--('Pitched Accounts'!$H$2:$H$111>0)) | D13: accounts | E13: offer regex matched
A14: 7 | B14: …minus those already live on Zoca scheduling | C14: =-SUMPRODUCT(--('Pitched Accounts'!$J$2:$J$111=TRUE)) | D14: accounts | E14: support, not a pitch
A15: 8 | B15: ACCOUNTS PITCHED | C15: =SUMPRODUCT(--('Pitched Accounts'!$J$2:$J$111=FALSE)) | D15: accounts | E15: the answer
B17: Outcome for the 98 pitched | C17: Accounts | D17: Rate
B18: Pitched | C18: =SUMPRODUCT(--('Pitched Accounts'!$J$2:$J$111=FALSE)) | D18: =C15/$C$15
B19: Started onboarding after the call | C19: =SUMPRODUCT(--('Pitched Accounts'!$J$2:$J$111=FALSE),--('Pitched Accounts'!$K$2:$K$111<>"")) | D19: =C16/$C$15
B20: Reached scheduling enabled | C20: =SUMPRODUCT(--('Pitched Accounts'!$J$2:$J$111=FALSE),--('Pitched Accounts'!$N$2:$N$111=TRUE)) | D20: =C17/$C$15
B21: Never started onboarding | C21: =SUMPRODUCT(--('Pitched Accounts'!$J$2:$J$111=FALSE),--('Pitched Accounts'!$K$2:$K$111="")) | D21: =C18/$C$15
A23: Coverage: only accounts whose attendee email matched a Chargebee customer are counted (230 of 433 distinct external emails, 53%). A further ~84 pitched emails match no customer record — prospects, excluded deliberately. 98 is a floor.

Sheet Pitched Accounts
A1: SUPERSEDED - JULY PITCH FIGURES ON THIS SHEET ARE WRONG. DO NOT QUOTE.
A2: Audit 03/08/26: the offer regex had no word boundary, so 'our booking platform' also matched 'y-our booking platform'. Reps saying "YOUR booking platform" (the customer's existing system) were counted as Zoca pitches - 55% false positives on a 22-call sample. Counting was also per Chargebee customer record, and 89 emails map to multiple records. CORRECTED: 63 accounts pitched (not 98); 8 reached scheduling enabled (not 15); 12.7% conversion (not 15%).
A3: UNAFFECTED: adoption funnel (444 locations, 368 enabled, 147 booking in 30d), payments ($645,568 / 139 accounts), cohort retention and migration sources use no regex and stand as published.
A4: Account | B4: Contact email | C4: MRR (USD) | D4: Sub status | E4: First call | F4: Last call | G4: Scheduling calls | H4: Offer calls | I4: First offer call — click to open in Fireflies | J4: Already live at pitch (excluded) | K4: Onboarding started | L4: Opted in | M4: Onboarding completed | N4: Scheduling enabled | O4: Payments configured | P4: Native bookings | Q4: Online bookings | R4: Last booking | S4: Mindbody | T4: Vagaro | U4: Booksy | V4: Fresha | W4: GlossGenius | X4: Acuity | Y4: Other tool | Z4: Deposits discussed | AA4: First offer call date | AB4: Call length (min) | AC4: Last offer call date | AD4: Fireflies URL — first offer | AE4: Fireflies URL — last offer
A5: J Madison Spa | B5: info@jmadisonspa.com | C5: 199 | D5: active | E5: 46204 | F5: 46212 | G5: 2 | H5: 2 | I5: J Madison Spa X Zoca | Check In July | J5: FALSE | L5: FALSE | M5: FALSE | N5: FALSE | O5: FALSE | P5: 0 | Q5: 0 | S5: FALSE | T5: FALSE | U5: FALSE | V5: FALSE | W5: FALSE | X5: FALSE | Y5: TRUE | Z5: TRUE | AA5: 46204 | AC5: 46212 | AD5: https://app.fireflies.ai/view/01KWCTTN3RNN15K1BER97NS33X | AE5: https://app.fireflies.ai/view/01KWYP7KBP026M401V03SN6F8Z
A6: Glenn | B6: Glennemeryskincare@gmail.com | C6: 149 | D6: active | E6: 46204 | F6: 46224 | G6: 4 | H6: 2 | I6: Glenn Emery Skincare X Zoca | Check In July | J6: FALSE | K6: 46205 | L6: TRUE | M6: TRUE | N6: TRUE | O6: TRUE | P6: 3 | Q6: 1 | R6: 46232 | S6: FALSE | T6: FALSE | U6: TRUE | V6: FALSE | W6: TRUE | X6: TRUE | Y6: FALSE | Z6: TRUE | AA6: 46204 | AC6: 46224 | AD6: https://app.fireflies.ai/view/01KWETFRAE7VJAPRPBD4TPFH83 | AE6: https://app.fireflies.ai/view/01KY083YEVGV3SQKWRXT54C710
A7: Be Tamed Hair Salon | B7: dreamphotographydfw@gmail.com | E7: 46204 | F7: 46209 | G7: 4 | H7: 2 | I7: Be Tamed Hair Salon X Zoca | Check In July | J7: FALSE | L7: FALSE | M7: FALSE | N7: FALSE | O7: FALSE | P7: 0 | Q7: 0 | S7: FALSE | T7: FALSE | U7: FALSE | V7: FALSE | W7: FALSE | X7: FALSE | Y7: FALSE | Z7: TRUE | AA7: 46204 | AC7: 46206 | AD7: https://app.fireflies.ai/view/01KWAJMPQTHXK62CHES8MP5MFS | AE7: https://app.fireflies.ai/view/01KWMM8M3J8PPNJJ2BNQEAEABH
A8: Rosado Beauty | B8: danielarosadoart@gmail.com | C8: 300 | D8: active | E8: 46204 | F8: 46211 | G8: 3 | H8: 3 | I8: Rosado Beauty X Zoca | Check In July | J8: FALSE | L8: FALSE | M8: FALSE | N8: FALSE | O8: FALSE | P8: 0 | Q8: 0 | S8: FALSE | T8: FALSE | U8: FALSE | V8: FALSE | W8: TRUE | X8: FALSE | Y8: FALSE | Z8: TRUE | AA8: 46204 | AB8: 45 | AC8: 46211 | AD8: https://app.fireflies.ai/view/01KWAK2D8NJRQNAVVCQV5PT97F | AE8: https://app.fireflies.ai/view/01KX0TKCEA6W59HEG10SWTDBFP
A9: Forever Balanced Massage | B9: darrinlane0@gmail.com | C9: 99 | D9: active | E9: 46205 | F9: 46219 | G9: 3 | H9: 2 | I9: Forever Balanced Massage X Zoca | Check In July | J9: FALSE | K9: 46210 | L9: TRUE | M9: TRUE | N9: TRUE | O9: FALSE | P9: 13 | Q9: 7 | R9: 46237 | S9: FALSE | T9: FALSE | U9: FALSE | V9: FALSE | W9: FALSE | X9: FALSE | Y9: FALSE | Z9: TRUE | AA9: 46205 | AC9: 46210 | AD9: https://app.fireflies.ai/view/01KWD6Z9869YYFXXGBXEJPVFTJ | AE9: https://app.fireflies.ai/view/01KWJJKZN53B8MSWT4DVRZ57R2
A10: Seven Layer Skin | B10: sevenlayerskin.ri@gmail.com | C10: 76.04 | D10: active | E10: 46205 | F10: 46205 | G10: 1 | H10: 1 | I10: Seven Layer Skin X Zoca | Check In July | J10: FALSE | L10: FALSE | M10: FALSE | N10: FALSE | O10: FALSE | P10: 0 | Q10: 0 | S10: FALSE | T10: FALSE | U10: FALSE | V10: FALSE | W10: FALSE | X10: FALSE | Y10: FALSE | Z10: TRUE | AA10: 46205 | AC10: 46205 | AD10: https://app.fireflies.ai/view/01KWFSZ5SJH6JF865SN7FNQ472 | AE10: https://app.fireflies.ai/view/01KWFSZ5SJH6JF865SN7FNQ472
A11: L&R Beauty | B11: lianacumbie585@gmail.com | C11: 199 | D11: active | E11: 46205 | F11: 46217 | G11: 3 | H11: 1 | I11: L&R Beauty X Zoca | Check In July | J11: TRUE | K11: 46181 | L11: TRUE | M11: TRUE | N11: TRUE | O11: TRUE | P11: 11 | Q11: 4 | R11: 46226 | S11: FALSE | T11: FALSE | U11: FALSE | V11: FALSE | W11: FALSE | X11: FALSE | Y11: FALSE | Z11: TRUE | AA11: 46205 | AC11: 46205 | AD11: https://app.fireflies.ai/view/01KWFEQ7KEX8RW3D76HKM9RHY2 | AE11: https://app.fireflies.ai/view/01KWFEQ7KEX8RW3D76HKM9RHY2
A12: SolVita Wellness Spa | B12: spadirector@mysolvita.com | C12: 249 | D12: active | E12: 46205 | F12: 46224 | G12: 3 | H12: 3 | I12: SolVita Wellness Spa X Zoca | Check In July | J12: FALSE | L12: FALSE | M12: FALSE | N12: FALSE | O12: FALSE | P12: 0 | Q12: 0 | S12: FALSE | T12: FALSE | U12: FALSE | V12: FALSE | W12: FALSE | X12: FALSE | Y12: FALSE | Z12: FALSE | AA12: 46205 | AC12: 46224 | AD12: https://app.fireflies.ai/view/01KWFY893YVKTQZP6890KFVA1M | AE12: https://app.fireflies.ai/view/01KY1AD4E1834PDFT2EJE4D0QA
A13: The Sculpt Spa | B13: thesculptspa@gmail.com | C13: 150 | D13: active | E13: 46205 | F13: 46223 | G13: 2 | H13: 2 | I13: The Sculpt Spa | J13: TRUE | K13: 46083 | L13: TRUE | M13: TRUE | N13: TRUE | O13: TRUE | P13: 6 | Q13: 6 | R13: 46199 | S13: FALSE | T13: FALSE | U13: FALSE | V13: FALSE | W13: FALSE | X13: FALSE | Y13: TRUE | Z13: TRUE | AA13: 46205 | AB13: 48 | AC13: 46223 | AD13: https://app.fireflies.ai/view/01KWJ6XA7E2C0TPBT5HX5PDWXZ | AE13: https://app.fireflies.ai/view/01KY07FQYHZT1CEYT2J524VKT0
A14: LeenaZoca | B14: desouza.leena@gmail.com | C14: 200 | D14: active | E14: 46206 | F14: 46209 | G14: 2 | H14: 1 | I14: LeenaZoca | J14: TRUE | K14: 46113 | L14: TRUE | M14: TRUE | N14: TRUE | O14: FALSE | P14: 531 | Q14: 80 | R14: 46236 | S14: FALSE | T14: FALSE | U14: FALSE | V14: FALSE | W14: FALSE | X14: FALSE | Y14: FALSE | Z14: FALSE | AA14: 46206 | AC14: 46206 | AD14: https://app.fireflies.ai/view/01KWGBVKBD29P2Q5B1D56XQXA8 | AE14: https://app.fireflies.ai/view/01KWGBVKBD29P2Q5B1D56XQXA8
A15: Saged NYC Beauty & Wellness | B15: sagednyc@gmail.com | C15: 159 | D15: active | E15: 46206 | F15: 46226 | G15: 2 | H15: 2 | I15: Saged NYC Beauty & Wellness X Zoca | Check In July | J15: FALSE | L15: FALSE | M15: FALSE | N15: FALSE | O15: FALSE | P15: 0 | Q15: 0 | S15: FALSE | T15: FALSE | U15: FALSE | V15: FALSE | W15: FALSE | X15: FALSE | Y15: FALSE | Z15: TRUE | AA15: 46206 | AB15: 59 | AC15: 46226 | AD15: https://app.fireflies.ai/view/01KWMMM9YF2D3M244HJ4442SBS | AE15: https://app.fireflies.ai/view/01KY7PZTWWHAE021KQ5D8NT853
A16: ZOCA | B16: fabulouscitysalon@gmail.com | C16: 200 | D16: active | E16: 46207 | F16: 46216 | G16: 2 | H16: 2 | I16: ZOCA <> Fabulouscity Beauty Salon | J16: FALSE | L16: FALSE | M16: FALSE | N16: FALSE | O16: FALSE | P16: 0 | Q16: 0 | S16: FALSE | T16: FALSE | U16: FALSE | V16: TRUE | W16: FALSE | X16: FALSE | Y16: FALSE | Z16: TRUE | AA16: 46207 | AB16: 11 | AC16: 46216 | AD16: https://app.fireflies.ai/view/01KWMR7GGCP9H5BK5XA8171XVT | AE16: https://app.fireflies.ai/view/01KXEE3YCVKPKCAC3NZXNDVNR8
A17: Wellness Your Way | B17: info@wellness-yourway.com | C17: 249 | D17: active | E17: 46209 | F17: 46223 | G17: 2 | H17: 1 | I17: Wellness Your Way X Zoca | Check In July | J17: FALSE | L17: FALSE | M17: FALSE | N17: FALSE | O17: FALSE | P17: 0 | Q17: 0 | S17: TRUE | T17: TRUE | U17: FALSE | V17: TRUE | W17: TRUE | X17: FALSE | Y17: FALSE | Z17: TRUE | AA17: 46209 | AB17: 73 | AC17: 46209 | AD17: https://app.fireflies.ai/view/01KWVPTCMXKB5J9ZD0K6VW5GG7 | AE17: https://app.fireflies.ai/view/01KWVPTCMXKB5J9ZD0K6VW5GG7
A18: Essence Esthetics: Skin · Lashes · Brows | B18: eesthetics7@gmail.com | C18: 100 | D18: active | E18: 46209 | F18: 46231 | G18: 3 | H18: 1 | I18: Essence Esthetics: Skin · Lashes · Brows X Zoca | Check In July | J18: FALSE | K18: 46210 | L18: TRUE | M18: TRUE | N18: TRUE | O18: TRUE | P18: 22 | Q18: 7 | R18: 46234 | S18: FALSE | T18: FALSE | U18: FALSE | V18: FALSE | W18: FALSE | X18: FALSE | Y18: FALSE | Z18: TRUE | AA18: 46210 | AB18: 138 | AC18: 46210 | AD18: https://app.fireflies.ai/view/01KWW3XDSQFPYC39AHE7X1QYEK | AE18: https://app.fireflies.ai/view/01KWW3XDSQFPYC39AHE7X1QYEK
A19: Donna Skin and Body Care | B19: donna.skin@gmail.com | C19: 150 | D19: active | E19: 46209 | F19: 46224 | G19: 4 | H19: 2 | I19: Donna Skin and Body Care X Zoca | Check In April | J19: TRUE | K19: 46169 | L19: TRUE | M19: TRUE | N19: TRUE | O19: TRUE | P19: 104 | Q19: 6 | R19: 46237 | S19: FALSE | T19: FALSE | U19: FALSE | V19: FALSE | W19: FALSE | X19: FALSE | Y19: FALSE | Z19: TRUE | AA19: 46216 | AB19: 33 | AC19: 46218 | AD19: https://app.fireflies.ai/view/01KWZ35QJGW8H8Y89FW82ARM9C | AE19: https://app.fireflies.ai/view/01KXE8RVTRA5HEWFSJA8RCSJTT
A20: Xanzalyn Beauty & Dermacare | B20: pamperedimagellc@gmail.com | E20: 46209 | F20: 46232 | G20: 2 | H20: 2 | I20: Xanzalyn Beauty & Dermacare X Zoca | Check In July | J20: FALSE | K20: 46232 | L20: TRUE | M20: FALSE | N20: FALSE | O20: FALSE | P20: 0 | Q20: 0 | S20: FALSE | T20: FALSE | U20: FALSE | V20: FALSE | W20: FALSE | X20: FALSE | Y20: FALSE | Z20: FALSE | AA20: 46209 | AB20: 18 | AC20: 46232 | AD20: https://app.fireflies.ai/view/01KWW3B796KPZEWZBRJE2D374M | AE20: https://app.fireflies.ai/view/01KYQ1NKE2JBW3345GG4Q8EACJ
A21: Lasting Beauty Spa | B21: info@lastingbeautyspa.com | C21: 120 | D21: active | E21: 46210 | F21: 46210 | G21: 1 | H21: 1 | I21: Lasting Beauty Spa X Zoca | Check In February | J21: FALSE | L21: FALSE | M21: FALSE | N21: FALSE | O21: FALSE | P21: 0 | Q21: 0 | S21: FALSE | T21: FALSE | U21: FALSE | V21: FALSE | W21: FALSE | X21: FALSE | Y21: FALSE | Z21: FALSE | AA21: 46210 | AB21: 44 | AC21: 46210 | AD21: https://app.fireflies.ai/view/01KWSEMR4B4B1B2JXMJWKSTFVM | AE21: https://app.fireflies.ai/view/01KWSEMR4B4B1B2JXMJWKSTFVM
A22: Nbraidstyles | B22: erudiceazonvide@gmail.com | C22: 135 | D22: active | E22: 46210 | F22: 46210 | G22: 1 | H22: 1 | I22: Nbraidstyles X Zoca | Check In July | J22: TRUE | K22: 46052 | L22: TRUE | M22: TRUE | N22: TRUE | O22: TRUE | P22: 273 | Q22: 73 | R22: 46237 | S22: FALSE | T22: FALSE | U22: FALSE | V22: FALSE | W22: FALSE | X22: FALSE | Y22: FALSE | Z22: FALSE | AA22: 46210 | AB22: 19 | AC22: 46210 | AD22: https://app.fireflies.ai/view/01KWYDAQMWGWG0KAQN11KWANJQ | AE22: https://app.fireflies.ai/view/01KWYDAQMWGWG0KAQN11KWANJQ
A23: Glow Skin Care | B23: umakemeglow@gmail.com | C23: 100 | D23: active | E23: 46210 | F23: 46227 | G23: 3 | H23: 1 | I23: Glow Skin Care X Zoca | Check In July | J23: FALSE | L23: FALSE | M23: FALSE | N23: FALSE | O23: FALSE | P23: 0 | Q23: 0 | S23: FALSE | T23: TRUE | U23: FALSE | V23: FALSE | W23: FALSE | X23: FALSE | Y23: FALSE | Z23: TRUE | AA23: 46210 | AC23: 46210 | AD23: https://app.fireflies.ai/view/01KWSP6FJGJ1SM0G3G1AJCRD26 | AE23: https://app.fireflies.ai/view/01KWSP6FJGJ1SM0G3G1AJCRD26
A24: Truve Fit | B24: alison@truvefit.com | E24: 46210 | F24: 46210 | G24: 1 | H24: 1 | I24: Truve Fit X Zoca | Check In July | J24: FALSE | L24: FALSE | M24: FALSE | N24: FALSE | O24: FALSE | P24: 0 | Q24: 0 | S24: FALSE | T24: FALSE | U24: FALSE | V24: FALSE | W24: FALSE | X24: FALSE | Y24: FALSE | Z24: TRUE | AA24: 46210 | AB24: 43 | AC24: 46210 | AD24: https://app.fireflies.ai/view/01KWX09A38MTKGHMKEQA20FXKT | AE24: https://app.fireflies.ai/view/01KWX09A38MTKGHMKEQA20FXKT
A25: All Love Collection | B25: we@alllovecollections.com | E25: 46210 | F25: 46223 | G25: 4 | H25: 3 | I25: Zoca <> All Love Collections | J25: FALSE | L25: FALSE | M25: FALSE | N25: FALSE | O25: FALSE | P25: 0 | Q25: 0 | S25: FALSE | T25: FALSE | U25: FALSE | V25: FALSE | W25: FALSE | X25: FALSE | Y25: FALSE | Z25: FALSE | AA25: 46210 | AB25: 84 | AC25: 46223 | AD25: https://app.fireflies.ai/view/01KWYZ11PSSAV6FVBDCZHKE3QA | AE25: https://app.fireflies.ai/view/01KXWAE7DJECPTQGX688MFETEP
A26: Just Because Hair Therapy Salon | B26: justbecausesalon@me.com | C26: 249 | D26: active | E26: 46210 | F26: 46210 | G26: 1 | H26: 1 | I26: Just Because Hair Therapy Salon X Zoca | Check In July | J26: FALSE | K26: 46210 | L26: TRUE | M26: TRUE | N26: TRUE | O26: TRUE | P26: 15 | Q26: 6 | R26: 46234 | S26: FALSE | T26: FALSE | U26: FALSE | V26: FALSE | W26: FALSE | X26: FALSE | Y26: FALSE | Z26: TRUE | AA26: 46210 | AB26: 60 | AC26: 46210 | AD26: https://app.fireflies.ai/view/01KWY3H2GSW906CGXTJ5XJCQ9E | AE26: https://app.fireflies.ai/view/01KWY3H2GSW906CGXTJ5XJCQ9E
A27: Lash and Skin Studio | B27: erica.business14@gmail.com | C27: 299 | D27: active | E27: 46210 | F27: 46210 | G27: 1 | H27: 1 | I27: Lash and Skin Studio X Zoca | Check In July | J27: FALSE | L27: FALSE | M27: FALSE | N27: FALSE | O27: FALSE | P27: 0 | Q27: 0 | S27: FALSE | T27: FALSE | U27: TRUE | V27: FALSE | W27: TRUE | X27: FALSE | Y27: FALSE | Z27: TRUE | AA27: 46210 | AB27: 46 | AC27: 46210 | AD27: https://app.fireflies.ai/view/01KWWETADJJ1REW0AQYSWQ3DTZ | AE27: https://app.fireflies.ai/view/01KWWETADJJ1REW0AQYSWQ3DTZ
A28: Anu & Isabella | B28: bellaxxx19@gmail.com | C28: 100 | D28: active | E28: 46211 | F28: 46211 | G28: 1 | H28: 1 | I28: Anu & Isabella | J28: FALSE | L28: FALSE | M28: FALSE | N28: FALSE | O28: FALSE | P28: 0 | Q28: 0 | S28: FALSE | T28: FALSE | U28: FALSE | V28: FALSE | W28: FALSE | X28: FALSE | Y28: FALSE | Z28: FALSE | AA28: 46211 | AB28: 12 | AC28: 46211 | AD28: https://app.fireflies.ai/view/01KWZ6ZG7DNJWDF79P4PJ1DNPF | AE28: https://app.fireflies.ai/view/01KWZ6ZG7DNJWDF79P4PJ1DNPF
A29: Ksweetshaircompany® Medical Wigs & Hair Restoration | B29: Ksweetshaircompany@gmail.com | E29: 46211 | F29: 46232 | G29: 2 | H29: 1 | I29: Ksweetshaircompany® Medical Wigs & Hair Restoration X Zoca | Check In | J29: FALSE | L29: FALSE | M29: FALSE | N29: FALSE | O29: FALSE | P29: 0 | Q29: 0 | S29: FALSE | T29: FALSE | U29: FALSE | V29: FALSE | W29: FALSE | X29: FALSE | Y29: FALSE | Z29: FALSE | AA29: 46211 | AC29: 46211 | AD29: https://app.fireflies.ai/view/01KWYCRBSZK2MKY8K7EFYNQZ8D | AE29: https://app.fireflies.ai/view/01KWYCRBSZK2MKY8K7EFYNQZ8D
A30: mcbh58 | B30: mcbh58@gmail.com | C30: 199 | D30: active | E30: 46211 | F30: 46211 | G30: 1 | H30: 1 | I30: CHECK-IN MEET | J30: FALSE | L30: FALSE | M30: FALSE | N30: FALSE | O30: FALSE | P30: 0 | Q30: 0 | S30: FALSE | T30: FALSE | U30: FALSE | V30: FALSE | W30: TRUE | X30: FALSE | Y30: FALSE | Z30: TRUE | AA30: 46211 | AC30: 46211 | AD30: https://app.fireflies.ai/view/01KWJJKZN0M986T9CR1CM0ZPK8 | AE30: https://app.fireflies.ai/view/01KWJJKZN0M986T9CR1CM0ZPK8
A31: Beverly Beauty Skincare & Spa | B31: beverlybeauty06@gmail.com | C31: 149 | D31: active | E31: 46211 | F31: 46211 | G31: 1 | H31: 1 | I31: Beverly Beauty Skincare & Spa | Facials|Skin Rejuvenation |lashes| wax | J31: FALSE | L31: FALSE | M31: FALSE | N31: FALSE | O31: FALSE | P31: 0 | Q31: 0 | S31: FALSE | T31: FALSE | U31: FALSE | V31: FALSE | W31: TRUE | X31: FALSE | Y31: FALSE | Z31: FALSE | AA31: 46211 | AB31: 32 | AC31: 46211 | AD31: https://app.fireflies.ai/view/01KWZ6G71XX95MZGN242RTERVN | AE31: https://app.fireflies.ai/view/01KWZ6G71XX95MZGN242RTERVN
A32: Anu & Deborah- Satori Massage | B32: debhpc@gmail.com | C32: 250 | D32: active | E32: 46211 | F32: 46230 | G32: 3 | H32: 2 | I32: Anu & Deborah- Satori Massage | J32: FALSE | L32: FALSE | M32: FALSE | N32: FALSE | O32: FALSE | P32: 0 | Q32: 0 | S32: FALSE | T32: TRUE | U32: FALSE | V32: FALSE | W32: FALSE | X32: FALSE | Y32: FALSE | Z32: FALSE | AA32: 46216 | AB32: 183 | AC32: 46230 | AD32: https://app.fireflies.ai/view/01KX9HGY3F1FE7NV3FB7Q8GK4W | AE32: https://app.fireflies.ai/view/01KYJ1ZCG58VKPE4ZNJVJ2ZW9K
A33: Perfectly Bare Wax | B33: perfectlybarewaxbar@gmail.com | C33: 746 | D33: active | E33: 46211 | F33: 46211 | G33: 1 | H33: 1 | I33: Perfectly Bare Wax X Zoca | Social Media Onboarding | J33: FALSE | L33: FALSE | M33: FALSE | N33: FALSE | O33: FALSE | P33: 0 | Q33: 0 | S33: FALSE | T33: FALSE | U33: FALSE | V33: FALSE | W33: FALSE | X33: FALSE | Y33: FALSE | Z33: FALSE | AA33: 46211 | AC33: 46211 | AD33: https://app.fireflies.ai/view/01KWZEF6KNDECHX8JBN2330AQQ | AE33: https://app.fireflies.ai/view/01KWZEF6KNDECHX8JBN2330AQQ
A34: Skinclub Wellness Center & Med Spa | B34: afsoonsmith97@gmail.com | E34: 46211 | F34: 46220 | G34: 3 | H34: 1 | I34: Skinclub Wellness Center & Med Spa X Zoca | Check In July | J34: FALSE | L34: FALSE | M34: FALSE | N34: FALSE | O34: FALSE | P34: 0 | Q34: 0 | S34: FALSE | T34: FALSE | U34: FALSE | V34: FALSE | W34: FALSE | X34: FALSE | Y34: FALSE | Z34: FALSE | AA34: 46220 | AB34: 42 | AC34: 46220 | AD34: https://app.fireflies.ai/view/01KXP62QZ2DFHTGSVBVD5HGBVN | AE34: https://app.fireflies.ai/view/01KXP62QZ2DFHTGSVBVD5HGBVN
A35: Michael's Salon | B35: baturov11@gmail.com | C35: 130 | D35: active | E35: 46211 | F35: 46211 | G35: 1 | H35: 1 | I35: Michael's Salon X Zoca | Check In July | J35: FALSE | K35: 46223 | L35: TRUE | M35: TRUE | N35: TRUE | O35: FALSE | P35: 1 | Q35: 1 | R35: 46235 | S35: FALSE | T35: FALSE | U35: FALSE | V35: FALSE | W35: TRUE | X35: FALSE | Y35: FALSE | Z35: FALSE | AA35: 46211 | AB35: 34 | AC35: 46211 | AD35: https://app.fireflies.ai/view/01KWZ3XX5D6RBMQN94T3P4N832 | AE35: https://app.fireflies.ai/view/01KWZ3XX5D6RBMQN94T3P4N832
A36: Anu & Christopher | B36: Christhecolorist2020@gmail.com | C36: 249 | D36: active | E36: 46211 | F36: 46211 | G36: 2 | H36: 1 | I36: Anu & Christopher | J36: FALSE | L36: FALSE | M36: FALSE | N36: FALSE | O36: FALSE | P36: 0 | Q36: 0 | S36: FALSE | T36: FALSE | U36: FALSE | V36: TRUE | W36: FALSE | X36: FALSE | Y36: FALSE | Z36: TRUE | AA36: 46211 | AB36: 40 | AC36: 46211 | AD36: https://app.fireflies.ai/view/01KX1QWKXAS1D9QE9CC0YHWJMG | AE36: https://app.fireflies.ai/view/01KX1QWKXAS1D9QE9CC0YHWJMG
A37: Simply Facials | B37: Mysimplyfacials@gmail.com | C37: 199 | D37: active | E37: 46211 | F37: 46211 | G37: 1 | H37: 1 | I37: Simply Facials | Thousand Oaks Esthetician X Zoca | Check In July | J37: TRUE | K37: 46104 | L37: TRUE | M37: TRUE | N37: TRUE | O37: TRUE | P37: 893 | Q37: 3 | R37: 46140 | S37: FALSE | T37: FALSE | U37: FALSE | V37: FALSE | W37: TRUE | X37: FALSE | Y37: FALSE | Z37: FALSE | AA37: 46211 | AB37: 32 | AC37: 46211 | AD37: https://app.fireflies.ai/view/01KWYGY66G975WRPTF35JM4F0J | AE37: https://app.fireflies.ai/view/01KWYGY66G975WRPTF35JM4F0J
A38: ZOCA | B38: bookings@danielkpalmer.com | C38: 249.67 | D38: active | E38: 46211 | F38: 46225 | G38: 2 | H38: 2 | I38: ZOCA <> Daniel K Palmer Salon | J38: FALSE | L38: FALSE | M38: FALSE | N38: FALSE | O38: FALSE | P38: 0 | Q38: 0 | S38: FALSE | T38: FALSE | U38: FALSE | V38: FALSE | W38: FALSE | X38: FALSE | Y38: FALSE | Z38: TRUE | AA38: 46211 | AB38: 27 | AC38: 46225 | AD38: https://app.fireflies.ai/view/01KX1P0KMHT8PXYDYJN8B91EK6 | AE38: https://app.fireflies.ai/view/01KY0QQAWMZJXP0BD721A2ZKD4
A39: Dr Shermi-Laser Skin & Wellness Center | B39: drparikh00@gmail.com | C39: 250 | D39: active | E39: 46212 | F39: 46226 | G39: 2 | H39: 1 | I39: Zoca - Dr Shermi-Laser Skin & Wellness Center | J39: FALSE | K39: 46212 | L39: TRUE | M39: FALSE | N39: FALSE | O39: FALSE | P39: 0 | Q39: 0 | S39: FALSE | T39: FALSE | U39: FALSE | V39: FALSE | W39: FALSE | X39: FALSE | Y39: FALSE | Z39: FALSE | AA39: 46226 | AB39: 181 | AC39: 46226 | AD39: https://app.fireflies.ai/view/01KY2X84QR7631VMNWQE4JJ677 | AE39: https://app.fireflies.ai/view/01KY2X84QR7631VMNWQE4JJ677
A40: NatalieZoca | B40: natalietlindo@gmail.com | C40: 329 | D40: active | E40: 46212 | F40: 46213 | G40: 2 | H40: 2 | I40: NatalieZoca | J40: FALSE | L40: FALSE | M40: FALSE | N40: FALSE | O40: FALSE | P40: 0 | Q40: 0 | S40: FALSE | T40: FALSE | U40: FALSE | V40: FALSE | W40: FALSE | X40: FALSE | Y40: FALSE | Z40: TRUE | AA40: 46212 | AC40: 46213 | AD40: https://app.fireflies.ai/view/01KX1MYVNPSDVG0504QQGNA4FF | AE40: https://app.fireflies.ai/view/01KX410ZK2Y17S3ARK3DNJS6F5
A41: Anu & Monique | B41: contact@bopskintherapy.com | C41: 249 | D41: active | E41: 46212 | F41: 46212 | G41: 1 | H41: 1 | I41: Anu & Monique | J41: FALSE | L41: FALSE | M41: FALSE | N41: FALSE | O41: FALSE | P41: 0 | Q41: 0 | S41: FALSE | T41: FALSE | U41: FALSE | V41: FALSE | W41: FALSE | X41: FALSE | Y41: FALSE | Z41: FALSE | AA41: 46212 | AB41: 35 | AC41: 46212 | AD41: https://app.fireflies.ai/view/01KX1GXHW53G6MG3VPXG0F17F1 | AE41: https://app.fireflies.ai/view/01KX1GXHW53G6MG3VPXG0F17F1
A42: Katherine Booth skincare & Spa | B42: kboothskincare@gmail.com | C42: 100 | D42: active | E42: 46212 | F42: 46212 | G42: 1 | H42: 1 | I42: Katherine Booth skincare & Spa X Zoca | Check In July | J42: FALSE | L42: FALSE | M42: FALSE | N42: FALSE | O42: FALSE | P42: 0 | Q42: 0 | S42: FALSE | T42: FALSE | U42: FALSE | V42: FALSE | W42: FALSE | X42: FALSE | Y42: FALSE | Z42: TRUE | AA42: 46212 | AC42: 46212 | AD42: https://app.fireflies.ai/view/01KX1N1WV3YSCGP67PD9VGCHP1 | AE42: https://app.fireflies.ai/view/01KX1N1WV3YSCGP67PD9VGCHP1
A43: Portia | B43: hydrat8.body@gmail.com | C43: 99 | D43: active | E43: 46212 | F43: 46212 | G43: 1 | H43: 1 | I43: Portia <> Check - in | J43: FALSE | L43: FALSE | M43: FALSE | N43: FALSE | O43: FALSE | P43: 0 | Q43: 0 | S43: FALSE | T43: FALSE | U43: FALSE | V43: FALSE | W43: FALSE | X43: FALSE | Y43: FALSE | Z43: FALSE | AA43: 46212 | AB43: 15 | AC43: 46212 | AD43: https://app.fireflies.ai/view/01KX42WR0JNHF67HSWDCN9BMJF | AE43: https://app.fireflies.ai/view/01KX42WR0JNHF67HSWDCN9BMJF
A44: Goscalp Scalp Micropigmentation Hair Loss Center | B44: goscalp@gmail.com | E44: 46212 | F44: 46232 | G44: 3 | H44: 2 | I44: Goscalp Scalp Micropigmentation Hair Loss Center X Zoca | Check In Jul | J44: FALSE | L44: FALSE | M44: FALSE | N44: FALSE | O44: FALSE | P44: 0 | Q44: 0 | S44: FALSE | T44: FALSE | U44: FALSE | V44: FALSE | W44: FALSE | X44: FALSE | Y44: FALSE | Z44: TRUE | AA44: 46212 | AC44: 46227 | AD44: https://app.fireflies.ai/view/01KX1NNCN6BWZKCHFX2QHP6VNY | AE44: https://app.fireflies.ai/view/01KY83Q9SYFJPK9P5XMMTQGA63
A45: Rema's Secrets Luxury Day Spa & Body Sculpting Massage | B45: jessicaharte31@gmail.com | C45: 250 | D45: active | E45: 46212 | F45: 46212 | G45: 1 | H45: 1 | I45: Rema's Secrets Luxury Day Spa & Body Sculpting Massage X Zoca | Check | J45: FALSE | L45: FALSE | M45: FALSE | N45: FALSE | O45: FALSE | P45: 0 | Q45: 0 | S45: FALSE | T45: FALSE | U45: FALSE | V45: FALSE | W45: FALSE | X45: FALSE | Y45: FALSE | Z45: TRUE | AA45: 46212 | AB45: 41 | AC45: 46212 | AD45: https://app.fireflies.ai/view/01KX3YRPZJN7A1YY74F79E7Z2W | AE45: https://app.fireflies.ai/view/01KX3YRPZJN7A1YY74F79E7Z2W
A46: Sublime Therapy Medical Massage | B46: sublimetherapymm@gmail.com | E46: 46213 | F46: 46213 | G46: 1 | H46: 1 | I46: Sublime Therapy Medical Massage X Zoca | Check In July | J46: FALSE | L46: FALSE | M46: FALSE | N46: FALSE | O46: FALSE | P46: 0 | Q46: 0 | S46: FALSE | T46: FALSE | U46: FALSE | V46: FALSE | W46: FALSE | X46: FALSE | Y46: FALSE | Z46: FALSE | AA46: 46213 | AC46: 46213 | AD46: https://app.fireflies.ai/view/01KX0WYX7QVVZVVPRQK03ZFYHD | AE46: https://app.fireflies.ai/view/01KX0WYX7QVVZVVPRQK03ZFYHD
A47: Robert Waters and Lalith Soni | B47: info@atlasbodyworks.com | C47: 149 | D47: active | E47: 46213 | F47: 46213 | G47: 1 | H47: 1 | I47: Robert Waters and Lalith Soni | J47: FALSE | K47: 46227 | L47: TRUE | M47: TRUE | N47: TRUE | O47: TRUE | P47: 25 | Q47: 1 | R47: 46235 | S47: FALSE | T47: FALSE | U47: FALSE | V47: FALSE | W47: FALSE | X47: FALSE | Y47: FALSE | Z47: TRUE | AA47: 46213 | AB47: 49 | AC47: 46213 | AD47: https://app.fireflies.ai/view/01KX21DRDZ9A127H3AJ0BRMP37 | AE47: https://app.fireflies.ai/view/01KX21DRDZ9A127H3AJ0BRMP37
A48: Corrine & Anu | B48: Moratherapeuticmassage@yahoo.com | C48: 150 | D48: active | E48: 46213 | F48: 46213 | G48: 1 | H48: 1 | I48: Corrine & Anu | J48: FALSE | L48: FALSE | M48: FALSE | N48: FALSE | O48: FALSE | P48: 0 | Q48: 0 | S48: FALSE | T48: FALSE | U48: FALSE | V48: FALSE | W48: FALSE | X48: FALSE | Y48: FALSE | Z48: TRUE | AA48: 46213 | AB48: 83 | AC48: 46213 | AD48: https://app.fireflies.ai/view/01KX4AY5G52TNSN7AMQF10NBK6 | AE48: https://app.fireflies.ai/view/01KX4AY5G52TNSN7AMQF10NBK6
A49: ZOCA | B49: priyaesthetic@gmail.com | C49: 750 | D49: active | E49: 46213 | F49: 46213 | G49: 1 | H49: 1 | I49: ZOCA <> GertyPerera | J49: FALSE | L49: FALSE | M49: FALSE | N49: FALSE | O49: FALSE | P49: 0 | Q49: 0 | S49: FALSE | T49: FALSE | U49: FALSE | V49: FALSE | W49: FALSE | X49: FALSE | Y49: FALSE | Z49: TRUE | AA49: 46213 | AB49: 41 | AC49: 46213 | AD49: https://app.fireflies.ai/view/01KWYWR8HWYECQMSHYH1J8SNRH | AE49: https://app.fireflies.ai/view/01KWYWR8HWYECQMSHYH1J8SNRH
A50: Limitless Skincare & Beauty LLC | B50: limitlessskincare83@gmail.com | C50: 249 | D50: active | E50: 46213 | F50: 46230 | G50: 3 | H50: 2 | I50: Limitless Skincare & Beauty LLC X Zoca | Check In July | J50: FALSE | L50: FALSE | M50: FALSE | N50: FALSE | O50: FALSE | P50: 0 | Q50: 0 | S50: FALSE | T50: TRUE | U50: FALSE | V50: FALSE | W50: FALSE | X50: FALSE | Y50: TRUE | Z50: TRUE | AA50: 46225 | AB50: 37 | AC50: 46230 | AD50: https://app.fireflies.ai/view/01KY4ZFTD0HH7YD8TJH4NNH921 | AE50: https://app.fireflies.ai/view/01KYJ9D46W5EHNWCN69CTX7A56
A51: Derma Aesthetics Spa | B51: seemaz0621@gmail.com | C51: 199 | D51: active | E51: 46213 | F51: 46213 | G51: 1 | H51: 1 | I51: Derma Aesthetics Spa X Zoca | Check In July | J51: TRUE | K51: 46113 | L51: TRUE | M51: TRUE | N51: TRUE | O51: FALSE | P51: 45 | Q51: 8 | R51: 46233 | S51: FALSE | T51: FALSE | U51: FALSE | V51: FALSE | W51: FALSE | X51: FALSE | Y51: FALSE | Z51: FALSE | AA51: 46213 | AC51: 46213 | AD51: https://app.fireflies.ai/view/01KX3V5DZ21XR19H4QXD54GR7E | AE51: https://app.fireflies.ai/view/01KX3V5DZ21XR19H4QXD54GR7E
A52: Bhumi’s Salon | B52: bhumikabhula@gmail.com | C52: 179 | D52: active | E52: 46213 | F52: 46217 | G52: 2 | H52: 1 | I52: Bhumi’s Salon | Waxing, Threading, Facial X Zoca | Check In July | J52: TRUE | K52: 46212 | L52: TRUE | M52: TRUE | N52: TRUE | O52: TRUE | P52: 7 | Q52: 0 | R52: 46235 | S52: FALSE | T52: FALSE | U52: FALSE | V52: FALSE | W52: FALSE | X52: FALSE | Y52: FALSE | Z52: TRUE | AA52: 46213 | AB52: 142 | AC52: 46213 | AD52: https://app.fireflies.ai/view/01KX6BWWEVBTHHPJK9HBN7V6MK | AE52: https://app.fireflies.ai/view/01KX6BWWEVBTHHPJK9HBN7V6MK
A53: Anu & Kiara- Pressure by Queen Ki LLC | B53: pressurebyqueenki@gmail.com | C53: 200 | D53: active | E53: 46216 | F53: 46231 | G53: 2 | H53: 2 | I53: Anu & Kiara- Pressure by Queen Ki LLC | J53: FALSE | L53: FALSE | M53: FALSE | N53: FALSE | O53: FALSE | P53: 0 | Q53: 0 | S53: FALSE | T53: FALSE | U53: TRUE | V53: FALSE | W53: FALSE | X53: FALSE | Y53: FALSE | Z53: FALSE | AA53: 46216 | AB53: 41 | AC53: 46231 | AD53: https://app.fireflies.ai/view/01KX8WX62F892J8HNR761HZD22 | AE53: https://app.fireflies.ai/view/01KYMZ7M7SG04KMT1PA52H4S3Z
A54: Dash Hair & Company, LLC | B54: ellistatamiatta@gmail.com | C54: 250 | D54: active | E54: 46216 | F54: 46216 | G54: 1 | H54: 1 | I54: Dash Hair & Company, LLC X Zoca | Check In July | J54: FALSE | L54: FALSE | M54: FALSE | N54: FALSE | O54: FALSE | P54: 0 | Q54: 0 | S54: FALSE | T54: FALSE | U54: FALSE | V54: FALSE | W54: FALSE | X54: FALSE | Y54: FALSE | Z54: FALSE | AA54: 46216 | AB54: 58 | AC54: 46216 | AD54: https://app.fireflies.ai/view/01KX46673MAHYR8S3PRRM14MTM | AE54: https://app.fireflies.ai/view/01KX46673MAHYR8S3PRRM14MTM
A55: Zoca | B55: lenatrueu@gmail.com | C55: 250 | D55: active | E55: 46216 | F55: 46216 | G55: 1 | H55: 1 | I55: Zoca <> True U Aesthetics | J55: FALSE | L55: FALSE | M55: FALSE | N55: FALSE | O55: FALSE | P55: 0 | Q55: 0 | S55: FALSE | T55: FALSE | U55: FALSE | V55: TRUE | W55: TRUE | X55: FALSE | Y55: FALSE | Z55: TRUE | AA55: 46216 | AB55: 40 | AC55: 46216 | AD55: https://app.fireflies.ai/view/01KX1TW7J9955SAGPGZMNKP1XC | AE55: https://app.fireflies.ai/view/01KX1TW7J9955SAGPGZMNKP1XC
A56: Beauty By Bowers Day Spa | B56: beautybybowers@gmail.com | C56: 100 | D56: active | E56: 46216 | F56: 46216 | G56: 1 | H56: 1 | I56: Beauty By Bowers Day Spa X Zoca | Check In July | J56: FALSE | L56: FALSE | M56: FALSE | N56: FALSE | O56: FALSE | P56: 0 | Q56: 0 | S56: FALSE | T56: FALSE | U56: FALSE | V56: FALSE | W56: TRUE | X56: FALSE | Y56: TRUE | Z56: TRUE | AA56: 46216 | AC56: 46216 | AD56: https://app.fireflies.ai/view/01KX94JHP63JFZFR3415Z7NRPW | AE56: https://app.fireflies.ai/view/01KX94JHP63JFZFR3415Z7NRPW
A57: Napa Vineyard Massage and Wellness | B57: napavineyardmassage1@gmail.com | C57: 125 | D57: active | E57: 46216 | F57: 46216 | G57: 1 | H57: 1 | I57: Napa Vineyard Massage and Wellness X Zoca | Check In July | J57: FALSE | L57: FALSE | M57: FALSE | N57: FALSE | O57: FALSE | P57: 0 | Q57: 0 | S57: FALSE | T57: FALSE | U57: FALSE | V57: FALSE | W57: FALSE | X57: FALSE | Y57: FALSE | Z57: TRUE | AA57: 46216 | AB57: 23 | AC57: 46216 | AD57: https://app.fireflies.ai/view/01KX9A7QKG7A6146MM396ZQVT0 | AE57: https://app.fireflies.ai/view/01KX9A7QKG7A6146MM396ZQVT0
A58: Retro Cuts-Kids Hair Salon & Special needs friendly | B58: retrocutsllc@gmail.com | C58: 199 | D58: active | E58: 46216 | F58: 46216 | G58: 1 | H58: 1 | I58: Retro Cuts-Kids Hair Salon & Special needs friendly X Zoca | Check In | J58: FALSE | L58: FALSE | M58: FALSE | N58: FALSE | O58: FALSE | P58: 0 | Q58: 0 | S58: FALSE | T58: FALSE | U58: FALSE | V58: FALSE | W58: TRUE | X58: FALSE | Y58: FALSE | Z58: TRUE | AA58: 46216 | AC58: 46216 | AD58: https://app.fireflies.ai/view/01KX9S5MFT763B3AKPBAYQ6N07 | AE58: https://app.fireflies.ai/view/01KX9S5MFT763B3AKPBAYQ6N07
A59: Lotus Beauty Collective | B59: Lotusbeautycollective@gmail.com | C59: 99 | D59: active | E59: 46216 | F59: 46216 | G59: 1 | H59: 1 | I59: Lotus Beauty Collective X Zoca | Check In July | J59: FALSE | L59: FALSE | M59: FALSE | N59: FALSE | O59: FALSE | P59: 0 | Q59: 0 | S59: FALSE | T59: FALSE | U59: FALSE | V59: FALSE | W59: TRUE | X59: FALSE | Y59: FALSE | Z59: FALSE | AA59: 46216 | AB59: 31 | AC59: 46216 | AD59: https://app.fireflies.ai/view/01KX9YTWDBV98JQ3G7805P12DJ | AE59: https://app.fireflies.ai/view/01KX9YTWDBV98JQ3G7805P12DJ
A60: Bodied Boss Studio | B60: Info@bodiedboss.com | C60: 199 | D60: active | E60: 46216 | F60: 46231 | G60: 2 | H60: 2 | I60: Bodied Boss Studio X Zoca | Check In July | J60: FALSE | L60: FALSE | M60: FALSE | N60: FALSE | O60: FALSE | P60: 0 | Q60: 0 | S60: FALSE | T60: FALSE | U60: FALSE | V60: FALSE | W60: FALSE | X60: FALSE | Y60: FALSE | Z60: TRUE | AA60: 46216 | AB60: 28 | AC60: 46231 | AD60: https://app.fireflies.ai/view/01KXE66VDG2696QEYJGVJSFDAH | AE60: https://app.fireflies.ai/view/01KYMY2EF0TKA08AY5412GM04Y
A61: IM=X Pilates and Fitness Mansfield | B61: michelle@imxpilates.com | C61: 199 | D61: active | E61: 46216 | F61: 46216 | G61: 1 | H61: 1 | I61: IM=X Pilates and Fitness Mansfield X Zoca | Check In July | J61: FALSE | L61: FALSE | M61: FALSE | N61: FALSE | O61: FALSE | P61: 0 | Q61: 0 | S61: TRUE | T61: FALSE | U61: FALSE | V61: FALSE | W61: FALSE | X61: FALSE | Y61: FALSE | Z61: FALSE | AA61: 46216 | AB61: 27 | AC61: 46216 | AD61: https://app.fireflies.ai/view/01KX9S5MJN9PP3F8C02WHE9CBB | AE61: https://app.fireflies.ai/view/01KX9S5MJN9PP3F8C02WHE9CBB
A62: Gregory Park and Lalith Soni | B62: acupressurecentre@gmail.com | C62: 249 | D62: active | E62: 46217 | F62: 46217 | G62: 1 | H62: 1 | I62: Gregory Park and Lalith Soni | J62: FALSE | L62: FALSE | M62: FALSE | N62: FALSE | O62: FALSE | P62: 0 | Q62: 0 | S62: FALSE | T62: FALSE | U62: FALSE | V62: FALSE | W62: FALSE | X62: FALSE | Y62: FALSE | Z62: FALSE | AA62: 46217 | AB62: 21 | AC62: 46217 | AD62: https://app.fireflies.ai/view/01KX4BBY9MV0M2MJ1VJ90QKBHA | AE62: https://app.fireflies.ai/view/01KX4BBY9MV0M2MJ1VJ90QKBHA
A63: Fusion MedSpa | B63: fusionmedspadfw@gmail.com | E63: 46217 | F63: 46217 | G63: 1 | H63: 1 | I63: Fusion MedSpa | J63: FALSE | L63: FALSE | M63: FALSE | N63: FALSE | O63: FALSE | P63: 0 | Q63: 0 | S63: FALSE | T63: FALSE | U63: FALSE | V63: FALSE | W63: FALSE | X63: FALSE | Y63: FALSE | Z63: FALSE | AA63: 46217 | AB63: 25 | AC63: 46217 | AD63: https://app.fireflies.ai/view/01KXGCTRYCB29GK1PZJVKATF9P | AE63: https://app.fireflies.ai/view/01KXGCTRYCB29GK1PZJVKATF9P
A64: Akshi Beauty Salon | B64: akshibeautysalon@gmail.com | C64: 250 | D64: active | E64: 46217 | F64: 46217 | G64: 1 | H64: 1 | I64: Akshi Beauty Salon X Zoca | Check In July | J64: FALSE | L64: FALSE | M64: FALSE | N64: FALSE | O64: FALSE | P64: 0 | Q64: 0 | S64: FALSE | T64: FALSE | U64: FALSE | V64: FALSE | W64: FALSE | X64: FALSE | Y64: FALSE | Z64: FALSE | AA64: 46217 | AB64: 39 | AC64: 46217 | AD64: https://app.fireflies.ai/view/01KXE5ZEWZX26ECQT43WKQ4VMY | AE64: https://app.fireflies.ai/view/01KXE5ZEWZX26ECQT43WKQ4VMY
A65: Adrian Blackhurst and Lalith Soni | B65: info@bayareabeatsdjs.com | C65: 75 | D65: active | E65: 46217 | F65: 46217 | G65: 1 | H65: 1 | I65: Adrian Blackhurst and Lalith Soni | J65: FALSE | L65: FALSE | M65: FALSE | N65: FALSE | O65: FALSE | P65: 0 | Q65: 0 | S65: FALSE | T65: FALSE | U65: FALSE | V65: FALSE | W65: FALSE | X65: FALSE | Y65: FALSE | Z65: TRUE | AA65: 46217 | AB65: 32 | AC65: 46217 | AD65: https://app.fireflies.ai/view/01KXF2JV34XDWK8PT436MZ1X5N | AE65: https://app.fireflies.ai/view/01KXF2JV34XDWK8PT436MZ1X5N
A66: Wholistic Essence | B66: wciw1423@gmail.com | C66: 150 | D66: active | E66: 46217 | F66: 46217 | G66: 1 | H66: 1 | I66: Wholistic Essence X Zoca | Check In July | J66: FALSE | L66: FALSE | M66: FALSE | N66: FALSE | O66: FALSE | P66: 0 | Q66: 0 | S66: FALSE | T66: TRUE | U66: FALSE | V66: FALSE | W66: FALSE | X66: FALSE | Y66: FALSE | Z66: FALSE | AA66: 46217 | AB66: 29 | AC66: 46217 | AD66: https://app.fireflies.ai/view/01KXEJAWSX2XGK0W8ZZ1VDEP1N | AE66: https://app.fireflies.ai/view/01KXEJAWSX2XGK0W8ZZ1VDEP1N
A67: Merolin-Spa Skin Well | B67: spa@shopskinwell.com | C67: 200 | D67: active | E67: 46217 | F67: 46217 | G67: 1 | H67: 1 | I67: Zoca - Merolin-Spa Skin Well | J67: FALSE | K67: 46218 | L67: TRUE | M67: FALSE | N67: FALSE | O67: FALSE | P67: 0 | Q67: 0 | S67: FALSE | T67: FALSE | U67: FALSE | V67: FALSE | W67: FALSE | X67: FALSE | Y67: FALSE | Z67: TRUE | AA67: 46217 | AB67: 26 | AC67: 46217 | AD67: https://app.fireflies.ai/view/01KXEEYWG04BVERWEGMXP7712W | AE67: https://app.fireflies.ai/view/01KXEEYWG04BVERWEGMXP7712W
A68: Zoca | B68: danielleruas2@gmail.com | E68: 46218 | F68: 46218 | G68: 2 | H68: 2 | I68: Zoca <> Head Spa Bar | J68: FALSE | L68: FALSE | M68: FALSE | N68: FALSE | O68: FALSE | P68: 0 | Q68: 0 | S68: FALSE | T68: TRUE | U68: FALSE | V68: FALSE | W68: FALSE | X68: FALSE | Y68: FALSE | Z68: FALSE | AA68: 46218 | AB68: 16 | AC68: 46218 | AD68: https://app.fireflies.ai/view/01KXHHGQGF5FG2VJAR7QCEPNFZ | AE68: https://app.fireflies.ai/view/01KXHJG88S4RZ1SWAYJJMW4TFP
A69: Unique Beauty Salon | B69: uniquebeautysalon21@gmail.com | C69: 200 | D69: active | E69: 46218 | F69: 46220 | G69: 2 | H69: 1 | I69: Unique Beauty Salon X Zoca | Check In July | J69: TRUE | K69: 46175 | L69: TRUE | M69: TRUE | N69: TRUE | O69: FALSE | P69: 52 | Q69: 12 | R69: 46237 | S69: FALSE | T69: FALSE | U69: FALSE | V69: FALSE | W69: FALSE | X69: FALSE | Y69: FALSE | Z69: FALSE | AA69: 46218 | AC69: 46218 | AD69: https://app.fireflies.ai/view/01KXK1MEGAC73ZKX55T6TP5QR8 | AE69: https://app.fireflies.ai/view/01KXK1MEGAC73ZKX55T6TP5QR8
A70: The Facial Room | B70: tfacialroom@gmail.com | C70: 250 | D70: active | E70: 46218 | F70: 46218 | G70: 1 | H70: 1 | I70: The Facial Room X Zoca | Check In July | J70: FALSE | L70: FALSE | M70: FALSE | N70: FALSE | O70: FALSE | P70: 0 | Q70: 0 | S70: FALSE | T70: FALSE | U70: FALSE | V70: TRUE | W70: FALSE | X70: FALSE | Y70: FALSE | Z70: TRUE | AA70: 46218 | AC70: 46218 | AD70: https://app.fireflies.ai/view/01KXEF15P3FR4ZKH42455BJSR8 | AE70: https://app.fireflies.ai/view/01KXEF15P3FR4ZKH42455BJSR8
A71: Zoca | B71: billiejostaten@yahoo.com | C71: 150 | D71: active | E71: 46218 | F71: 46234 | G71: 4 | H71: 2 | I71: Zoca <> Avon Beauty Salon | J71: FALSE | K71: 46230 | L71: TRUE | M71: FALSE | N71: FALSE | O71: FALSE | P71: 0 | Q71: 0 | S71: FALSE | T71: FALSE | U71: TRUE | V71: TRUE | W71: FALSE | X71: FALSE | Y71: FALSE | Z71: TRUE | AA71: 46218 | AB71: 20 | AC71: 46233 | AD71: https://app.fireflies.ai/view/01KXKQHD1QPRY1EX79ZTCTZNKD | AE71: https://app.fireflies.ai/view/01KYQS3BB5BNN0QMJQ9NMBV6Q3
A72: Zoca | B72: noendofstudio@gmail.com | C72: 200 | D72: active | E72: 46218 | F72: 46218 | G72: 1 | H72: 1 | I72: Zoca <> Noendof Hair Studio | J72: FALSE | L72: FALSE | M72: FALSE | N72: FALSE | O72: FALSE | P72: 0 | Q72: 0 | S72: FALSE | T72: FALSE | U72: FALSE | V72: TRUE | W72: FALSE | X72: FALSE | Y72: FALSE | Z72: FALSE | AA72: 46218 | AB72: 50 | AC72: 46218 | AD72: https://app.fireflies.ai/view/01KXKDRMNFPPA5559E2YX0T38M | AE72: https://app.fireflies.ai/view/01KXKDRMNFPPA5559E2YX0T38M
A73: Zoca | B73: info@nexmedaesthetics.com | C73: 249 | D73: active | E73: 46218 | F73: 46223 | G73: 2 | H73: 1 | I73: Zoca <> Nex Med Aesthetics | J73: FALSE | L73: FALSE | M73: FALSE | N73: FALSE | O73: FALSE | P73: 0 | Q73: 0 | S73: FALSE | T73: FALSE | U73: FALSE | V73: FALSE | W73: FALSE | X73: FALSE | Y73: FALSE | Z73: FALSE | AA73: 46223 | AB73: 74 | AC73: 46223 | AD73: https://app.fireflies.ai/view/01KXKWZCNSBZG71BYJBHZ06H8K | AE73: https://app.fireflies.ai/view/01KXKWZCNSBZG71BYJBHZ06H8K
A74: Mora & Zoca | B74: corrine3963@gmail.com | E74: 46219 | F74: 46219 | G74: 1 | H74: 1 | I74: Mora & Zoca | J74: FALSE | L74: FALSE | M74: FALSE | N74: FALSE | O74: FALSE | P74: 0 | Q74: 0 | S74: FALSE | T74: FALSE | U74: FALSE | V74: FALSE | W74: FALSE | X74: FALSE | Y74: FALSE | Z74: TRUE | AA74: 46219 | AB74: 40 | AC74: 46219 | AD74: https://app.fireflies.ai/view/01KXK1QEKDY8T4A2DMMTH7N9V9 | AE74: https://app.fireflies.ai/view/01KXK1QEKDY8T4A2DMMTH7N9V9
A75: ZOCA | B75: info@thewowstudio.net | C75: 250 | D75: active | E75: 46219 | F75: 46219 | G75: 1 | H75: 1 | I75: ZOCA <> DeylineBedoya | J75: FALSE | L75: FALSE | M75: FALSE | N75: FALSE | O75: FALSE | P75: 0 | Q75: 0 | S75: FALSE | T75: FALSE | U75: FALSE | V75: FALSE | W75: FALSE | X75: FALSE | Y75: FALSE | Z75: FALSE | AA75: 46219 | AB75: 64 | AC75: 46219 | AD75: https://app.fireflies.ai/view/01KXKCVC20YTKB0TKZTV3QYNH9 | AE75: https://app.fireflies.ai/view/01KXKCVC20YTKB0TKZTV3QYNH9
A76: Braiding Hair Max of Baltimore | B76: gloirenicky0@gmail.com | C76: 150 | D76: active | E76: 46220 | F76: 46231 | G76: 2 | H76: 2 | I76: Braiding Hair Max of Baltimore X Zoca | Check In July | J76: FALSE | K76: 46220 | L76: TRUE | M76: TRUE | N76: TRUE | O76: TRUE | P76: 2 | Q76: 2 | R76: 46234 | S76: FALSE | T76: FALSE | U76: FALSE | V76: FALSE | W76: FALSE | X76: FALSE | Y76: FALSE | Z76: TRUE | AA76: 46220 | AB76: 106 | AC76: 46231 | AD76: https://app.fireflies.ai/view/01KXR8PNBPYKQBEXA4M0TG0KNX | AE76: https://app.fireflies.ai/view/01KYMJJPMQPGPDT12PTPBKTT5Z
A77: Profiles Nails and Beauty Salon | B77: profilesofbonita@gmail.com | C77: 150 | D77: active | E77: 46220 | F77: 46226 | G77: 2 | H77: 1 | I77: Profiles Nails and Beauty Salon X Zoca | Check In July | J77: FALSE | K77: 46220 | L77: TRUE | M77: TRUE | N77: TRUE | O77: FALSE | P77: 3 | Q77: 3 | R77: 46235 | S77: FALSE | T77: FALSE | U77: FALSE | V77: FALSE | W77: FALSE | X77: FALSE | Y77: FALSE | Z77: TRUE | AA77: 46226 | AB77: 36 | AC77: 46226 | AD77: https://app.fireflies.ai/view/01KY5W2XCDD1NFTJF9S3QY2CBB | AE77: https://app.fireflies.ai/view/01KY5W2XCDD1NFTJF9S3QY2CBB
A78: Golden Jade Massage & Healing | B78: goldenjade.mh@gmail.com | C78: 349 | D78: active | E78: 46220 | F78: 46232 | G78: 2 | H78: 2 | I78: Golden Jade Massage & Healing X Zoca | Check In July | J78: FALSE | K78: 46232 | L78: TRUE | M78: TRUE | N78: TRUE | O78: FALSE | P78: 10 | Q78: 6 | R78: 46236 | S78: FALSE | T78: FALSE | U78: FALSE | V78: TRUE | W78: FALSE | X78: FALSE | Y78: FALSE | Z78: TRUE | AA78: 46220 | AB78: 55 | AC78: 46232 | AD78: https://app.fireflies.ai/view/01KXPEXVJ30Q3YMN5NGQ9SW9EM | AE78: https://app.fireflies.ai/view/01KYMECCSQ45VTXFC2XEP8V1E4
A79: Zoca | B79: lea.stylingco@gmail.com | C79: 200 | D79: active | E79: 46220 | F79: 46220 | G79: 1 | H79: 1 | I79: Zoca <> Styling Company Belmar | J79: FALSE | L79: FALSE | M79: FALSE | N79: FALSE | O79: FALSE | P79: 0 | Q79: 0 | S79: FALSE | T79: FALSE | U79: FALSE | V79: FALSE | W79: FALSE | X79: FALSE | Y79: FALSE | Z79: FALSE | AA79: 46220 | AB79: 36 | AC79: 46220 | AD79: https://app.fireflies.ai/view/01KXKAATCTNXTJJZQ1EHDMHVQQ | AE79: https://app.fireflies.ai/view/01KXKAATCTNXTJJZQ1EHDMHVQQ
A80: Vita Aesthetics & Wellness | B80: Nick@montesmedical.com | C80: 200 | D80: active | E80: 46220 | F80: 46227 | G80: 2 | H80: 2 | I80: Vita Aesthetics & Wellness <> Check - in | J80: FALSE | L80: FALSE | M80: FALSE | N80: FALSE | O80: FALSE | P80: 0 | Q80: 0 | S80: FALSE | T80: FALSE | U80: FALSE | V80: FALSE | W80: FALSE | X80: FALSE | Y80: TRUE | Z80: TRUE | AA80: 46220 | AC80: 46227 | AD80: https://app.fireflies.ai/view/01KXK27KM5XN56T9SVKJYXV2NW | AE80: https://app.fireflies.ai/view/01KY86SK0Q0KHDVG4W696333D8
A81: theconciergetherapist | B81: theconciergetherapist@gmail.com | D81: in_trial | E81: 46223 | F81: 46234 | G81: 3 | H81: 2 | I81: Zoca <> Dr. Calvin | J81: FALSE | K81: 46225 | L81: TRUE | M81: TRUE | N81: TRUE | O81: FALSE | P81: 4 | Q81: 4 | R81: 46235 | S81: FALSE | T81: FALSE | U81: TRUE | V81: FALSE | W81: FALSE | X81: TRUE | Y81: TRUE | Z81: TRUE | AA81: 46223 | AB81: 84 | AC81: 46225 | AD81: https://app.fireflies.ai/view/01KXV5W2QX9H2GGWF4KMESMY35 | AE81: https://app.fireflies.ai/view/01KY560MEFZ3J4ERBCX5FXBF81
A82: Anu & Koji | B82: bbmemesalon@gmail.com | C82: 249 | D82: active | E82: 46223 | F82: 46224 | G82: 2 | H82: 1 | I82: Anu & Koji | J82: FALSE | K82: 46224 | L82: TRUE | M82: TRUE | N82: TRUE | O82: FALSE | P82: 0 | Q82: 0 | S82: FALSE | T82: FALSE | U82: TRUE | V82: FALSE | W82: FALSE | X82: FALSE | Y82: FALSE | Z82: TRUE | AA82: 46223 | AB82: 23 | AC82: 46223 | AD82: https://app.fireflies.ai/view/01KY017VA0AV9QKFJKSK8SR1ZG | AE82: https://app.fireflies.ai/view/01KY017VA0AV9QKFJKSK8SR1ZG
A83: Efflorescence Aesthetic and Cellulite Reduction Spa | B83: debra.mccaslin@comcast.net | C83: 150 | D83: active | E83: 46223 | F83: 46223 | G83: 1 | H83: 1 | I83: Efflorescence Aesthetic and Cellulite Reduction Spa X Zoca | Check In | J83: TRUE | K83: 46097 | L83: TRUE | M83: TRUE | N83: FALSE | O83: FALSE | P83: 0 | Q83: 0 | S83: FALSE | T83: FALSE | U83: FALSE | V83: FALSE | W83: TRUE | X83: FALSE | Y83: FALSE | Z83: FALSE | AA83: 46223 | AB83: 41 | AC83: 46223 | AD83: https://app.fireflies.ai/view/01KXVJD9T9YV9F2QDF0BPEQE7G | AE83: https://app.fireflies.ai/view/01KXVJD9T9YV9F2QDF0BPEQE7G
A84: The Braiding Place Elgin | B84: Kelojou@gmail.com | C84: 199 | D84: active | E84: 46223 | F84: 46224 | G84: 2 | H84: 1 | I84: The Braiding Place Elgin X Zoca | Check In July | J84: FALSE | K84: 46224 | L84: TRUE | M84: FALSE | N84: FALSE | O84: FALSE | P84: 0 | Q84: 0 | S84: FALSE | T84: FALSE | U84: FALSE | V84: FALSE | W84: FALSE | X84: FALSE | Y84: FALSE | Z84: TRUE | AA84: 46223 | AB84: 24 | AC84: 46223 | AD84: https://app.fireflies.ai/view/01KXVMDBQRSR399KE16S0593YF | AE84: https://app.fireflies.ai/view/01KXVMDBQRSR399KE16S0593YF
A85: Ohana Sun Tanning | B85: tan@ohanasuntanning.com | C85: 305 | D85: active | E85: 46223 | F85: 46223 | G85: 1 | H85: 1 | I85: Ohana Sun Tanning X Zoca | Check In July | J85: FALSE | L85: FALSE | M85: FALSE | N85: FALSE | O85: FALSE | P85: 0 | Q85: 0 | S85: FALSE | T85: FALSE | U85: FALSE | V85: FALSE | W85: FALSE | X85: FALSE | Y85: FALSE | Z85: TRUE | AA85: 46223 | AB85: 48 | AC85: 46223 | AD85: https://app.fireflies.ai/view/01KXZM3TGYW0TR1ZP5MPT9PER6 | AE85: https://app.fireflies.ai/view/01KXZM3TGYW0TR1ZP5MPT9PER6
A86: DOLLFACE | B86: dimopoulos029@gmail.com | C86: 249 | D86: active | E86: 46223 | F86: 46223 | G86: 1 | H86: 1 | I86: DOLLFACE X Zoca | Check In July | J86: FALSE | L86: FALSE | M86: FALSE | N86: FALSE | O86: FALSE | P86: 0 | Q86: 0 | S86: FALSE | T86: FALSE | U86: FALSE | V86: FALSE | W86: FALSE | X86: FALSE | Y86: TRUE | Z86: FALSE | AA86: 46223 | AB86: 92 | AC86: 46223 | AD86: https://app.fireflies.ai/view/01KXVMDBS01BQ70YFYHYYS4F5V | AE86: https://app.fireflies.ai/view/01KXVMDBS01BQ70YFYHYYS4F5V
A87: Hairbygino | B87: ginomagnarelli@gmail.com | C87: 149 | D87: active | E87: 46225 | F87: 46225 | G87: 2 | H87: 2 | I87: Hairbygino X Zoca | Check In July | J87: FALSE | K87: 46225 | L87: TRUE | M87: TRUE | N87: TRUE | O87: FALSE | P87: 0 | Q87: 0 | S87: FALSE | T87: FALSE | U87: FALSE | V87: FALSE | W87: FALSE | X87: FALSE | Y87: FALSE | Z87: TRUE | AA87: 46225 | AB87: 44 | AC87: 46225 | AD87: https://app.fireflies.ai/view/01KY524PF40BRCE5MXDRG4FYMQ | AE87: https://app.fireflies.ai/view/01KY5B5K4SDAVYK9X80787ME3A
A88: Elite Spa Wellness Center | B88: info@elitespawellness.com | C88: 250 | D88: active | E88: 46226 | F88: 46233 | G88: 2 | H88: 2 | I88: Elite Spa Wellness Center X Zoca | Check In July | J88: FALSE | L88: FALSE | M88: FALSE | N88: FALSE | O88: FALSE | P88: 0 | Q88: 0 | S88: TRUE | T88: TRUE | U88: FALSE | V88: FALSE | W88: FALSE | X88: FALSE | Y88: FALSE | Z88: TRUE | AA88: 46226 | AB88: 21 | AC88: 46233 | AD88: https://app.fireflies.ai/view/01KY5SNDQ6XKCR7WC1YM620DAC | AE88: https://app.fireflies.ai/view/01KYQTGFZ81HZETWHZ5VS9Q7EG
A89: Connected Health Plano | B89: plano@connectedhealthcenter.com | C89: 150 | D89: active | E89: 46226 | F89: 46226 | G89: 1 | H89: 1 | I89: Connected Health Plano X Zoca | Implementation call | J89: FALSE | K89: 46226 | L89: TRUE | M89: FALSE | N89: FALSE | O89: FALSE | P89: 2 | Q89: 2 | R89: 46234 | S89: FALSE | T89: FALSE | U89: FALSE | V89: FALSE | W89: FALSE | X89: FALSE | Y89: FALSE | Z89: TRUE | AA89: 46226 | AB89: 51 | AC89: 46226 | AD89: https://app.fireflies.ai/view/01KY609WZH5YN9ES8T5A2DM16A | AE89: https://app.fireflies.ai/view/01KY609WZH5YN9ES8T5A2DM16A
A90: Salon Greco The European Day Spa | B90: salongreco@aol.com | C90: 249 | D90: active | E90: 46226 | F90: 46226 | G90: 1 | H90: 1 | I90: Salon Greco The European Day Spa X Zoca | Check In July | J90: FALSE | K90: 46226 | L90: TRUE | M90: FALSE | N90: FALSE | O90: FALSE | P90: 0 | Q90: 0 | S90: FALSE | T90: FALSE | U90: FALSE | V90: FALSE | W90: FALSE | X90: FALSE | Y90: FALSE | Z90: TRUE | AA90: 46226 | AC90: 46226 | AD90: https://app.fireflies.ai/view/01KY37FFZHAB372Q59SQHCTB80 | AE90: https://app.fireflies.ai/view/01KY37FFZHAB372Q59SQHCTB80
A91: Healing Hands By Andrea | B91: andreacoy99@gmail.com | C91: 149 | D91: active | E91: 46227 | F91: 46227 | G91: 1 | H91: 1 | I91: Healing Hands By Andrea X Zoca | Check In July | J91: FALSE | L91: FALSE | M91: FALSE | N91: FALSE | O91: FALSE | P91: 0 | Q91: 0 | S91: FALSE | T91: FALSE | U91: FALSE | V91: FALSE | W91: FALSE | X91: FALSE | Y91: FALSE | Z91: FALSE | AA91: 46227 | AB91: 27 | AC91: 46227 | AD91: https://app.fireflies.ai/view/01KY8A9JQ93R3BAVMGQJPK2T68 | AE91: https://app.fireflies.ai/view/01KY8A9JQ93R3BAVMGQJPK2T68
A92: Worldwide Stretch Therapy | B92: philoy.williams@gmail.com | C92: 149 | D92: active | E92: 46227 | F92: 46227 | G92: 1 | H92: 1 | I92: Worldwide Stretch Therapy X Zoca | Check In July | J92: FALSE | K92: 46227 | L92: TRUE | M92: TRUE | N92: TRUE | O92: TRUE | P92: 1 | Q92: 1 | R92: 46236 | S92: FALSE | T92: FALSE | U92: FALSE | V92: FALSE | W92: FALSE | X92: FALSE | Y92: FALSE | Z92: TRUE | AA92: 46227 | AB92: 265 | AC92: 46227 | AD92: https://app.fireflies.ai/view/01KYAG0AA12NBM57SVBF8XEN18 | AE92: https://app.fireflies.ai/view/01KYAG0AA12NBM57SVBF8XEN18
A93: JL Studio | B93: jackie.leveille@gmail.com | C93: 150 | D93: active | E93: 46230 | F93: 46234 | G93: 2 | H93: 2 | I93: JL Studio X Zoca | Check In July | J93: TRUE | K93: 46156 | L93: TRUE | M93: FALSE | N93: FALSE | O93: FALSE | P93: 0 | Q93: 0 | S93: FALSE | T93: FALSE | U93: FALSE | V93: FALSE | W93: FALSE | X93: FALSE | Y93: FALSE | Z93: FALSE | AA93: 46230 | AB93: 64 | AC93: 46234 | AD93: https://app.fireflies.ai/view/01KYAP8ZXDMFASM46783R08KX5 | AE93: https://app.fireflies.ai/view/01KYT4KYXZ2BQGP49B74QNWWAC
A94: Zoca | B94: estevan333@gmail.com | C94: 100 | D94: non_renewing | E94: 46230 | F94: 46230 | G94: 1 | H94: 1 | I94: Zoca <> Salon Estevan | J94: FALSE | L94: FALSE | M94: FALSE | N94: FALSE | O94: FALSE | P94: 0 | Q94: 0 | S94: TRUE | T94: FALSE | U94: FALSE | V94: TRUE | W94: TRUE | X94: FALSE | Y94: FALSE | Z94: FALSE | AA94: 46230 | AB94: 93 | AC94: 46230 | AD94: https://app.fireflies.ai/view/01KY82B5DVRBEV0H6XTDX4GNPB | AE94: https://app.fireflies.ai/view/01KY82B5DVRBEV0H6XTDX4GNPB
A95: DanielZoca | B95: feinman77@yahoo.com | C95: 99 | D95: active | E95: 46230 | F95: 46230 | G95: 1 | H95: 1 | I95: DanielZoca | J95: FALSE | L95: FALSE | M95: FALSE | N95: FALSE | O95: FALSE | P95: 0 | Q95: 0 | S95: FALSE | T95: FALSE | U95: FALSE | V95: FALSE | W95: FALSE | X95: FALSE | Y95: FALSE | Z95: TRUE | AA95: 46230 | AB95: 72 | AC95: 46230 | AD95: https://app.fireflies.ai/view/01KYAP8ZXGZ4B8BEJ6A9GT08PM | AE95: https://app.fireflies.ai/view/01KYAP8ZXGZ4B8BEJ6A9GT08PM
A96: AKKI Aesthetics | B96: akkimedspa@gmail.com | C96: 200 | D96: active | E96: 46230 | F96: 46233 | G96: 2 | H96: 2 | I96: AKKI Aesthetics X Zoca | Check In July | J96: FALSE | L96: FALSE | M96: FALSE | N96: FALSE | O96: FALSE | P96: 0 | Q96: 0 | S96: FALSE | T96: FALSE | U96: FALSE | V96: FALSE | W96: TRUE | X96: FALSE | Y96: FALSE | Z96: TRUE | AA96: 46230 | AB96: 64 | AC96: 46233 | AD96: https://app.fireflies.ai/view/01KYA73PFQN6MWTK8AGXV97KG1 | AE96: https://app.fireflies.ai/view/01KYJJJ2CS14TF1KK0HD5062VV
A97: Natures Wax & Med Spa | B97: nwaxservice@gmail.com | C97: 300 | D97: active | E97: 46230 | F97: 46230 | G97: 1 | H97: 1 | I97: Natures Wax & Med Spa X Zoca | Check In July | J97: FALSE | L97: FALSE | M97: FALSE | N97: FALSE | O97: FALSE | P97: 0 | Q97: 0 | S97: FALSE | T97: FALSE | U97: FALSE | V97: FALSE | W97: FALSE | X97: FALSE | Y97: FALSE | Z97: TRUE | AA97: 46230 | AB97: 70 | AC97: 46231 | AD97: https://app.fireflies.ai/view/01KYJ1Y52ZQTNJT7SJQBVKRR3D | AE97: https://app.fireflies.ai/view/01KYJPK7G2FXDPQ5FD79B28WAA
A98: Serge-VIP Aesthetic Center Med Spa | B98: sergejanov@gmail.com | C98: 150 | D98: active | E98: 46230 | F98: 46230 | G98: 1 | H98: 1 | I98: Zoca - Serge-VIP Aesthetic Center Med Spa | J98: FALSE | L98: FALSE | M98: FALSE | N98: FALSE | O98: FALSE | P98: 0 | Q98: 0 | S98: FALSE | T98: FALSE | U98: FALSE | V98: FALSE | W98: FALSE | X98: FALSE | Y98: FALSE | Z98: FALSE | AA98: 46230 | AB98: 46 | AC98: 46230 | AD98: https://app.fireflies.ai/view/01KYFZ29BFNNGKDNWBJB49ZHA3 | AE98: https://app.fireflies.ai/view/01KYFZ29BFNNGKDNWBJB49ZHA3
A99: Zoca | B99: info@LincolnParkPilates.com | C99: 200 | D99: active | E99: 46231 | F99: 46231 | G99: 1 | H99: 1 | I99: Zoca <> Lincoln Park Pilates | J99: FALSE | L99: FALSE | M99: FALSE | N99: FALSE | O99: FALSE | P99: 0 | Q99: 0 | S99: FALSE | T99: FALSE | U99: FALSE | V99: FALSE | W99: FALSE | X99: FALSE | Y99: FALSE | Z99: FALSE | AA99: 46231 | AB99: 116 | AC99: 46231 | AD99: https://app.fireflies.ai/view/01KY5VZ3CHSJ0223AAPJX283JW | AE99: https://app.fireflies.ai/view/01KY5VZ3CHSJ0223AAPJX283JW
A100: Rosy Tips Nail Salon Chula Vista CA | B100: rosytipsnailsnspa@gmail.com | C100: 249 | D100: active | E100: 46231 | F100: 46231 | G100: 1 | H100: 1 | I100: Rosy Tips Nail Salon Chula Vista CA X Zoca | Check In July | J100: FALSE | L100: FALSE | M100: FALSE | N100: FALSE | O100: FALSE | P100: 0 | Q100: 0 | S100: FALSE | T100: FALSE | U100: FALSE | V100: FALSE | W100: FALSE | X100: FALSE | Y100: FALSE | Z100: TRUE | AA100: 46231 | AB100: 68 | AC100: 46231 | AD100: https://app.fireflies.ai/view/01KYJ4W4BN3KWRZDP9XMZ03WC0 | AE100: https://app.fireflies.ai/view/01KYJ4W4BN3KWRZDP9XMZ03WC0
...

Sheet Adoption Funnel
A1: Scheduling adoption funnel — all 444 onboarding locations, 30/01/26 to 31/07/26
A2: Every count calculates from the Locations sheet.
A4: Stage | B4: Locations | C4: % of entered | D4: Reading
A5: Entered onboarding | B5: =COUNTA(Locations!$A$2:$A$445) | C5: =B5/$B$5 | D5: Denominator
A6: Opted in | B6: =SUMPRODUCT(--(Locations!$E$2:$E$445=TRUE)) | C6: =B6/$B$5
A7: Business details set | B7: =SUMPRODUCT(--(Locations!$F$2:$F$445=TRUE)) | C7: =B7/$B$5
A8: Services configured | B8: =SUMPRODUCT(--(Locations!$G$2:$G$445=TRUE)) | C8: =B8/$B$5
A9: Booking rules configured | B9: =SUMPRODUCT(--(Locations!$H$2:$H$445=TRUE)) | C9: =B9/$B$5
A10: Booking policies configured | B10: =SUMPRODUCT(--(Locations!$I$2:$I$445=TRUE)) | C10: =B10/$B$5
A11: Website flipped to Zoca booking | B11: =SUMPRODUCT(--(Locations!$N$2:$N$445=TRUE)) | C11: =B11/$B$5
A12: Onboarding completed | B12: =SUMPRODUCT(--(Locations!$L$2:$L$445=TRUE)) | C12: =B12/$B$5
A13: Scheduling enabled | B13: =SUMPRODUCT(--(Locations!$M$2:$M$445=TRUE)) | C13: =B13/$B$5 | D13: SETUP conversion
A14: Payments configured | B14: =SUMPRODUCT(--(Locations!$J$2:$J$445=TRUE)) | C14: =B14/$B$5 | D14: The wall
A15: Payments explicitly skipped | B15: =SUMPRODUCT(--(Locations!$K$2:$K$445=TRUE)) | C15: =B15/$B$5 | D15: The wall
A16: Ever took a booking | B16: =SUMPRODUCT(--(Locations!$O$2:$O$445>0)) | C16: =B16/$B$5 | D16: ACTIVATION conversion
A17: Ever took a customer-made online booking | B17: =SUMPRODUCT(--(Locations!$P$2:$P$445>0)) | C17: =B17/$B$5
A18: Booked in last 90 days | B18: =SUMPRODUCT(--(Locations!$T$2:$T$445>=Summary!$B$3-90)) | C18: =B18/$B$5 | D18: 198 here vs 196 in the report: the report used query-run time, this uses the fixed as-of date (a ~16h wider window). This is the reproducible one.
A19: Booked in last 30 days | B19: =SUMPRODUCT(--(Locations!$T$2:$T$445>=Summary!$B$3-30)) | C19: =B19/$B$5 | D19: SUSTAINED conversion
A21: Three different conversion rates live in this one funnel. Say which one you are quoting: setup 83%, activation 64%, sustained 33%.

Sheet Locations
A1: Location entity id | B1: Business name | C1: Onboarding started | D1: Cohort | E1: Opted in | F1: Business details | G1: Services configured | H1: Booking rules | I1: Booking policies | J1: Payments configured | K1: Payments skipped | L1: Onboarding completed | M1: Scheduling enabled | N1: Website flipped | O1: Native bookings | P1: Online bookings | Q1: Migrated bookings | R1: Migration source | S1: First booking | T1: Last booking | U1: Paid transactions | V1: Paid amount (USD) | W1: Chargebee customer id | X1: MRR (USD) | Y1: Subscription status | Z1: Name source
A2: f2930e96-c10f-4273-834d-948790dcb785 | B2: Nbraidstyles | C2: 46052 | D2: 2026-01 | E2: TRUE | F2: TRUE | G2: TRUE | H2: TRUE | I2: TRUE | J2: TRUE | K2: FALSE | L2: TRUE | M2: TRUE | N2: TRUE | O2: 273 | P2: 73 | Q2: 0 | S2: 45202 | T2: 46237 | U2: 69 | V2: 2627 | W2: cus_OGiPoqL0Cu6SL2 | X2: 135 | Y2: active | Z2: gbp
A3: 4dd18bab-a516-46e7-a193-1eb215074802 | B3: timelyAI | C3: 46052 | D3: 2026-01 | E3: TRUE | F3: TRUE | G3: TRUE | H3: TRUE | I3: TRUE | J3: TRUE | K3: FALSE | L3: TRUE | M3: TRUE | N3: TRUE | O3: 5 | P3: 0 | Q3: 0 | S3: 46052 | T3: 46052 | U3: 1 | V3: 1.5 | Z3: gbp
A4: 0a3e4ac6-9bdb-4e76-b354-7e2f2d6bb72c | B4: Natasha super salon | C4: 46053 | D4: 2026-01 | E4: TRUE | F4: TRUE | G4: FALSE | H4: FALSE | I4: FALSE | J4: FALSE | K4: FALSE | L4: FALSE | M4: FALSE | N4: FALSE | O4: 0 | P4: 0 | Q4: 0 | U4: 0 | V4: 0 | Z4: gbp_logs
A5: b31bc9ca-9a1c-4cb7-b76f-7621a2cc9a5c | B5: (name not on file) | C5: 46053 | D5: 2026-01 | E5: TRUE | F5: TRUE | G5: FALSE | H5: FALSE | I5: FALSE | J5: FALSE | K5: FALSE | L5: FALSE | M5: FALSE | N5: FALSE | O5: 0 | P5: 0 | Q5: 0 | U5: 0 | V5: 0 | Z5: unknown
A6: d1983fab-fb1b-43c6-af50-2e25684bdc16 | B6: Natasha super salon | C6: 46053 | D6: 2026-01 | E6: TRUE | F6: TRUE | G6: TRUE | H6: TRUE | I6: TRUE | J6: FALSE | K6: TRUE | L6: TRUE | M6: TRUE | N6: TRUE | O6: 5 | P6: 0 | Q6: 0 | S6: 46053 | T6: 46053 | U6: 0 | V6: 0 | Z6: gbp_logs
A7: c38002b7-6d03-4e9d-9772-c8b9ef9593be | B7: (name not on file) | C7: 46053 | D7: 2026-01 | E7: TRUE | F7: TRUE | G7: TRUE | H7: TRUE | I7: TRUE | J7: FALSE | K7: FALSE | L7: FALSE | M7: FALSE | N7: FALSE | O7: 0 | P7: 0 | Q7: 0 | U7: 0 | V7: 0 | Z7: unknown
A8: 61bcfc8a-d56d-4b46-a4a3-658ce60aa48f | B8: Natasha super salon | C8: 46053 | D8: 2026-01 | E8: TRUE | F8: TRUE | G8: TRUE | H8: TRUE | I8: TRUE | J8: FALSE | K8: TRUE | L8: TRUE | M8: TRUE | N8: TRUE | O8: 3 | P8: 0 | Q8: 0 | S8: 46053 | T8: 46055 | U8: 0 | V8: 0 | Z8: gbp_logs
A9: 06055989-747f-477b-9e4f-36849d39a605 | B9: (name not on file) | C9: 46053 | D9: 2026-01 | E9: TRUE | F9: TRUE | G9: TRUE | H9: TRUE | I9: TRUE | J9: FALSE | K9: TRUE | L9: TRUE | M9: FALSE | N9: FALSE | O9: 0 | P9: 0 | Q9: 0 | U9: 0 | V9: 0 | Z9: unknown
A10: 29021b0b-4156-4d36-b27e-3ae09ac17ce9 | B10: Doom Salon | C10: 46053 | D10: 2026-01 | E10: TRUE | F10: TRUE | G10: TRUE | H10: TRUE | I10: TRUE | J10: FALSE | K10: TRUE | L10: TRUE | M10: TRUE | N10: TRUE | O10: 5 | P10: 3 | Q10: 0 | S10: 46053 | T10: 46055 | U10: 0 | V10: 0 | Z10: gbp_logs
A11: 4c62f8a6-fffd-45fa-9c24-410228f4c0eb | B11: Beauty and a Beast Salon | C11: 46053 | D11: 2026-01 | E11: TRUE | F11: TRUE | G11: TRUE | H11: TRUE | I11: TRUE | J11: TRUE | K11: TRUE | L11: TRUE | M11: TRUE | N11: TRUE | O11: 13 | P11: 3 | Q11: 0 | S11: 46053 | T11: 46055 | U11: 2 | V11: 4881.25 | Z11: gbp_logs
A12: 90d177ff-eef3-48f8-b56c-3bdaf1d1b431 | B12: Saxena's spa | C12: 46055 | D12: 2026-02 | E12: TRUE | F12: TRUE | G12: FALSE | H12: FALSE | I12: FALSE | J12: FALSE | K12: FALSE | L12: FALSE | M12: FALSE | N12: FALSE | O12: 0 | P12: 0 | Q12: 0 | U12: 0 | V12: 0 | Z12: gbp_logs
A13: 07233b3c-c922-40a7-8ac3-e57986ffb675 | B13: Natasha super salon | C13: 46055 | D13: 2026-02 | E13: TRUE | F13: TRUE | G13: TRUE | H13: TRUE | I13: TRUE | J13: FALSE | K13: TRUE | L13: TRUE | M13: TRUE | N13: TRUE | O13: 17 | P13: 9 | Q13: 0 | S13: 46055 | T13: 46056 | U13: 0 | V13: 0 | Z13: gbp_logs
A14: ca0b1b82-9b25-4c51-9ab5-65575cee49c4 | B14: (name not on file) | C14: 46055 | D14: 2026-02 | E14: TRUE | F14: TRUE | G14: TRUE | H14: TRUE | I14: TRUE | J14: FALSE | K14: TRUE | L14: TRUE | M14: TRUE | N14: TRUE | O14: 0 | P14: 0 | Q14: 0 | U14: 0 | V14: 0 | Z14: unknown
A15: 0f95c289-b0a7-4149-97be-2f0e3782cf2c | B15: Shine Salon & Spa | C15: 46055 | D15: 2026-02 | E15: TRUE | F15: TRUE | G15: TRUE | H15: TRUE | I15: TRUE | J15: FALSE | K15: TRUE | L15: TRUE | M15: TRUE | N15: TRUE | O15: 54 | P15: 17 | Q15: 0 | S15: 46055 | T15: 46058 | U15: 39 | V15: 58 | Z15: gbp_logs
A16: e85a1d81-1a0f-41e6-b286-c358d63f8251 | B16: (name not on file) | C16: 46055 | D16: 2026-02 | E16: TRUE | F16: FALSE | G16: FALSE | H16: FALSE | I16: FALSE | J16: FALSE | K16: FALSE | L16: FALSE | M16: FALSE | N16: FALSE | O16: 0 | P16: 0 | Q16: 0 | U16: 0 | V16: 0 | Z16: unknown
A17: 140217cf-0058-4d4c-8814-0235ee218898 | B17: Shine Salon & Spa - Hair, Skin, Nails, Massage | C17: 46055 | D17: 2026-02 | E17: TRUE | F17: TRUE | G17: TRUE | H17: TRUE | I17: TRUE | J17: FALSE | K17: FALSE | L17: FALSE | M17: FALSE | N17: FALSE | O17: 0 | P17: 0 | Q17: 0 | U17: 0 | V17: 0 | Z17: gbp
A18: 736264eb-3de6-49d0-a1fb-6706edc2ac61 | B18: Creations Art and Beauty | C18: 46055 | D18: 2026-02 | E18: TRUE | F18: TRUE | G18: TRUE | H18: TRUE | I18: TRUE | J18: TRUE | K18: FALSE | L18: TRUE | M18: TRUE | N18: TRUE | O18: 23 | P18: 12 | Q18: 0 | S18: 46055 | T18: 46233 | U18: 1 | V18: 1.4 | W18: AzqhpEUzYFk7hC0ut | X18: 350 | Y18: active | Z18: gbp
A19: 27022460-a4b6-4090-b990-c97c73a8f56a | B19: Alia Bhat Makeup | C19: 46056 | D19: 2026-02 | E19: TRUE | F19: TRUE | G19: TRUE | H19: TRUE | I19: TRUE | J19: FALSE | K19: TRUE | L19: TRUE | M19: TRUE | N19: TRUE | O19: 19 | P19: 9 | Q19: 0 | S19: 46056 | T19: 46057 | U19: 0 | V19: 0 | Z19: gbp_logs
A20: 410b7b26-6680-425d-8f37-642290a08d52 | B20: Natasha super salon | C20: 46056 | D20: 2026-02 | E20: TRUE | F20: TRUE | G20: TRUE | H20: TRUE | I20: TRUE | J20: FALSE | K20: TRUE | L20: TRUE | M20: TRUE | N20: TRUE | O20: 14 | P20: 8 | Q20: 0 | S20: 46056 | T20: 46057 | U20: 0 | V20: 0 | Z20: gbp_logs
A21: 5b860bec-4d4b-44d0-b44c-1d70e53990f5 | B21: (name not on file) | C21: 46056 | D21: 2026-02 | E21: TRUE | F21: TRUE | G21: TRUE | H21: TRUE | I21: TRUE | J21: FALSE | K21: TRUE | L21: TRUE | M21: TRUE | N21: TRUE | O21: 0 | P21: 0 | Q21: 0 | U21: 0 | V21: 0 | Z21: unknown
A22: 9cde7f89-b4bd-4bf0-a467-27a8be0e059a | B22: Sylph Salon | C22: 46056 | D22: 2026-02 | E22: TRUE | F22: TRUE | G22: TRUE | H22: TRUE | I22: TRUE | J22: FALSE | K22: TRUE | L22: TRUE | M22: TRUE | N22: TRUE | O22: 3 | P22: 2 | Q22: 0 | S22: 46056 | T22: 46056 | U22: 0 | V22: 0 | Z22: gbp_logs
A23: 0ca958cd-28a7-4da9-b78f-b36897268677 | B23: Superb Salon & Spa | C23: 46056 | D23: 2026-02 | E23: TRUE | F23: TRUE | G23: TRUE | H23: TRUE | I23: TRUE | J23: FALSE | K23: TRUE | L23: TRUE | M23: TRUE | N23: TRUE | O23: 12 | P23: 10 | Q23: 0 | S23: 46056 | T23: 46057 | U23: 0 | V23: 0 | Z23: gbp_logs
A24: 37aef7c8-89d0-477a-8929-604d5927322c | B24: Glamour Salon & Spa | C24: 46056 | D24: 2026-02 | E24: TRUE | F24: TRUE | G24: TRUE | H24: TRUE | I24: TRUE | J24: FALSE | K24: TRUE | L24: TRUE | M24: TRUE | N24: TRUE | O24: 7 | P24: 4 | Q24: 0 | S24: 46069 | T24: 46136 | U24: 0 | V24: 0 | Z24: gbp_logs
A25: 46013d86-0ba6-4350-a1f0-d604a85a56a7 | B25: Sunny Spa | C25: 46056 | D25: 2026-02 | E25: TRUE | F25: TRUE | G25: TRUE | H25: TRUE | I25: TRUE | J25: TRUE | K25: FALSE | L25: TRUE | M25: TRUE | N25: TRUE | O25: 8 | P25: 7 | Q25: 0 | S25: 46056 | T25: 46103 | U25: 0 | V25: 0 | Z25: gbp
A26: fdbb9826-ab57-479e-9ac1-2bdcaa1ce2d8 | B26: (name not on file) | C26: 46057 | D26: 2026-02 | E26: TRUE | F26: TRUE | G26: TRUE | H26: TRUE | I26: TRUE | J26: FALSE | K26: TRUE | L26: TRUE | M26: TRUE | N26: TRUE | O26: 7 | P26: 5 | Q26: 0 | S26: 46057 | T26: 46057 | U26: 0 | V26: 0 | Z26: unknown
A27: 7f669982-4323-42d1-8e6d-4314a08033bd | B27: Doom Salon | C27: 46057 | D27: 2026-02 | E27: TRUE | F27: TRUE | G27: TRUE | H27: TRUE | I27: TRUE | J27: FALSE | K27: TRUE | L27: TRUE | M27: TRUE | N27: TRUE | O27: 3 | P27: 1 | Q27: 0 | S27: 46057 | T27: 46057 | U27: 0 | V27: 0 | Z27: gbp_logs
A28: f72ac231-6a87-43ef-b01d-60f1ba670cc9 | B28: Natasha super salon | C28: 46057 | D28: 2026-02 | E28: TRUE | F28: TRUE | G28: TRUE | H28: TRUE | I28: TRUE | J28: FALSE | K28: TRUE | L28: TRUE | M28: TRUE | N28: TRUE | O28: 15 | P28: 1 | Q28: 0 | S28: 46057 | T28: 46063 | U28: 2 | V28: 246 | Z28: gbp_logs
A29: 15963e89-bbce-4a40-bb5c-da14dc135e6d | B29: Saxena's spa | C29: 46057 | D29: 2026-02 | E29: TRUE | F29: TRUE | G29: TRUE | H29: TRUE | I29: TRUE | J29: FALSE | K29: TRUE | L29: TRUE | M29: TRUE | N29: TRUE | O29: 0 | P29: 0 | Q29: 0 | U29: 0 | V29: 0 | Z29: gbp_logs
A30: 67e3523d-dff6-47d4-bebf-55bba69ef991 | B30: ponceluxe laser studio | C30: 46058 | D30: 2026-02 | E30: TRUE | F30: TRUE | G30: TRUE | H30: TRUE | I30: TRUE | J30: FALSE | K30: TRUE | L30: TRUE | M30: TRUE | N30: TRUE | O30: 431 | P30: 54 | Q30: 0 | S30: 46058 | T30: 46237 | U30: 1 | V30: 3500 | W30: AzZkqoV5Dtkn82au8 | X30: 100 | Y30: active | Z30: gbp
A31: daf368e0-54b3-4e34-93b0-b2dd15b204d0 | B31: (name not on file) | C31: 46059 | D31: 2026-02 | E31: TRUE | F31: TRUE | G31: TRUE | H31: TRUE | I31: TRUE | J31: FALSE | K31: TRUE | L31: TRUE | M31: TRUE | N31: TRUE | O31: 22 | P31: 15 | Q31: 0 | S31: 46059 | T31: 46059 | U31: 0 | V31: 0 | Z31: unknown
A32: 5b0c1aa0-57c8-469c-a23c-115aa7e6d30e | B32: Shine Salon & Spa | C32: 46059 | D32: 2026-02 | E32: TRUE | F32: TRUE | G32: TRUE | H32: TRUE | I32: TRUE | J32: TRUE | K32: FALSE | L32: TRUE | M32: TRUE | N32: TRUE | O32: 117 | P32: 70 | Q32: 0 | S32: 46059 | T32: 46107 | U32: 36 | V32: 1582.5 | Z32: gbp_logs
A33: 5872c647-324b-43f1-9b1d-b3dc976b9d91 | B33: Nancy's Nail Spa - Best in Bangalore | C33: 46059 | D33: 2026-02 | E33: TRUE | F33: TRUE | G33: TRUE | H33: TRUE | I33: TRUE | J33: FALSE | K33: TRUE | L33: TRUE | M33: TRUE | N33: TRUE | O33: 17 | P33: 14 | Q33: 0 | S33: 46059 | T33: 46120 | U33: 1 | V33: 500 | Z33: gbp_logs
A34: a6d263b8-b099-4c62-b823-9c5f40d1cec8 | B34: (name not on file) | C34: 46059 | D34: 2026-02 | E34: TRUE | F34: TRUE | G34: TRUE | H34: TRUE | I34: TRUE | J34: FALSE | K34: TRUE | L34: TRUE | M34: TRUE | N34: TRUE | O34: 0 | P34: 0 | Q34: 0 | U34: 0 | V34: 0 | Z34: unknown
A35: 08409d6f-f05c-48e9-aef5-1cf77f9de987 | B35: (name not on file) | C35: 46059 | D35: 2026-02 | E35: TRUE | F35: TRUE | G35: TRUE | H35: TRUE | I35: TRUE | J35: FALSE | K35: TRUE | L35: TRUE | M35: TRUE | N35: TRUE | O35: 0 | P35: 0 | Q35: 0 | U35: 0 | V35: 0 | Z35: unknown
A36: 0f4398a1-bb1a-4bff-96fa-e4948216a5a5 | B36: (name not on file) | C36: 46059 | D36: 2026-02 | E36: TRUE | F36: TRUE | G36: TRUE | H36: TRUE | I36: TRUE | J36: FALSE | K36: TRUE | L36: TRUE | M36: TRUE | N36: TRUE | O36: 0 | P36: 0 | Q36: 0 | U36: 0 | V36: 0 | Z36: unknown
A37: f774f9a1-e3df-458b-949f-a1cd9a346214 | B37: Jeans lash lounge | C37: 46059 | D37: 2026-02 | E37: TRUE | F37: TRUE | G37: TRUE | H37: TRUE | I37: TRUE | J37: TRUE | K37: FALSE | L37: TRUE | M37: TRUE | N37: TRUE | O37: 24 | P37: 22 | Q37: 0 | S37: 46059 | T37: 46223 | U37: 0 | V37: 0 | W37: AzqKGMUj2VY405ZFf | X37: 399 | Y37: active | Z37: gbp
A38: bbc01faa-717b-49c6-90f2-ffa50e45af99 | B38: (name not on file) | C38: 46062 | D38: 2026-02 | E38: TRUE | F38: TRUE | G38: TRUE | H38: TRUE | I38: TRUE | J38: FALSE | K38: TRUE | L38: TRUE | M38: TRUE | N38: TRUE | O38: 4 | P38: 4 | Q38: 0 | S38: 46062 | T38: 46063 | U38: 0 | V38: 0 | Z38: unknown
A39: 8516a713-7500-4ad6-9dde-d49f249abbb4 | B39: Lord of Locs | C39: 46062 | D39: 2026-02 | E39: TRUE | F39: TRUE | G39: TRUE | H39: TRUE | I39: TRUE | J39: TRUE | K39: TRUE | L39: TRUE | M39: TRUE | N39: TRUE | O39: 611 | P39: 67 | Q39: 0 | S39: 45465 | T39: 46237 | U39: 72 | V39: 3956 | W39: cus_Q0yzaP9rDqi7TT | X39: 150 | Y39: active | Z39: gbp
A40: db2e88b9-af6a-4d47-8900-9fcca27925a9 | B40: The Beauty Bar Salon and Spa | C40: 46062 | D40: 2026-02 | E40: TRUE | F40: TRUE | G40: TRUE | H40: TRUE | I40: TRUE | J40: TRUE | K40: FALSE | L40: TRUE | M40: TRUE | N40: TRUE | O40: 2623 | P40: 415 | Q40: 0 | S40: 45197 | T40: 46237 | U40: 271 | V40: 8558.5 | W40: cus_OUyjtBRaU7IAeF | X40: 162.94 | Y40: active | Z40: gbp
A41: c22560c1-9c4e-4d1d-9791-4e148782530c | B41: (name not on file) | C41: 46063 | D41: 2026-02 | E41: TRUE | F41: TRUE | G41: TRUE | H41: TRUE | I41: TRUE | J41: FALSE | K41: TRUE | L41: TRUE | M41: TRUE | N41: TRUE | O41: 3 | P41: 1 | Q41: 0 | S41: 46063 | T41: 46063 | U41: 1 | V41: 7 | Z41: unknown
A42: ccf27c15-8215-40aa-8204-aa7573903d30 | B42: Premium African Braids | C42: 46063 | D42: 2026-02 | E42: TRUE | F42: TRUE | G42: TRUE | H42: TRUE | I42: TRUE | J42: TRUE | K42: FALSE | L42: TRUE | M42: TRUE | N42: TRUE | O42: 111 | P42: 6 | Q42: 0 | S42: 45223 | T42: 46172 | U42: 0 | V42: 0 | W42: cus_RR29SxTsdXcDRw | X42: 108.62 | Y42: active | Z42: gbp
A43: 05916f29-3a28-429d-8fc1-16a83af4204d | B43: Tokai Hair Salon | C43: 46064 | D43: 2026-02 | E43: TRUE | F43: TRUE | G43: TRUE | H43: TRUE | I43: TRUE | J43: FALSE | K43: TRUE | L43: TRUE | M43: TRUE | N43: TRUE | O43: 0 | P43: 0 | Q43: 0 | U43: 0 | V43: 0 | Z43: gbp_logs
A44: b5974616-7dcd-4f9f-91f7-d27f886d343d | B44: (name not on file) | C44: 46064 | D44: 2026-02 | E44: TRUE | F44: TRUE | G44: TRUE | H44: TRUE | I44: TRUE | J44: FALSE | K44: TRUE | L44: TRUE | M44: TRUE | N44: TRUE | O44: 1 | P44: 1 | Q44: 0 | S44: 46064 | T44: 46064 | U44: 0 | V44: 0 | Z44: unknown
A45: 7913db14-c705-4575-af16-c5bd815e7677 | B45: (name not on file) | C45: 46064 | D45: 2026-02 | E45: TRUE | F45: FALSE | G45: FALSE | H45: FALSE | I45: FALSE | J45: FALSE | K45: FALSE | L45: FALSE | M45: FALSE | N45: FALSE | O45: 0 | P45: 0 | Q45: 0 | U45: 0 | V45: 0 | Z45: unknown
A46: 9cf920f2-201a-48cf-9fe9-429538bd4db7 | B46: Saxena's spa | C46: 46065 | D46: 2026-02 | E46: TRUE | F46: TRUE | G46: TRUE | H46: TRUE | I46: TRUE | J46: FALSE | K46: TRUE | L46: TRUE | M46: TRUE | N46: TRUE | O46: 1 | P46: 1 | Q46: 0 | S46: 46065 | T46: 46065 | U46: 0 | V46: 0 | Z46: gbp_logs
A47: ae7ca3a4-295e-4372-8971-d2fc516fc7c5 | B47: Natasha super salon | C47: 46065 | D47: 2026-02 | E47: TRUE | F47: TRUE | G47: FALSE | H47: FALSE | I47: FALSE | J47: FALSE | K47: FALSE | L47: FALSE | M47: FALSE | N47: FALSE | O47: 0 | P47: 0 | Q47: 0 | U47: 0 | V47: 0 | Z47: gbp_logs
A48: 07a8e1fa-f005-4cf5-9182-f1d48d82fa2e | B48: Emporio African Braids | C48: 46065 | D48: 2026-02 | E48: TRUE | F48: TRUE | G48: TRUE | H48: TRUE | I48: TRUE | J48: TRUE | K48: FALSE | L48: TRUE | M48: TRUE | N48: TRUE | O48: 272 | P48: 56 | Q48: 0 | S48: 45526 | T48: 46235 | U48: 39 | V48: 1767.6 | W48: cus_Q7pV871MpzSuGB | X48: 50 | Y48: active | Z48: gbp
A49: 4ebee20a-db99-4e09-b3f0-afa88cb49861 | B49: Adel braids | C49: 46066 | D49: 2026-02 | E49: TRUE | F49: TRUE | G49: TRUE | H49: TRUE | I49: TRUE | J49: TRUE | K49: FALSE | L49: TRUE | M49: TRUE | N49: TRUE | O49: 19 | P49: 17 | Q49: 0 | S49: 46066 | T49: 46220 | U49: 9 | V49: 396 | W49: AzqH9DV2H2LEsW8T | X49: 199 | Y49: active | Z49: gbp
A50: 2223edcb-30e6-4131-ad63-42d5a3b2d50f | B50: Gauri Khan Threading | C50: 46066 | D50: 2026-02 | E50: TRUE | F50: TRUE | G50: TRUE | H50: TRUE | I50: TRUE | J50: FALSE | K50: TRUE | L50: TRUE | M50: TRUE | N50: TRUE | O50: 8 | P50: 8 | Q50: 0 | S50: 46066 | T50: 46067 | U50: 1 | V50: 90 | Z50: gbp_logs
A51: 5f132fee-bad3-4f76-9c53-4b846a78ee80 | B51: Saxena's spa | C51: 46069 | D51: 2026-02 | E51: TRUE | F51: FALSE | G51: FALSE | H51: FALSE | I51: FALSE | J51: FALSE | K51: FALSE | L51: FALSE | M51: FALSE | N51: FALSE | O51: 0 | P51: 0 | Q51: 0 | U51: 0 | V51: 0 | Z51: gbp_logs
A52: deb377ee-558f-4ff8-917e-6a8725703b3f | B52: Natasha super salon | C52: 46069 | D52: 2026-02 | E52: TRUE | F52: TRUE | G52: TRUE | H52: TRUE | I52: TRUE | J52: FALSE | K52: TRUE | L52: TRUE | M52: TRUE | N52: TRUE | O52: 10 | P52: 10 | Q52: 0 | S52: 46069 | T52: 46070 | U52: 0 | V52: 0 | Z52: gbp_logs
A53: b4576719-fbb5-4c71-a074-7d930330c273 | B53: (name not on file) | C53: 46069 | D53: 2026-02 | E53: TRUE | F53: TRUE | G53: TRUE | H53: TRUE | I53: TRUE | J53: FALSE | K53: TRUE | L53: TRUE | M53: TRUE | N53: TRUE | O53: 10 | P53: 10 | Q53: 0 | S53: 46069 | T53: 46070 | U53: 0 | V53: 0 | Z53: unknown
A54: c6df8e71-c5bf-4318-b15b-9e34799ac408 | B54: APUDON GLOSS | C54: 46069 | D54: 2026-02 | E54: TRUE | F54: FALSE | G54: FALSE | H54: FALSE | I54: FALSE | J54: FALSE | K54: FALSE | L54: FALSE | M54: FALSE | N54: FALSE | O54: 0 | P54: 0 | Q54: 0 | U54: 0 | V54: 0 | Z54: gbp
A55: 1a9df389-238c-4bff-9e58-9ceab264099b | B55: Elea Hair Salon | C55: 46069 | D55: 2026-02 | E55: TRUE | F55: TRUE | G55: TRUE | H55: TRUE | I55: TRUE | J55: FALSE | K55: TRUE | L55: TRUE | M55: TRUE | N55: TRUE | O55: 2 | P55: 1 | Q55: 0 | S55: 46076 | T55: 46146 | U55: 0 | V55: 0 | Z55: gbp
A56: 8857bf8f-37aa-4449-b3df-2390bc0571c1 | B56: Vikings salon | C56: 46069 | D56: 2026-02 | E56: TRUE | F56: TRUE | G56: TRUE | H56: TRUE | I56: TRUE | J56: FALSE | K56: TRUE | L56: TRUE | M56: TRUE | N56: TRUE | O56: 1 | P56: 1 | Q56: 0 | S56: 46069 | T56: 46069 | U56: 0 | V56: 0 | Z56: gbp
A57: 057bd190-669e-4fc4-b5b1-814d5f806efc | B57: Flanker42 Data Solutions | C57: 46069 | D57: 2026-02 | E57: TRUE | F57: TRUE | G57: TRUE | H57: TRUE | I57: TRUE | J57: FALSE | K57: TRUE | L57: TRUE | M57: TRUE | N57: TRUE | O57: 0 | P57: 0 | Q57: 0 | U57: 0 | V57: 0 | Z57: gbp_logs
A58: d0803500-603f-4fcd-8a21-c643ecbde37c | B58: Kanak'sKaya | C58: 46069 | D58: 2026-02 | E58: TRUE | F58: TRUE | G58: TRUE | H58: TRUE | I58: TRUE | J58: FALSE | K58: TRUE | L58: TRUE | M58: TRUE | N58: TRUE | O58: 6 | P58: 0 | Q58: 0 | S58: 46100 | T58: 46210 | U58: 0 | V58: 0 | Z58: gbp
A59: f4e8b9a9-46e1-479f-9f79-6d0f56fe0c74 | B59: Furiends Pet Salon | C59: 46069 | D59: 2026-02 | E59: TRUE | F59: TRUE | G59: TRUE | H59: TRUE | I59: TRUE | J59: FALSE | K59: TRUE | L59: TRUE | M59: TRUE | N59: TRUE | O59: 1 | P59: 1 | Q59: 0 | S59: 46069 | T59: 46069 | U59: 0 | V59: 0 | Z59: gbp
A60: 944015d3-4946-455b-81b1-50c191c065fe | B60: Chetan Beauty Salon | C60: 46069 | D60: 2026-02 | E60: TRUE | F60: TRUE | G60: TRUE | H60: TRUE | I60: TRUE | J60: FALSE | K60: TRUE | L60: TRUE | M60: TRUE | N60: TRUE | O60: 0 | P60: 0 | Q60: 0 | U60: 0 | V60: 0 | Z60: gbp_logs
A61: c70eb5a6-8f52-446c-b67b-49560bbea6ae | B61: Hubern's Hair Salon | C61: 46069 | D61: 2026-02 | E61: TRUE | F61: TRUE | G61: TRUE | H61: TRUE | I61: TRUE | J61: FALSE | K61: TRUE | L61: TRUE | M61: TRUE | N61: TRUE | O61: 0 | P61: 0 | Q61: 0 | U61: 0 | V61: 0 | Z61: gbp
A62: 596bd62f-ea2d-4ce2-a44b-bc7c8888b034 | B62: MUTO salon | C62: 46069 | D62: 2026-02 | E62: TRUE | F62: TRUE | G62: TRUE | H62: TRUE | I62: TRUE | J62: FALSE | K62: TRUE | L62: TRUE | M62: TRUE | N62: TRUE | O62: 0 | P62: 0 | Q62: 0 | U62: 0 | V62: 0 | Z62: gbp
A63: 2e5da6d2-b27e-4cfc-8cd5-9af10f425b72 | B63: BB Salon | C63: 46069 | D63: 2026-02 | E63: TRUE | F63: TRUE | G63: TRUE | H63: TRUE | I63: TRUE | J63: FALSE | K63: TRUE | L63: TRUE | M63: TRUE | N63: TRUE | O63: 3 | P63: 0 | Q63: 0 | S63: 46129 | T63: 46142 | U63: 0 | V63: 0 | Z63: gbp
A64: b437c301-371b-45b7-8b9b-d82f78e6a14d | B64: (name not on file) | C64: 46069 | D64: 2026-02 | E64: TRUE | F64: TRUE | G64: TRUE | H64: TRUE | I64: TRUE | J64: FALSE | K64: TRUE | L64: TRUE | M64: TRUE | N64: TRUE | O64: 0 | P64: 0 | Q64: 0 | U64: 0 | V64: 0 | Z64: unknown
A65: 7e3f3474-2872-4e9c-8127-b50b5d9550b0 | B65: (name not on file) | C65: 46070 | D65: 2026-02 | E65: TRUE | F65: TRUE | G65: TRUE | H65: TRUE | I65: TRUE | J65: FALSE | K65: TRUE | L65: TRUE | M65: TRUE | N65: TRUE | O65: 2 | P65: 2 | Q65: 0 | S65: 46070 | T65: 46070 | U65: 0 | V65: 0 | Z65: unknown
A66: 01574329-949e-4df4-9a4c-429f61c2ec0c | B66: Saxena Consultancy | C66: 46070 | D66: 2026-02 | E66: TRUE | F66: TRUE | G66: TRUE | H66: TRUE | I66: TRUE | J66: FALSE | K66: TRUE | L66: TRUE | M66: TRUE | N66: TRUE | O66: 4 | P66: 4 | Q66: 0 | S66: 46070 | T66: 46070 | U66: 0 | V66: 0 | Z66: gbp_logs
A67: 90f08be7-5e18-468b-bfc1-70908389b793 | B67: Gauri Khan Threading | C67: 46070 | D67: 2026-02 | E67: TRUE | F67: TRUE | G67: TRUE | H67: TRUE | I67: TRUE | J67: FALSE | K67: TRUE | L67: TRUE | M67: TRUE | N67: TRUE | O67: 1 | P67: 1 | Q67: 0 | S67: 46070 | T67: 46070 | U67: 0 | V67: 0 | Z67: gbp_logs
A68: 383a7fdd-b410-414b-a3db-82c1774616fb | B68: Hair By Camille | C68: 46070 | D68: 2026-02 | E68: TRUE | F68: TRUE | G68: TRUE | H68: TRUE | I68: TRUE | J68: TRUE | K68: FALSE | L68: TRUE | M68: TRUE | N68: TRUE | O68: 605 | P68: 48 | Q68: 0 | S68: 45658 | T68: 46237 | U68: 0 | V68: 0 | W68: cus_RiJ2uhBiBlg9ZH | X68: 179 | Y68: active | Z68: gbp
A69: 3be18092-1615-4c48-915c-f83e8ba38950 | B69: Om salon Uni Hair cut | C69: 46071 | D69: 2026-02 | E69: TRUE | F69: TRUE | G69: TRUE | H69: TRUE | I69: TRUE | J69: FALSE | K69: TRUE | L69: TRUE | M69: TRUE | N69: TRUE | O69: 3 | P69: 3 | Q69: 0 | S69: 46071 | T69: 46071 | U69: 0 | V69: 0 | Z69: gbp_logs
A70: 71a02eb8-ece7-43a2-952a-4554295a5207 | B70: (name not on file) | C70: 46071 | D70: 2026-02 | E70: TRUE | F70: TRUE | G70: TRUE | H70: TRUE | I70: TRUE | J70: FALSE | K70: TRUE | L70: TRUE | M70: TRUE | N70: TRUE | O70: 1 | P70: 1 | Q70: 0 | S70: 46071 | T70: 46071 | U70: 0 | V70: 0 | Z70: unknown
A71: d4b0001a-028f-492d-bf2e-cbf163c4756c | B71: (name not on file) | C71: 46071 | D71: 2026-02 | E71: TRUE | F71: TRUE | G71: FALSE | H71: FALSE | I71: FALSE | J71: FALSE | K71: FALSE | L71: FALSE | M71: FALSE | N71: FALSE | O71: 0 | P71: 0 | Q71: 0 | U71: 0 | V71: 0 | Z71: unknown
A72: 4a056532-3362-4689-b3b5-36bc43cc5150 | B72: Saxena's spa | C72: 46072 | D72: 2026-02 | E72: TRUE | F72: TRUE | G72: TRUE | H72: TRUE | I72: TRUE | J72: FALSE | K72: TRUE | L72: TRUE | M72: TRUE | N72: TRUE | O72: 4 | P72: 4 | Q72: 0 | S72: 46072 | T72: 46072 | U72: 0 | V72: 0 | Z72: gbp_logs
A73: cee7df4b-ba3b-43df-858d-9304187b4723 | B73: Natasha super salon | C73: 46072 | D73: 2026-02 | E73: TRUE | F73: TRUE | G73: TRUE | H73: TRUE | I73: TRUE | J73: FALSE | K73: TRUE | L73: TRUE | M73: TRUE | N73: TRUE | O73: 2 | P73: 2 | Q73: 0 | S73: 46072 | T73: 46073 | U73: 0 | V73: 0 | Z73: gbp_logs
A74: e18a07a4-c625-4130-b7b1-9c30dadfd462 | B74: (name not on file) | C74: 46072 | D74: 2026-02 | E74: TRUE | F74: TRUE | G74: TRUE | H74: TRUE | I74: TRUE | J74: FALSE | K74: TRUE | L74: TRUE | M74: TRUE | N74: TRUE | O74: 6 | P74: 6 | Q74: 0 | S74: 46072 | T74: 46073 | U74: 0 | V74: 0 | Z74: unknown
A75: 5e89682f-bcb4-42ad-8513-b8e6775dd43b | B75: (name not on file) | C75: 46072 | D75: 2026-02 | E75: TRUE | F75: FALSE | G75: FALSE | H75: FALSE | I75: FALSE | J75: FALSE | K75: FALSE | L75: FALSE | M75: FALSE | N75: FALSE | O75: 0 | P75: 0 | Q75: 0 | U75: 0 | V75: 0 | Z75: unknown
A76: 9dc141d1-5328-4203-b80d-9ab04501e647 | B76: HSR Beauty | C76: 46072 | D76: 2026-02 | E76: TRUE | F76: TRUE | G76: TRUE | H76: TRUE | I76: TRUE | J76: FALSE | K76: TRUE | L76: TRUE | M76: TRUE | N76: TRUE | O76: 7 | P76: 7 | Q76: 0 | S76: 46086 | T76: 46086 | U76: 0 | V76: 0 | Z76: gbp_logs
A77: 35ec62bf-e310-4eac-a4d7-5749940717b7 | B77: (name not on file) | C77: 46073 | D77: 2026-02 | E77: TRUE | F77: FALSE | G77: FALSE | H77: FALSE | I77: FALSE | J77: FALSE | K77: FALSE | L77: FALSE | M77: FALSE | N77: FALSE | O77: 0 | P77: 0 | Q77: 0 | U77: 0 | V77: 0 | Z77: unknown
A78: 65ea1fd7-32da-44db-b820-bfc51ce9eb03 | B78: Saxena's spa | C78: 46073 | D78: 2026-02 | E78: TRUE | F78: FALSE | G78: FALSE | H78: FALSE | I78: FALSE | J78: FALSE | K78: FALSE | L78: FALSE | M78: FALSE | N78: FALSE | O78: 0 | P78: 0 | Q78: 0 | U78: 0 | V78: 0 | Z78: gbp_logs
A79: fa2619ea-5509-4815-8b9e-a933e26321bf | B79: Natasha super salon | C79: 46073 | D79: 2026-02 | E79: TRUE | F79: TRUE | G79: TRUE | H79: TRUE | I79: TRUE | J79: FALSE | K79: TRUE | L79: TRUE | M79: TRUE | N79: TRUE | O79: 0 | P79: 0 | Q79: 0 | U79: 0 | V79: 0 | Z79: gbp_logs
A80: 531390d6-9578-4932-bd96-9b31b1ca98b9 | B80: Himalaya Spa & Healing Center | C80: 46073 | D80: 2026-02 | E80: TRUE | F80: TRUE | G80: TRUE | H80: TRUE | I80: TRUE | J80: TRUE | K80: FALSE | L80: TRUE | M80: TRUE | N80: TRUE | O80: 227 | P80: 67 | Q80: 0 | S80: 46077 | T80: 46141 | U80: 5 | V80: 192 | W80: cus_U0FgisDa4ev4b3 | Y80: cancelled | Z80: gbp
A81: 54a27121-0b23-4ed0-9153-aec06840a7f7 | B81: it's Waxing & Threading | C81: 46074 | D81: 2026-02 | E81: TRUE | F81: TRUE | G81: TRUE | H81: TRUE | I81: TRUE | J81: FALSE | K81: TRUE | L81: TRUE | M81: TRUE | N81: TRUE | O81: 106 | P81: 76 | Q81: 0 | S81: 46078 | T81: 46235 | U81: 14 | V81: 903 | W81: 16AflPVAZLsIpMXS4 | X81: 1250.07 | Y81: active | Z81: gbp
A82: 8b68efc1-f459-41e4-a791-e15ea36c7419 | B82: Saxena's spa | C82: 46076 | D82: 2026-02 | E82: TRUE | F82: TRUE | G82: TRUE | H82: TRUE | I82: TRUE | J82: FALSE | K82: TRUE | L82: TRUE | M82: TRUE | N82: TRUE | O82: 0 | P82: 0 | Q82: 0 | U82: 0 | V82: 0 | Z82: gbp_logs
A83: c20e28a3-3732-4e0a-a52e-d45eba2814ae | B83: COAL Hair Dressers | C83: 46076 | D83: 2026-02 | E83: TRUE | F83: TRUE | G83: TRUE | H83: TRUE | I83: TRUE | J83: FALSE | K83: TRUE | L83: TRUE | M83: TRUE | N83: TRUE | O83: 7 | P83: 3 | Q83: 0 | S83: 46076 | T83: 46119 | U83: 2 | V83: 467.2 | Z83: gbp_logs
A84: 83916826-46e1-4f27-a452-cc286ad5dd5a | B84: Saxena's spa | C84: 46076 | D84: 2026-02 | E84: TRUE | F84: TRUE | G84: TRUE | H84: TRUE | I84: TRUE | J84: FALSE | K84: TRUE | L84: TRUE | M84: TRUE | N84: TRUE | O84: 16 | P84: 16 | Q84: 0 | S84: 46076 | T84: 46076 | U84: 0 | V84: 0 | Z84: gbp_logs
A85: aba20322-bc17-4a18-b31d-326dd9b15d69 | B85: Elegant Expressions Beauty And Styles Salon (DBA) Frankiss Signature Hair | C85: 46076 | D85: 2026-02 | E85: TRUE | F85: TRUE | G85: TRUE | H85: TRUE | I85: TRUE | J85: FALSE | K85: TRUE | L85: TRUE | M85: TRUE | N85: TRUE | O85: 718 | P85: 45 | Q85: 0 | S85: 45416 | T85: 46197 | U85: 0 | V85: 0 | W85: cus_QvDY5RSTT5uwmB | Y85: cancelled | Z85: gbp
A86: 11e81849-6bde-4d33-855d-927f443698bd | B86: Miracle hands braiding Studio | C86: 46077 | D86: 2026-02 | E86: TRUE | F86: TRUE | G86: TRUE | H86: TRUE | I86: TRUE | J86: FALSE | K86: TRUE | L86: TRUE | M86: TRUE | N86: TRUE | O86: 391 | P86: 33 | Q86: 0 | S86: 45259 | T86: 46237 | U86: 0 | V86: 0 | W86: cus_PU3NzApnWkMxob | X86: 150 | Y86: active | Z86: gbp
A87: 5cd38499-e52e-4591-9053-15b5cb7f0f44 | B87: Glamourous Salon & Spa | C87: 46078 | D87: 2026-02 | E87: TRUE | F87: FALSE | G87: FALSE | H87: FALSE | I87: FALSE | J87: FALSE | K87: FALSE | L87: FALSE | M87: FALSE | N87: FALSE | O87: 0 | P87: 0 | Q87: 0 | U87: 0 | V87: 0 | Z87: gbp_logs
A88: 1b26e354-eb83-433b-a77c-7f2b3f9355f3 | B88: Natasha super salon | C88: 46078 | D88: 2026-02 | E88: TRUE | F88: TRUE | G88: TRUE | H88: TRUE | I88: TRUE | J88: FALSE | K88: TRUE | L88: TRUE | M88: TRUE | N88: TRUE | O88: 21 | P88: 21 | Q88: 0 | S88: 46078 | T88: 46079 | U88: 0 | V88: 0 | Z88: gbp_logs
A89: 1b4dcb5c-13a5-45c2-a457-6440fe18841e | B89: DianeFabulous | C89: 46078 | D89: 2026-02 | E89: TRUE | F89: TRUE | G89: TRUE | H89: TRUE | I89: TRUE | J89: TRUE | K89: FALSE | L89: TRUE | M89: TRUE | N89: TRUE | O89: 10 | P89: 10 | Q89: 0 | S89: 46078 | T89: 46180 | U89: 2 | V89: 100 | W89: AzqUCIV2CxWKp5qw | Y89: cancelled | Z89: gbp
A90: bdcb9096-7934-440c-bc24-57268f63b08b | B90: Vida Beauty Bar | C90: 46078 | D90: 2026-02 | E90: TRUE | F90: TRUE | G90: TRUE | H90: TRUE | I90: TRUE | J90: FALSE | K90: TRUE | L90: TRUE | M90: TRUE | N90: TRUE | O90: 692 | P90: 191 | Q90: 0 | S90: 46078 | T90: 46237 | U90: 0 | V90: 0 | W90: 16BXdwUvalf4c3pdW | X90: 199 | Y90: active | Z90: gbp
A91: 3a38f3a3-b66e-4f62-b841-3e9ce14350ad | B91: Golden Hair Braiding | C91: 46079 | D91: 2026-02 | E91: TRUE | F91: TRUE | G91: TRUE | H91: TRUE | I91: TRUE | J91: FALSE | K91: TRUE | L91: TRUE | M91: TRUE | N91: TRUE | O91: 128 | P91: 128 | Q91: 0 | S91: 46107 | T91: 46234 | U91: 0 | V91: 0 | W91: AzqO4bV13axpA8JbC | X91: 200 | Y91: active | Z91: gbp
A92: 9003bb0e-f33b-4ee6-ad2c-74463ffed97f | B92: (name not on file) | C92: 46079 | D92: 2026-02 | E92: TRUE | F92: TRUE | G92: TRUE | H92: TRUE | I92: TRUE | J92: FALSE | K92: TRUE | L92: TRUE | M92: TRUE | N92: TRUE | O92: 23 | P92: 16 | Q92: 0 | S92: 46104 | T92: 46142 | U92: 3 | V92: 111 | Z92: unknown
A93: 04d19914-49c8-44f2-b251-5fbd643a2300 | B93: Jamila African Hair Braiding | C93: 46079 | D93: 2026-02 | E93: TRUE | F93: TRUE | G93: TRUE | H93: TRUE | I93: TRUE | J93: FALSE | K93: TRUE | L93: TRUE | M93: TRUE | N93: TRUE | O93: 114 | P93: 114 | Q93: 0 | S93: 46088 | T93: 46237 | U93: 0 | V93: 0 | W93: AzqbodV0xNjaWDWp0 | X93: 150 | Y93: active | Z93: gbp
A94: 24bfdf15-2446-4669-8c35-771d953ac52a | B94: 5T BEAUTY ACADEMY | C94: 46079 | D94: 2026-02 | E94: TRUE | F94: FALSE | G94: FALSE | H94: FALSE | I94: FALSE | J94: FALSE | K94: FALSE | L94: FALSE | M94: FALSE | N94: FALSE | O94: 0 | P94: 0 | Q94: 0 | U94: 0 | V94: 0 | W94: AzqcbiV0qkmiw6bth | Y94: cancelled | Z94: gbp
A95: 65dd98d3-43be-49f3-93f4-ef35117d66b3 | B95: Natasha super salon | C95: 46080 | D95: 2026-02 | E95: TRUE | F95: TRUE | G95: TRUE | H95: TRUE | I95: TRUE | J95: FALSE | K95: TRUE | L95: TRUE | M95: TRUE | N95: TRUE | O95: 14 | P95: 14 | Q95: 0 | S95: 46080 | T95: 46083 | U95: 1 | V95: 55 | Z95: gbp_logs
A96: 059e2eba-670d-4618-bd84-63b3a685bad1 | B96: Naomi's African Hair Braiding Salon | C96: 46080 | D96: 2026-02 | E96: TRUE | F96: TRUE | G96: TRUE | H96: TRUE | I96: TRUE | J96: FALSE | K96: FALSE | L96: FALSE | M96: FALSE | N96: FALSE | O96: 0 | P96: 0 | Q96: 0 | U96: 0 | V96: 0 | W96: cus_PjQE46ZlgRsQvY | X96: 100 | Y96: active | Z96: gbp
A97: 52edec61-4a93-4906-b110-28c16415fba5 | B97: Saxena's spa | C97: 46083 | D97: 2026-03 | E97: TRUE | F97: TRUE | G97: TRUE | H97: TRUE | I97: TRUE | J97: FALSE | K97: TRUE | L97: TRUE | M97: TRUE | N97: TRUE | O97: 0 | P97: 0 | Q97: 0 | U97: 0 | V97: 0 | Z97: gbp_logs
A98: ffe5f041-42ca-46f0-adf2-ce15e6b17731 | B98: (name not on file) | C98: 46083 | D98: 2026-03 | E98: TRUE | F98: TRUE | G98: TRUE | H98: TRUE | I98: TRUE | J98: FALSE | K98: TRUE | L98: TRUE | M98: TRUE | N98: TRUE | O98: 0 | P98: 0 | Q98: 0 | U98: 0 | V98: 0 | Z98: unknown
A99: 2dacf4e8-5a71-4efa-851e-b482eb38a6b0 | B99: XCAPE | C99: 46083 | D99: 2026-03 | E99: FALSE | F99: TRUE | G99: TRUE | H99: TRUE | I99: TRUE | J99: TRUE | K99: FALSE | L99: FALSE | M99: FALSE | N99: TRUE | O99: 10 | P99: 0 | Q99: 0 | S99: 46112 | T99: 46116 | U99: 2 | V99: 290 | W99: 16BRsZV0gyslo6Gfi | Y99: cancelled | Z99: gbp
A100: b7c19608-d68c-4f1d-860d-ff6f70d4a564 | B100: The Moon Beauty | Facial Spa | C100: 46083 | D100: 2026-03 | E100: TRUE | F100: TRUE | G100: FALSE | H100: FALSE | I100: FALSE | J100: FALSE | K100: FALSE | L100: FALSE | M100: FALSE | N100: FALSE | O100: 0 | P100: 0 | Q100: 0 | U100: 0 | V100: 0 | W100: cus_Q265iKOdiQIKnz | X100: 200 | Y100: active | Z100: gbp
...

Sheet Cohort Retention
A1: Cohort retention — do accounts keep booking after they switch it on?
A2: Cohort = month the location entered onboarding. Live = took a native booking within 30 days of the as-of date on Summary.
A4: Cohort | B4: Entered | C4: Enabled | D4: Ever booked | E4: Live in last 30d | F4: % of enabled still live
A5: 2026-01 | B5: =SUMPRODUCT(--(Locations!$D$2:$D$445=$A5)) | C5: =SUMPRODUCT(--(Locations!$D$2:$D$445=$A5),--(Locations!$M$2:$M$445=TRUE)) | D5: =SUMPRODUCT(--(Locations!$D$2:$D$445=$A5),--(Locations!$M$2:$M$445=TRUE),--(Locations!$O$2:$O$445>0)) | E5: =SUMPRODUCT(--(Locations!$D$2:$D$445=$A5),--(Locations!$M$2:$M$445=TRUE),--(Locations!$T$2:$T$445>=Summary!$B$3-30)) | F5: =IFERROR(E5/C5,0)
A6: 2026-02 | B6: =SUMPRODUCT(--(Locations!$D$2:$D$445=$A6)) | C6: =SUMPRODUCT(--(Locations!$D$2:$D$445=$A6),--(Locations!$M$2:$M$445=TRUE)) | D6: =SUMPRODUCT(--(Locations!$D$2:$D$445=$A6),--(Locations!$M$2:$M$445=TRUE),--(Locations!$O$2:$O$445>0)) | E6: =SUMPRODUCT(--(Locations!$D$2:$D$445=$A6),--(Locations!$M$2:$M$445=TRUE),--(Locations!$T$2:$T$445>=Summary!$B$3-30)) | F6: =IFERROR(E6/C6,0)
A7: 2026-03 | B7: =SUMPRODUCT(--(Locations!$D$2:$D$445=$A7)) | C7: =SUMPRODUCT(--(Locations!$D$2:$D$445=$A7),--(Locations!$M$2:$M$445=TRUE)) | D7: =SUMPRODUCT(--(Locations!$D$2:$D$445=$A7),--(Locations!$M$2:$M$445=TRUE),--(Locations!$O$2:$O$445>0)) | E7: =SUMPRODUCT(--(Locations!$D$2:$D$445=$A7),--(Locations!$M$2:$M$445=TRUE),--(Locations!$T$2:$T$445>=Summary!$B$3-30)) | F7: =IFERROR(E7/C7,0)
A8: 2026-04 | B8: =SUMPRODUCT(--(Locations!$D$2:$D$445=$A8)) | C8: =SUMPRODUCT(--(Locations!$D$2:$D$445=$A8),--(Locations!$M$2:$M$445=TRUE)) | D8: =SUMPRODUCT(--(Locations!$D$2:$D$445=$A8),--(Locations!$M$2:$M$445=TRUE),--(Locations!$O$2:$O$445>0)) | E8: =SUMPRODUCT(--(Locations!$D$2:$D$445=$A8),--(Locations!$M$2:$M$445=TRUE),--(Locations!$T$2:$T$445>=Summary!$B$3-30)) | F8: =IFERROR(E8/C8,0)
A9: 2026-05 | B9: =SUMPRODUCT(--(Locations!$D$2:$D$445=$A9)) | C9: =SUMPRODUCT(--(Locations!$D$2:$D$445=$A9),--(Locations!$M$2:$M$445=TRUE)) | D9: =SUMPRODUCT(--(Locations!$D$2:$D$445=$A9),--(Locations!$M$2:$M$445=TRUE),--(Locations!$O$2:$O$445>0)) | E9: =SUMPRODUCT(--(Locations!$D$2:$D$445=$A9),--(Locations!$M$2:$M$445=TRUE),--(Locations!$T$2:$T$445>=Summary!$B$3-30)) | F9: =IFERROR(E9/C9,0)
A10: 2026-06 | B10: =SUMPRODUCT(--(Locations!$D$2:$D$445=$A10)) | C10: =SUMPRODUCT(--(Locations!$D$2:$D$445=$A10),--(Locations!$M$2:$M$445=TRUE)) | D10: =SUMPRODUCT(--(Locations!$D$2:$D$445=$A10),--(Locations!$M$2:$M$445=TRUE),--(Locations!$O$2:$O$445>0)) | E10: =SUMPRODUCT(--(Locations!$D$2:$D$445=$A10),--(Locations!$M$2:$M$445=TRUE),--(Locations!$T$2:$T$445>=Summary!$B$3-30)) | F10: =IFERROR(E10/C10,0)
A11: 2026-07 | B11: =SUMPRODUCT(--(Locations!$D$2:$D$445=$A11)) | C11: =SUMPRODUCT(--(Locations!$D$2:$D$445=$A11),--(Locations!$M$2:$M$445=TRUE)) | D11: =SUMPRODUCT(--(Locations!$D$2:$D$445=$A11),--(Locations!$M$2:$M$445=TRUE),--(Locations!$O$2:$O$445>0)) | E11: =SUMPRODUCT(--(Locations!$D$2:$D$445=$A11),--(Locations!$M$2:$M$445=TRUE),--(Locations!$T$2:$T$445>=Summary!$B$3-30)) | F11: =IFERROR(E11/C11,0)
A12: TOTAL | B12: =SUM(B5:B11) | C12: =SUM(C5:C11) | D12: =SUM(D5:D11) | E12: =SUM(E5:E11) | F12: =IFERROR(E12/C12,0)
A14: Every settled cohort lands at roughly 20-25% still booking. July looks healthy only because it just onboarded — it has not aged yet. This is a retention problem, not a conversion problem.

Sheet Bookings and Revenue
A1: Bookings, payments and displaced incumbents
A3: VALUE PROCESSED
A4: Metric | B4: Value | C4: Source
A5: Completed payments (USD) | B5: =SUM(Locations!$V$2:$V$445) | C5: Locations sheet, col U
A6: Completed transactions | B6: =SUM(Locations!$U$2:$U$445) | C6: Locations sheet, col T
A7: Accounts that processed a payment | B7: =SUMPRODUCT(--(Locations!$U$2:$U$445>0)) | C7: Locations sheet
A8: Native bookings | B8: =SUM(Locations!$O$2:$O$445) | C8: Excludes migrated history
A9: Customer self-serve bookings | B9: =SUM(Locations!$P$2:$P$445) | C9: created_by_type EC or CLIENT
A10: Migrated (historical) bookings | B10: =SUM(Locations!$Q$2:$Q$445) | C10: Imported, not earned
A12: BOOKING CREATOR MIX — all bookings, from scheduling.bookings
A13: Hardcoded. Source: scheduling.bookings grouped by created_by_type and migration_source, queried 03/08/26.
A14: Creator type | B14: Bookings | C14: Accounts | D14: Meaning
A15: SP — staff-made | B15: 11028 | C15: 197 | D15: Business enters the booking
A16: SYSTEM — automated | B16: 7091 | C16: 4
A17: EC — end customer self-serve | B17: 4352 | C17: 247 | D17: The number that proves the product works
A18: CLIENT — client app | B18: 260 | C18: 31
A19: MCP — agent | B19: 48 | C19: 12
A20: MIGRATION — native flag | B20: 240 | C20: 1
A22: INCUMBENT SYSTEMS MIGRATED FROM
A23: Hardcoded. Source: scheduling.bookings.migration_source, queried 03/08/26. Only 14 accounts imported history — the rest either had nothing to move or never fully switched.
A24: Prior system | B24: Bookings migrated | C24: Accounts
A25: Zoca internal ops | B25: 15756 | C25: 2
A26: Square | B26: 7748 | C26: 4
A27: Vagaro | B27: 6321 | C27: 1
A28: Fresha | B28: 4984 | C28: 1
A29: Booksy | B29: 4088 | C29: 1
A30: GlossGenius | B30: 3978 | C30: 1
A31: Acuity | B31: 3338 | C31: 4
A32: Setmore | B32: 1158 | C32: 1
A33: GoDaddy | B33: 56 | C33: 2
A35: RECONCILIATION — why this sheet says $632,036 and the written report says $645,568
A36: This workbook aggregates the 444 locations in scheduling.onboarding. scheduling.payments contains one further paying entity with no onboarding record, worth $13,532 across 1 account. All-entity truth: $645,568.21 / 6,061 completed transactions / 139 accounts. Neither figure is wrong; they have different denominators. Quote the all-entity number externally and this one when working from these sheets.

Sheet Objection Themes
A1: Why accounts did not convert
A2: Two classes of evidence. The mechanical evidence is reliable. The stated evidence is directional only.
A4: MECHANICAL — proven by the funnel
A5: Finding | B5: Value | C5: Why it matters
A6: Locations that skipped payment setup | B6: =SUMPRODUCT(--(Locations!$K$2:$K$445=TRUE)) | C6: No deposits, no no-show fees. An account without payments is running a diary, and a diary loses to the incumbent.
A7: Locations that configured payments | B7: =SUMPRODUCT(--(Locations!$J$2:$J$445=TRUE))
A8: Enabled but never took a booking | B8: =SUMPRODUCT(--(Locations!$M$2:$M$445=TRUE),--(Locations!$O$2:$O$445=0)) | C8: Completed every setup step, then did nothing. Setup completion is being mistaken for adoption.
A9: Enabled but dormant (no booking in 30d) | B9: =SUMPRODUCT(--(Locations!$M$2:$M$445=TRUE),--(Locations!$T$2:$T$445<Summary!$B$3-30))
A10: Accounts that imported history from a rival | B10: =SUMPRODUCT(--(Locations!$R$2:$R$445<>"")) | C10: Only this many actually moved their history across.
A13: STATED — topic prevalence across 1,829 scheduling calls, 01/11/25 to 03/08/26
A14: Hardcoded. Source: regex over sales.fireflies_meeting.summary, queried 03/08/26. CAUTION: these calls carry no entity_id, so these reasons CANNOT be counted per account. Do not present as 'N accounts said X'.
A15: Topic | B15: Calls | C15: Share of 1,829 | D15: Comment
A16: Deferred / 'not right now' | B16: 441 | C16: =B16/1829
A17: Migration or data-transfer effort | B17: 247 | C17: =B17/1829
A18: Payments, deposits, no-show fees | B18: 227 | C18: =B18/1829 | D18: Matches the mechanical finding above
A19: Contract / lock-in language | B19: 215 | C19: =B19/1829 | D19: Noisy — 'contract' matches loosely
A20: Named an incumbent competitor | B20: 303 | C20: =B20/1829 | D20: The reliable signal
A21: Explicit refusal language | B21: 174 | C21: =B21/1829
A22: Prefers phone / walk-in / manual | B22: 119 | C22: =B22/1829
A23: Price or budget | B23: 69 | C23: =B23/1829
A24: Staff resistance or complexity | B24: 42 | C24: =B24/1829
A26: INCUMBENTS NAMED IN CALL SUMMARIES
A27: Hardcoded, same source. Square is inflated — the word matches non-product uses. Treat Vagaro, Booksy, Mindbody and Fresha as the reliable signals.
A28: Competitor | B28: Calls naming it
A29: Square (inflated) | B29: 269
A30: Vagaro | B30: 105
A31: Booksy | B31: 46
A32: Mindbody | B32: 39
A33: Fresha | B33: 35
A34: Acuity | B34: 26
A35: StyleSeat | B35: 11
A36: GlossGenius | B36: 11
A37: Boulevard / Phorest / Setmore / Schedulicity | B37: 43
A39: THEMES VERIFIED BY READING CALL EXCERPTS BY HAND
A40: • Feature gaps keep the old system alive — staff revenue and commission reporting, clock-in/out, staff permission levels, calendar column-per-staff view, selective client blocking, package and membership migration, intake forms.
A41: • Payment processor economics — Stripe rates raised as a negotiation point rather than accepted.
A42: • Base subscription price — $149/month cited as unaffordable by an account under budget freeze. A whole-platform objection, not a scheduling one.
A43: • Rollback on confusion — at least one account asked for the booking system to be revoked 'to reduce confusion and inefficiency' after enabling it.
A44: • Free is the wedge that works — where the pitch replaces a paid incumbent at no cost, it lands. Cost displacement is the strongest observed motivator.

Sheet Instrumentation Gaps
A1: Where a pitch record should live, and what is actually there
A2: This is the finding underneath the finding: the pitch is recoverable by archaeology, but it is not recorded.
A4: System / table | B4: What is actually there | C4: Consequence
A5: cx.upsell_potential | B5: Covers only the five AI agents (ADS, WIN, LOYALTY, SOCIAL, DISCOVERY). No scheduling row. Stops 12/01/26. All 3,124 rows status POTENTIAL, upsold_amount = 0 on every row. | C5: No upsell tracking for scheduling at all
A6: sales.customer_meetings.product | B6: Null on 11,113 of 11,128 rows (99.9%). The 15 populated rows are May 2025 only. | C6: Cannot tell which product a meeting was about
A7: sales.fireflies_meeting.entity_id | B7: Populated on 431 of 22,242 rows (1.9%). | C7: Useless as a join key — attribution had to go via participant email instead
A8: cx.open_issues / cx.churn_potential | B8: Both stop writing 14/01/26 — two weeks BEFORE scheduling launched. | C8: The qualitative feed went dark at the worst possible moment
A9: offboarding.reason_template_mapping | B9: 30 rows total, exactly 5 per reason. | C9: A seeded template list, not collected data
A10: Chargebee catalogue | B10: No scheduling SKU. Closest items are Booking-Agent, Lead-to-Booking, FrontDesk. | C10: Scheduling is bundled, so billing shows no adoption signal
A11: scheduling.onboarding.entity_id | B11: Zero overlap with bookings or Chargebee. The account key is location_entity_id. | C11: A join on entity_id returns a valid-looking all-zero result rather than an error
A13: TO MAKE THIS ANSWERABLE WITHOUT ARCHAEOLOGY
A14: Priority | B14: Action | C14: Why
A15: 1 | B15: Add pitched_at / pitched_by / pitch_outcome / decline_reason to the scheduling onboarding record, set when an AM makes the offer | C15: Without it every future version of this question needs a month of transcript work
A16: 2 | B16: Backfill entity_id on Fireflies rows from participants email | C16: 98% of call intelligence is currently unattributable; this unlocks it retrospectively and makes the pitch a live metric
A17: 3 | B17: Find out why cx.open_issues and cx.churn_potential stopped writing on 14/01/26 | C17: Two account-health tables going dark together is either a broken job or a decommissioned pipeline
A18: 4 | B18: Instrument dormancy, not setup | C18: 'Scheduling enabled' is the visible metric; 'booked in the last 30 days' is the one that matters and is 2.5x smaller
